Workbook

Sheet README
B2: 10-YEAR COMPENSATION COMPARISON — CORRECTED MODEL
B4: Rebuilt from 10_year_Comp_Comparison_Calc.xlsx, tab "CompOffer Comparison".
B6: HOW TO USE
B7: 1. Scenarios tab: set the three growth scenarios. Every lever is editable.
B8: 2. Offer_1 / Offer_2 / Offer_3 / Current_Comp tabs: fill the blue input cells in rows 4-21.
B9: 3. Set the vesting schedules in rows 26-27. Each row must total 100% or the check cell reads ERROR.
B10: 4. Read results on the Comparison tab. Nothing on that tab is an input.
B12: COLOR LEGEND
B13: Blue text = hardcoded input, edit these.
B14: Black text = formula, do not edit.
B15: Green text = link to another tab.
B16: Yellow fill = key assumption.
... B50: The seeded example values in Offer_1 are the Google block from the original workbook.

Sheet Scenarios
A1: GROWTH SCENARIOS
A2: Blue cells are inputs. Every lever below is user-editable.
A3: Lever | C3: Conservative | D3: Medium | E3: Aggressive
A4: Share price appreciation %/yr | C4: 0 | D4: 0.07 | E4: 0.15 | G4: Medium 7%/yr is a long-run broad-market nominal assumption, NOT a forecast for any specific ticker.
A5: Merit increase factor (x offer input) | C5: 0.5 | D5: 1 | E5: 1.5 | G5: Aggressive 15%/yr is a placeholder. Replace with the ticker trailing 5-yr CAGR entered below, and cap it.
A6: Bonus performance multiplier | C6: 0.75 | D6: 1 | E6: 1.25 | G6: Applied to each offer tab merit % input. Conservative halves it; aggressive adds 50%.
A7: Refresher grant growth factor (x offer input) | C7: 0 | D7: 1 | E7: 1 | G7: Applied to bonus target %. Models below-target / at-target / above-target payout.
A8: Number of refresher grant years | C8: 4 | D8: 12 | E8: 12 | G8: Set to 0 in Conservative so refresher grant SIZE does not grow.
G9: Conservative assumes refreshers stop after 4 years. Medium/Aggressive run the full horizon.
A11: TICKER CONTEXT (manual entry — context only, not an input to the model)
A12: Trailing 1-year total return | G12: Past performance does not indicate future results. These cells feed nothing; they exist so the
A13: Trailing 5-year CAGR | G13: appreciation assumption above can be set with the trailing figures visible next to it.
A14: As-of date
A15: Suggested cap on aggressive appreciation | C15: 0.2
A17: Source of all values on this tab: user-entered assumptions. No market data is embedded in this workbook.

Sheet Offer_1
A1: OFFER 1
A2: Blue = you edit. Black = formula, do not edit. Green = link to another tab. Yellow = key assumption.
A3: INPUTS
A4: Company name | B4: Company A
A5: Ticker | B5: TICKA
A6: Start calendar year | B6: 2026
A7: Base salary at start | B7: 200000
A8: Merit increase %/yr | B8: 0.03
A9: Bonus target % of base | B9: 0.22
A10: Bonus basis (Current or Prior) | B10: Current
A11: Bonus paid in Year 1? (Yes/No) | B11: No
A12: Sign-on total | B12: 100000
A13: Sign-on % paid Year 1 | B13: 0.5
A14: Sign-on % paid Year 2 | B14: 0.5
A15: Sign-on % paid Year 3 | B15: 0
A16: Sign-on check (must equal 100%) | B16: =SUM(B13:B15) -> 1 | C16: =IF(ROUND(B16,6)=1,"OK","ERROR - must total 100%") -> OK
A17: Grant-date share price | B17: 150
A18: Initial grant value ($) | B18: 400000
A19: Refresher value, first grant ($) | B19: 150000
A20: First refresher calendar year | B20: 2027
A21: Refresher grant growth %/yr | B21: 0.03
A22: First vest timing (0 = grant year, 1 = year after) | B22: 1
A23: Share price is entered manually. Replace with a market data lookup in the web app. The original workbook vested in the grant year itself (offset 0); real grants usually vest a year later (offset 1).
A24: VESTING SCHEDULES — % of the grant that vests in each year AFTER the grant date
A25: Years after grant | C25: 1 | D25: 2 | E25: 3 | F25: 4 | G25: 5 | H25: 6 | I25: 7 | J25: 8 | K25: Total
A26: Initial grant | C26: 0.4 | D26: 0.28 | E26: 0.2 | F26: 0.12 | G26: 0 | H26: 0 | I26: 0 | J26: 0 | K26: =SUM(C26:J26) -> 1 | L26: =IF(ROUND(K26,6)=1,"OK","ERROR - must total 100%") -> OK
A27: Refresher grants | C27: 0.25 | D27: 0.25 | E27: 0.25 | F27: 0.25 | G27: 0 | H27: 0 | I27: 0 | J27: 0 | K27: =SUM(C27:J27) -> 1 | L27: =IF(ROUND(K27,6)=1,"OK","ERROR - must total 100%") -> OK
A28: Annual granularity. Sub-annual (quarterly/monthly) vesting and cliffs are handled in the web app, not here.
A31: SCENARIO: CONSERVATIVE | B31: =Scenarios!C$3 -> Conservative
A32: Year index | C32: 1 | D32: 2 | E32: 3 | F32: 4 | G32: 5 | H32: 6 | I32: 7 | J32: 8 | K32: 9 | L32: 10 | M32: 11 | N32: 12 | O32: 13 | P32: 14 | Q32: 15
A33: Calendar year | C33: =$B$6 -> 2026 | D33: =C33+1 -> 2027 | E33: =D33+1 -> 2028 | F33: =E33+1 -> 2029 | G33: =F33+1 -> 2030 | H33: =G33+1 -> 2031 | I33: =H33+1 -> 2032 | J33: =I33+1 -> 2033 | K33: =J33+1 -> 2034 | ... Q33: =P33+1 -> 2040
A34: Share price ($) | C34: =$B$17 -> 150 | D34: =C34*(1+Scenarios!$C$4) -> 150 | E34: =D34*(1+Scenarios!$C$4) -> 150 | F34: =E34*(1+Scenarios!$C$4) -> 150 | G34: =F34*(1+Scenarios!$C$4) -> 150 | H34: =G34*(1+Scenarios!$C$4) -> 150 | I34: =H34*(1+Scenarios!$C$4) -> 150 | J34: =I34*(1+Scenarios!$C$4) -> 150 | K34: =J34*(1+Scenarios!$C$4) -> 150 | ... Q34: =P34*(1+Scenarios!$C$4) -> 150
A35: Base salary | C35: =$B$7 -> 200000 | D35: =C35*(1+$B$8*Scenarios!$C$5) -> 203000 | E35: =D35*(1+$B$8*Scenarios!$C$5) -> 206045 | F35: =E35*(1+$B$8*Scenarios!$C$5) -> 209135.67 | G35: =F35*(1+$B$8*Scenarios!$C$5) -> 212272.71 | H35: =G35*(1+$B$8*Scenarios!$C$5) -> 215456.8 | I35: =H35*(1+$B$8*Scenarios!$C$5) -> 218688.65 | J35: =I35*(1+$B$8*Scenarios!$C$5) -> 221968.98 | K35: =J35*(1+$B$8*Scenarios!$C$5) -> 225298.52 | ... Q35: =P35*(1+$B$8*Scenarios!$C$5) -> 246351.15
A36: Bonus basis salary | C36: =IF($B$10="Prior",0,C35) -> 200000 | D36: =IF($B$10="Prior",C35,D35) -> 203000 | E36: =IF($B$10="Prior",D35,E35) -> 206045 | F36: =IF($B$10="Prior",E35,F35) -> 209135.67 | G36: =IF($B$10="Prior",F35,G35) -> 212272.71 | H36: =IF($B$10="Prior",G35,H35) -> 215456.8 | I36: =IF($B$10="Prior",H35,I35) -> 218688.65 | J36: =IF($B$10="Prior",I35,J35) -> 221968.98 | K36: =IF($B$10="Prior",J35,K35) -> 225298.52 | ... Q36: =IF($B$10="Prior",P35,Q35) -> 246351.15
A37: Annual bonus | C37: =IF($B$11="No",0,C36*$B$9*Scenarios!$C$6) -> 0 | D37: =D36*$B$9*Scenarios!$C$6 -> 33495 | E37: =E36*$B$9*Scenarios!$C$6 -> 33997.425 | F37: =F36*$B$9*Scenarios!$C$6 -> 34507.386 | G37: =G36*$B$9*Scenarios!$C$6 -> 35024.997 | H37: =H36*$B$9*Scenarios!$C$6 -> 35550.372 | I37: =I36*$B$9*Scenarios!$C$6 -> 36083.628 | J37: =J36*$B$9*Scenarios!$C$6 -> 36624.882 | K37: =K36*$B$9*Scenarios!$C$6 -> 37174.255 | ... Q37: =Q36*$B$9*Scenarios!$C$6 -> 40647.939
A38: Sign-on paid | C38: =$B$12*$B$13 -> 50000 | D38: =$B$12*$B$14 -> 50000 | E38: =$B$12*$B$15 -> 0 | F38: 0 | G38: 0 | H38: 0 | I38: 0 | J38: 0 | K38: 0 | L38: 0 | M38: 0 | N38: 0 | O38: 0 | P38: 0 | Q38: 0
A40: GRANT LEDGER — dollar value vesting each year, one row per grant | S40: Grant year | T40: Grant value ($) | U40: Shares granted | V40: Shares vested in horizon | W40: Unvested shares
A41: Initial grant | C41: =IF(AND(C$33-$S41+1-$B$22>=1,C$33-$S41+1-$B$22<=8),INDEX($C$26:$J$26,1,C$33-$S41+1-$B$22),0)*$U41*C$34 -> 0 | D41: =IF(AND(D$33-$S41+1-$B$22>=1,D$33-$S41+1-$B$22<=8),INDEX($C$26:$J$26,1,D$33-$S41+1-$B$22),0)*$U41*D$34 -> 160000 | E41: =IF(AND(E$33-$S41+1-$B$22>=1,E$33-$S41+1-$B$22<=8),INDEX($C$26:$J$26,1,E$33-$S41+1-$B$22),0)*$U41*E$34 -> 112000 | F41: =IF(AND(F$33-$S41+1-$B$22>=1,F$33-$S41+1-$B$22<=8),INDEX($C$26:$J$26,1,F$33-$S41+1-$B$22),0)*$U41*F$34 -> 80000 | G41: =IF(AND(G$33-$S41+1-$B$22>=1,G$33-$S41+1-$B$22<=8),INDEX($C$26:$J$26,1,G$33-$S41+1-$B$22),0)*$U41*G$34 -> 48000 | H41: =IF(AND(H$33-$S41+1-$B$22>=1,H$33-$S41+1-$B$22<=8),INDEX($C$26:$J$26,1,H$33-$S41+1-$B$22),0)*$U41*H$34 -> 0 | I41: =IF(AND(I$33-$S41+1-$B$22>=1,I$33-$S41+1-$B$22<=8),INDEX($C$26:$J$26,1,I$33-$S41+1-$B$22),0)*$U41*I$34 -> 0 | J41: =IF(AND(J$33-$S41+1-$B$22>=1,J$33-$S41+1-$B$22<=8),INDEX($C$26:$J$26,1,J$33-$S41+1-$B$22),0)*$U41*J$34 -> 0 | ... Q41: =IF(AND(Q$33-$S41+1-$B$22>=1,Q$33-$S41+1-$B$22<=8),INDEX($C$26:$J$26,1,Q$33-$S41+1-$B$22),0)*$U41*Q$34 -> 0 | S41: =$B$6 -> 2026 | T41: =$B$18 -> 400000 | U41: =IFERROR(T41/$B$17,0) -> 2666.6667 | V41: =SUMPRODUCT(($C$25:$J$25<=$Q$33-$S41+1-$B$22)*$C$26:$J$26)*$U41 -> 2666.6667 | W41: =$U41-$V41 -> 0
A42: Refresher grant 1 | C42: =IF(AND(C$33-$S42+1-$B$22>=1,C$33-$S42+1-$B$22<=8),INDEX($C$27:$J$27,1,C$33-$S42+1-$B$22),0)*$U42*C$34 -> 0 | D42: =IF(AND(D$33-$S42+1-$B$22>=1,D$33-$S42+1-$B$22<=8),INDEX($C$27:$J$27,1,D$33-$S42+1-$B$22),0)*$U42*D$34 -> 0 | E42: =IF(AND(E$33-$S42+1-$B$22>=1,E$33-$S42+1-$B$22<=8),INDEX($C$27:$J$27,1,E$33-$S42+1-$B$22),0)*$U42*E$34 -> 37500 | F42: =IF(AND(F$33-$S42+1-$B$22>=1,F$33-$S42+1-$B$22<=8),INDEX($C$27:$J$27,1,F$33-$S42+1-$B$22),0)*$U42*F$34 -> 37500 | G42: =IF(AND(G$33-$S42+1-$B$22>=1,G$33-$S42+1-$B$22<=8),INDEX($C$27:$J$27,1,G$33-$S42+1-$B$22),0)*$U42*G$34 -> 37500 | H42: =IF(AND(H$33-$S42+1-$B$22>=1,H$33-$S42+1-$B$22<=8),INDEX($C$27:$J$27,1,H$33-$S42+1-$B$22),0)*$U42*H$34 -> 37500 | I42: =IF(AND(I$33-$S42+1-$B$22>=1,I$33-$S42+1-$B$22<=8),INDEX($C$27:$J$27,1,I$33-$S42+1-$B$22),0)*$U42*I$34 -> 0 | J42: =IF(AND(J$33-$S42+1-$B$22>=1,J$33-$S42+1-$B$22<=8),INDEX($C$27:$J$27,1,J$33-$S42+1-$B$22),0)*$U42*J$34 -> 0 | ... Q42: =IF(AND(Q$33-$S42+1-$B$22>=1,Q$33-$S42+1-$B$22<=8),INDEX($C$27:$J$27,1,Q$33-$S42+1-$B$22),0)*$U42*Q$34 -> 0 | S42: =$B$20+0 -> 2027 | T42: =IF($S42>$B$20+Scenarios!$C$8-1,0,$B$19*(1+$B$21*Scenarios!$C$7)^0) -> 150000 | U42: =IFERROR($T42/INDEX($C$34:$Q$34,1,MATCH($S42,$C$33:$Q$33,0)),0) -> 1000 | V42: =SUMPRODUCT(($C$25:$J$25<=$Q$33-$S42+1-$B$22)*$C$27:$J$27)*$U42 -> 1000 | W42: =$U42-$V42 -> 0
A43: Refresher grant 2 | C43: =IF(AND(C$33-$S43+1-$B$22>=1,C$33-$S43+1-$B$22<=8),INDEX($C$27:$J$27,1,C$33-$S43+1-$B$22),0)*$U43*C$34 -> 0 | D43: =IF(AND(D$33-$S43+1-$B$22>=1,D$33-$S43+1-$B$22<=8),INDEX($C$27:$J$27,1,D$33-$S43+1-$B$22),0)*$U43*D$34 -> 0 | E43: =IF(AND(E$33-$S43+1-$B$22>=1,E$33-$S43+1-$B$22<=8),INDEX($C$27:$J$27,1,E$33-$S43+1-$B$22),0)*$U43*E$34 -> 0 | F43: =IF(AND(F$33-$S43+1-$B$22>=1,F$33-$S43+1-$B$22<=8),INDEX($C$27:$J$27,1,F$33-$S43+1-$B$22),0)*$U43*F$34 -> 37500 | G43: =IF(AND(G$33-$S43+1-$B$22>=1,G$33-$S43+1-$B$22<=8),INDEX($C$27:$J$27,1,G$33-$S43+1-$B$22),0)*$U43*G$34 -> 37500 | H43: =IF(AND(H$33-$S43+1-$B$22>=1,H$33-$S43+1-$B$22<=8),INDEX($C$27:$J$27,1,H$33-$S43+1-$B$22),0)*$U43*H$34 -> 37500 | I43: =IF(AND(I$33-$S43+1-$B$22>=1,I$33-$S43+1-$B$22<=8),INDEX($C$27:$J$27,1,I$33-$S43+1-$B$22),0)*$U43*I$34 -> 37500 | J43: =IF(AND(J$33-$S43+1-$B$22>=1,J$33-$S43+1-$B$22<=8),INDEX($C$27:$J$27,1,J$33-$S43+1-$B$22),0)*$U43*J$34 -> 0 | ... Q43: =IF(AND(Q$33-$S43+1-$B$22>=1,Q$33-$S43+1-$B$22<=8),INDEX($C$27:$J$27,1,Q$33-$S43+1-$B$22),0)*$U43*Q$34 -> 0 | S43: =$B$20+1 -> 2028 | T43: =IF($S43>$B$20+Scenarios!$C$8-1,0,$B$19*(1+$B$21*Scenarios!$C$7)^1) -> 150000 | U43: =IFERROR($T43/INDEX($C$34:$Q$34,1,MATCH($S43,$C$33:$Q$33,0)),0) -> 1000 | V43: =SUMPRODUCT(($C$25:$J$25<=$Q$33-$S43+1-$B$22)*$C$27:$J$27)*$U43 -> 1000 | W43: =$U43-$V43 -> 0
A44: Refresher grant 3 | C44: =IF(AND(C$33-$S44+1-$B$22>=1,C$33-$S44+1-$B$22<=8),INDEX($C$27:$J$27,1,C$33-$S44+1-$B$22),0)*$U44*C$34 -> 0 | D44: =IF(AND(D$33-$S44+1-$B$22>=1,D$33-$S44+1-$B$22<=8),INDEX($C$27:$J$27,1,D$33-$S44+1-$B$22),0)*$U44*D$34 -> 0 | E44: =IF(AND(E$33-$S44+1-$B$22>=1,E$33-$S44+1-$B$22<=8),INDEX($C$27:$J$27,1,E$33-$S44+1-$B$22),0)*$U44*E$34 -> 0 | F44: =IF(AND(F$33-$S44+1-$B$22>=1,F$33-$S44+1-$B$22<=8),INDEX($C$27:$J$27,1,F$33-$S44+1-$B$22),0)*$U44*F$34 -> 0 | G44: =IF(AND(G$33-$S44+1-$B$22>=1,G$33-$S44+1-$B$22<=8),INDEX($C$27:$J$27,1,G$33-$S44+1-$B$22),0)*$U44*G$34 -> 37500 | H44: =IF(AND(H$33-$S44+1-$B$22>=1,H$33-$S44+1-$B$22<=8),INDEX($C$27:$J$27,1,H$33-$S44+1-$B$22),0)*$U44*H$34 -> 37500 | I44: =IF(AND(I$33-$S44+1-$B$22>=1,I$33-$S44+1-$B$22<=8),INDEX($C$27:$J$27,1,I$33-$S44+1-$B$22),0)*$U44*I$34 -> 37500 | J44: =IF(AND(J$33-$S44+1-$B$22>=1,J$33-$S44+1-$B$22<=8),INDEX($C$27:$J$27,1,J$33-$S44+1-$B$22),0)*$U44*J$34 -> 37500 | ... Q44: =IF(AND(Q$33-$S44+1-$B$22>=1,Q$33-$S44+1-$B$22<=8),INDEX($C$27:$J$27,1,Q$33-$S44+1-$B$22),0)*$U44*Q$34 -> 0 | S44: =$B$20+2 -> 2029 | T44: =IF($S44>$B$20+Scenarios!$C$8-1,0,$B$19*(1+$B$21*Scenarios!$C$7)^2) -> 150000 | U44: =IFERROR($T44/INDEX($C$34:$Q$34,1,MATCH($S44,$C$33:$Q$33,0)),0) -> 1000 | V44: =SUMPRODUCT(($C$25:$J$25<=$Q$33-$S44+1-$B$22)*$C$27:$J$27)*$U44 -> 1000 | W44: =$U44-$V44 -> 0
A45: Refresher grant 4 | C45: =IF(AND(C$33-$S45+1-$B$22>=1,C$33-$S45+1-$B$22<=8),INDEX($C$27:$J$27,1,C$33-$S45+1-$B$22),0)*$U45*C$34 -> 0 | D45: =IF(AND(D$33-$S45+1-$B$22>=1,D$33-$S45+1-$B$22<=8),INDEX($C$27:$J$27,1,D$33-$S45+1-$B$22),0)*$U45*D$34 -> 0 | E45: =IF(AND(E$33-$S45+1-$B$22>=1,E$33-$S45+1-$B$22<=8),INDEX($C$27:$J$27,1,E$33-$S45+1-$B$22),0)*$U45*E$34 -> 0 | F45: =IF(AND(F$33-$S45+1-$B$22>=1,F$33-$S45+1-$B$22<=8),INDEX($C$27:$J$27,1,F$33-$S45+1-$B$22),0)*$U45*F$34 -> 0 | G45: =IF(AND(G$33-$S45+1-$B$22>=1,G$33-$S45+1-$B$22<=8),INDEX($C$27:$J$27,1,G$33-$S45+1-$B$22),0)*$U45*G$34 -> 0 | H45: =IF(AND(H$33-$S45+1-$B$22>=1,H$33-$S45+1-$B$22<=8),INDEX($C$27:$J$27,1,H$33-$S45+1-$B$22),0)*$U45*H$34 -> 37500 | I45: =IF(AND(I$33-$S45+1-$B$22>=1,I$33-$S45+1-$B$22<=8),INDEX($C$27:$J$27,1,I$33-$S45+1-$B$22),0)*$U45*I$34 -> 37500 | J45: =IF(AND(J$33-$S45+1-$B$22>=1,J$33-$S45+1-$B$22<=8),INDEX($C$27:$J$27,1,J$33-$S45+1-$B$22),0)*$U45*J$34 -> 37500 | ... Q45: =IF(AND(Q$33-$S45+1-$B$22>=1,Q$33-$S45+1-$B$22<=8),INDEX($C$27:$J$27,1,Q$33-$S45+1-$B$22),0)*$U45*Q$34 -> 0 | S45: =$B$20+3 -> 2030 | T45: =IF($S45>$B$20+Scenarios!$C$8-1,0,$B$19*(1+$B$21*Scenarios!$C$7)^3) -> 150000 | U45: =IFERROR($T45/INDEX($C$34:$Q$34,1,MATCH($S45,$C$33:$Q$33,0)),0) -> 1000 | V45: =SUMPRODUCT(($C$25:$J$25<=$Q$33-$S45+1-$B$22)*$C$27:$J$27)*$U45 -> 1000 | W45: =$U45-$V45 -> 0
A46: Refresher grant 5 | C46: =IF(AND(C$33-$S46+1-$B$22>=1,C$33-$S46+1-$B$22<=8),INDEX($C$27:$J$27,1,C$33-$S46+1-$B$22),0)*$U46*C$34 -> 0 | D46: =IF(AND(D$33-$S46+1-$B$22>=1,D$33-$S46+1-$B$22<=8),INDEX($C$27:$J$27,1,D$33-$S46+1-$B$22),0)*$U46*D$34 -> 0 | E46: =IF(AND(E$33-$S46+1-$B$22>=1,E$33-$S46+1-$B$22<=8),INDEX($C$27:$J$27,1,E$33-$S46+1-$B$22),0)*$U46*E$34 -> 0 | F46: =IF(AND(F$33-$S46+1-$B$22>=1,F$33-$S46+1-$B$22<=8),INDEX($C$27:$J$27,1,F$33-$S46+1-$B$22),0)*$U46*F$34 -> 0 | G46: =IF(AND(G$33-$S46+1-$B$22>=1,G$33-$S46+1-$B$22<=8),INDEX($C$27:$J$27,1,G$33-$S46+1-$B$22),0)*$U46*G$34 -> 0 | H46: =IF(AND(H$33-$S46+1-$B$22>=1,H$33-$S46+1-$B$22<=8),INDEX($C$27:$J$27,1,H$33-$S46+1-$B$22),0)*$U46*H$34 -> 0 | I46: =IF(AND(I$33-$S46+1-$B$22>=1,I$33-$S46+1-$B$22<=8),INDEX($C$27:$J$27,1,I$33-$S46+1-$B$22),0)*$U46*I$34 -> 0 | J46: =IF(AND(J$33-$S46+1-$B$22>=1,J$33-$S46+1-$B$22<=8),INDEX($C$27:$J$27,1,J$33-$S46+1-$B$22),0)*$U46*J$34 -> 0 | ... Q46: =IF(AND(Q$33-$S46+1-$B$22>=1,Q$33-$S46+1-$B$22<=8),INDEX($C$27:$J$27,1,Q$33-$S46+1-$B$22),0)*$U46*Q$34 -> 0 | S46: =$B$20+4 -> 2031 | T46: =IF($S46>$B$20+Scenarios!$C$8-1,0,$B$19*(1+$B$21*Scenarios!$C$7)^4) -> 0 | U46: =IFERROR($T46/INDEX($C$34:$Q$34,1,MATCH($S46,$C$33:$Q$33,0)),0) -> 0 | V46: =SUMPRODUCT(($C$25:$J$25<=$Q$33-$S46+1-$B$22)*$C$27:$J$27)*$U46 -> 0 | W46: =$U46-$V46 -> 0
A47: Refresher grant 6 | C47: =IF(AND(C$33-$S47+1-$B$22>=1,C$33-$S47+1-$B$22<=8),INDEX($C$27:$J$27,1,C$33-$S47+1-$B$22),0)*$U47*C$34 -> 0 | D47: =IF(AND(D$33-$S47+1-$B$22>=1,D$33-$S47+1-$B$22<=8),INDEX($C$27:$J$27,1,D$33-$S47+1-$B$22),0)*$U47*D$34 -> 0 | E47: =IF(AND(E$33-$S47+1-$B$22>=1,E$33-$S47+1-$B$22<=8),INDEX($C$27:$J$27,1,E$33-$S47+1-$B$22),0)*$U47*E$34 -> 0 | F47: =IF(AND(F$33-$S47+1-$B$22>=1,F$33-$S47+1-$B$22<=8),INDEX($C$27:$J$27,1,F$33-$S47+1-$B$22),0)*$U47*F$34 -> 0 | G47: =IF(AND(G$33-$S47+1-$B$22>=1,G$33-$S47+1-$B$22<=8),INDEX($C$27:$J$27,1,G$33-$S47+1-$B$22),0)*$U47*G$34 -> 0 | H47: =IF(AND(H$33-$S47+1-$B$22>=1,H$33-$S47+1-$B$22<=8),INDEX($C$27:$J$27,1,H$33-$S47+1-$B$22),0)*$U47*H$34 -> 0 | I47: =IF(AND(I$33-$S47+1-$B$22>=1,I$33-$S47+1-$B$22<=8),INDEX($C$27:$J$27,1,I$33-$S47+1-$B$22),0)*$U47*I$34 -> 0 | J47: =IF(AND(J$33-$S47+1-$B$22>=1,J$33-$S47+1-$B$22<=8),INDEX($C$27:$J$27,1,J$33-$S47+1-$B$22),0)*$U47*J$34 -> 0 | ... Q47: =IF(AND(Q$33-$S47+1-$B$22>=1,Q$33-$S47+1-$B$22<=8),INDEX($C$27:$J$27,1,Q$33-$S47+1-$B$22),0)*$U47*Q$34 -> 0 | S47: =$B$20+5 -> 2032 | T47: =IF($S47>$B$20+Scenarios!$C$8-1,0,$B$19*(1+$B$21*Scenarios!$C$7)^5) -> 0 | U47: =IFERROR($T47/INDEX($C$34:$Q$34,1,MATCH($S47,$C$33:$Q$33,0)),0) -> 0 | V47: =SUMPRODUCT(($C$25:$J$25<=$Q$33-$S47+1-$B$22)*$C$27:$J$27)*$U47 -> 0 | W47: =$U47-$V47 -> 0
A48: Refresher grant 7 | C48: =IF(AND(C$33-$S48+1-$B$22>=1,C$33-$S48+1-$B$22<=8),INDEX($C$27:$J$27,1,C$33-$S48+1-$B$22),0)*$U48*C$34 -> 0 | D48: =IF(AND(D$33-$S48+1-$B$22>=1,D$33-$S48+1-$B$22<=8),INDEX($C$27:$J$27,1,D$33-$S48+1-$B$22),0)*$U48*D$34 -> 0 | E48: =IF(AND(E$33-$S48+1-$B$22>=1,E$33-$S48+1-$B$22<=8),INDEX($C$27:$J$27,1,E$33-$S48+1-$B$22),0)*$U48*E$34 -> 0 | F48: =IF(AND(F$33-$S48+1-$B$22>=1,F$33-$S48+1-$B$22<=8),INDEX($C$27:$J$27,1,F$33-$S48+1-$B$22),0)*$U48*F$34 -> 0 | G48: =IF(AND(G$33-$S48+1-$B$22>=1,G$33-$S48+1-$B$22<=8),INDEX($C$27:$J$27,1,G$33-$S48+1-$B$22),0)*$U48*G$34 -> 0 | H48: =IF(AND(H$33-$S48+1-$B$22>=1,H$33-$S48+1-$B$22<=8),INDEX($C$27:$J$27,1,H$33-$S48+1-$B$22),0)*$U48*H$34 -> 0 | I48: =IF(AND(I$33-$S48+1-$B$22>=1,I$33-$S48+1-$B$22<=8),INDEX($C$27:$J$27,1,I$33-$S48+1-$B$22),0)*$U48*I$34 -> 0 | J48: =IF(AND(J$33-$S48+1-$B$22>=1,J$33-$S48+1-$B$22<=8),INDEX($C$27:$J$27,1,J$33-$S48+1-$B$22),0)*$U48*J$34 -> 0 | ... Q48: =IF(AND(Q$33-$S48+1-$B$22>=1,Q$33-$S48+1-$B$22<=8),INDEX($C$27:$J$27,1,Q$33-$S48+1-$B$22),0)*$U48*Q$34 -> 0 | S48: =$B$20+6 -> 2033 | T48: =IF($S48>$B$20+Scenarios!$C$8-1,0,$B$19*(1+$B$21*Scenarios!$C$7)^6) -> 0 | U48: =IFERROR($T48/INDEX($C$34:$Q$34,1,MATCH($S48,$C$33:$Q$33,0)),0) -> 0 | V48: =SUMPRODUCT(($C$25:$J$25<=$Q$33-$S48+1-$B$22)*$C$27:$J$27)*$U48 -> 0 | W48: =$U48-$V48 -> 0
A49: Refresher grant 8 | C49: =IF(AND(C$33-$S49+1-$B$22>=1,C$33-$S49+1-$B$22<=8),INDEX($C$27:$J$27,1,C$33-$S49+1-$B$22),0)*$U49*C$34 -> 0 | D49: =IF(AND(D$33-$S49+1-$B$22>=1,D$33-$S49+1-$B$22<=8),INDEX($C$27:$J$27,1,D$33-$S49+1-$B$22),0)*$U49*D$34 -> 0 | E49: =IF(AND(E$33-$S49+1-$B$22>=1,E$33-$S49+1-$B$22<=8),INDEX($C$27:$J$27,1,E$33-$S49+1-$B$22),0)*$U49*E$34 -> 0 | F49: =IF(AND(F$33-$S49+1-$B$22>=1,F$33-$S49+1-$B$22<=8),INDEX($C$27:$J$27,1,F$33-$S49+1-$B$22),0)*$U49*F$34 -> 0 | G49: =IF(AND(G$33-$S49+1-$B$22>=1,G$33-$S49+1-$B$22<=8),INDEX($C$27:$J$27,1,G$33-$S49+1-$B$22),0)*$U49*G$34 -> 0 | H49: =IF(AND(H$33-$S49+1-$B$22>=1,H$33-$S49+1-$B$22<=8),INDEX($C$27:$J$27,1,H$33-$S49+1-$B$22),0)*$U49*H$34 -> 0 | I49: =IF(AND(I$33-$S49+1-$B$22>=1,I$33-$S49+1-$B$22<=8),INDEX($C$27:$J$27,1,I$33-$S49+1-$B$22),0)*$U49*I$34 -> 0 | J49: =IF(AND(J$33-$S49+1-$B$22>=1,J$33-$S49+1-$B$22<=8),INDEX($C$27:$J$27,1,J$33-$S49+1-$B$22),0)*$U49*J$34 -> 0 | ... Q49: =IF(AND(Q$33-$S49+1-$B$22>=1,Q$33-$S49+1-$B$22<=8),INDEX($C$27:$J$27,1,Q$33-$S49+1-$B$22),0)*$U49*Q$34 -> 0 | S49: =$B$20+7 -> 2034 | T49: =IF($S49>$B$20+Scenarios!$C$8-1,0,$B$19*(1+$B$21*Scenarios!$C$7)^7) -> 0 | U49: =IFERROR($T49/INDEX($C$34:$Q$34,1,MATCH($S49,$C$33:$Q$33,0)),0) -> 0 | V49: =SUMPRODUCT(($C$25:$J$25<=$Q$33-$S49+1-$B$22)*$C$27:$J$27)*$U49 -> 0 | W49: =$U49-$V49 -> 0
A50: Refresher grant 9 | C50: =IF(AND(C$33-$S50+1-$B$22>=1,C$33-$S50+1-$B$22<=8),INDEX($C$27:$J$27,1,C$33-$S50+1-$B$22),0)*$U50*C$34 -> 0 | D50: =IF(AND(D$33-$S50+1-$B$22>=1,D$33-$S50+1-$B$22<=8),INDEX($C$27:$J$27,1,D$33-$S50+1-$B$22),0)*$U50*D$34 -> 0 | E50: =IF(AND(E$33-$S50+1-$B$22>=1,E$33-$S50+1-$B$22<=8),INDEX($C$27:$J$27,1,E$33-$S50+1-$B$22),0)*$U50*E$34 -> 0 | F50: =IF(AND(F$33-$S50+1-$B$22>=1,F$33-$S50+1-$B$22<=8),INDEX($C$27:$J$27,1,F$33-$S50+1-$B$22),0)*$U50*F$34 -> 0 | G50: =IF(AND(G$33-$S50+1-$B$22>=1,G$33-$S50+1-$B$22<=8),INDEX($C$27:$J$27,1,G$33-$S50+1-$B$22),0)*$U50*G$34 -> 0 | H50: =IF(AND(H$33-$S50+1-$B$22>=1,H$33-$S50+1-$B$22<=8),INDEX($C$27:$J$27,1,H$33-$S50+1-$B$22),0)*$U50*H$34 -> 0 | I50: =IF(AND(I$33-$S50+1-$B$22>=1,I$33-$S50+1-$B$22<=8),INDEX($C$27:$J$27,1,I$33-$S50+1-$B$22),0)*$U50*I$34 -> 0 | J50: =IF(AND(J$33-$S50+1-$B$22>=1,J$33-$S50+1-$B$22<=8),INDEX($C$27:$J$27,1,J$33-$S50+1-$B$22),0)*$U50*J$34 -> 0 | ... Q50: =IF(AND(Q$33-$S50+1-$B$22>=1,Q$33-$S50+1-$B$22<=8),INDEX($C$27:$J$27,1,Q$33-$S50+1-$B$22),0)*$U50*Q$34 -> 0 | S50: =$B$20+8 -> 2035 | T50: =IF($S50>$B$20+Scenarios!$C$8-1,0,$B$19*(1+$B$21*Scenarios!$C$7)^8) -> 0 | U50: =IFERROR($T50/INDEX($C$34:$Q$34,1,MATCH($S50,$C$33:$Q$33,0)),0) -> 0 | V50: =SUMPRODUCT(($C$25:$J$25<=$Q$33-$S50+1-$B$22)*$C$27:$J$27)*$U50 -> 0 | W50: =$U50-$V50 -> 0
A51: Refresher grant 10 | C51: =IF(AND(C$33-$S51+1-$B$22>=1,C$33-$S51+1-$B$22<=8),INDEX($C$27:$J$27,1,C$33-$S51+1-$B$22),0)*$U51*C$34 -> 0 | D51: =IF(AND(D$33-$S51+1-$B$22>=1,D$33-$S51+1-$B$22<=8),INDEX($C$27:$J$27,1,D$33-$S51+1-$B$22),0)*$U51*D$34 -> 0 | E51: =IF(AND(E$33-$S51+1-$B$22>=1,E$33-$S51+1-$B$22<=8),INDEX($C$27:$J$27,1,E$33-$S51+1-$B$22),0)*$U51*E$34 -> 0 | F51: =IF(AND(F$33-$S51+1-$B$22>=1,F$33-$S51+1-$B$22<=8),INDEX($C$27:$J$27,1,F$33-$S51+1-$B$22),0)*$U51*F$34 -> 0 | G51: =IF(AND(G$33-$S51+1-$B$22>=1,G$33-$S51+1-$B$22<=8),INDEX($C$27:$J$27,1,G$33-$S51+1-$B$22),0)*$U51*G$34 -> 0 | H51: =IF(AND(H$33-$S51+1-$B$22>=1,H$33-$S51+1-$B$22<=8),INDEX($C$27:$J$27,1,H$33-$S51+1-$B$22),0)*$U51*H$34 -> 0 | I51: =IF(AND(I$33-$S51+1-$B$22>=1,I$33-$S51+1-$B$22<=8),INDEX($C$27:$J$27,1,I$33-$S51+1-$B$22),0)*$U51*I$34 -> 0 | J51: =IF(AND(J$33-$S51+1-$B$22>=1,J$33-$S51+1-$B$22<=8),INDEX($C$27:$J$27,1,J$33-$S51+1-$B$22),0)*$U51*J$34 -> 0 | ... Q51: =IF(AND(Q$33-$S51+1-$B$22>=1,Q$33-$S51+1-$B$22<=8),INDEX($C$27:$J$27,1,Q$33-$S51+1-$B$22),0)*$U51*Q$34 -> 0 | S51: =$B$20+9 -> 2036 | T51: =IF($S51>$B$20+Scenarios!$C$8-1,0,$B$19*(1+$B$21*Scenarios!$C$7)^9) -> 0 | U51: =IFERROR($T51/INDEX($C$34:$Q$34,1,MATCH($S51,$C$33:$Q$33,0)),0) -> 0 | V51: =SUMPRODUCT(($C$25:$J$25<=$Q$33-$S51+1-$B$22)*$C$27:$J$27)*$U51 -> 0 | W51: =$U51-$V51 -> 0
A52: Refresher grant 11 | C52: =IF(AND(C$33-$S52+1-$B$22>=1,C$33-$S52+1-$B$22<=8),INDEX($C$27:$J$27,1,C$33-$S52+1-$B$22),0)*$U52*C$34 -> 0 | D52: =IF(AND(D$33-$S52+1-$B$22>=1,D$33-$S52+1-$B$22<=8),INDEX($C$27:$J$27,1,D$33-$S52+1-$B$22),0)*$U52*D$34 -> 0 | E52: =IF(AND(E$33-$S52+1-$B$22>=1,E$33-$S52+1-$B$22<=8),INDEX($C$27:$J$27,1,E$33-$S52+1-$B$22),0)*$U52*E$34 -> 0 | F52: =IF(AND(F$33-$S52+1-$B$22>=1,F$33-$S52+1-$B$22<=8),INDEX($C$27:$J$27,1,F$33-$S52+1-$B$22),0)*$U52*F$34 -> 0 | G52: =IF(AND(G$33-$S52+1-$B$22>=1,G$33-$S52+1-$B$22<=8),INDEX($C$27:$J$27,1,G$33-$S52+1-$B$22),0)*$U52*G$34 -> 0 | H52: =IF(AND(H$33-$S52+1-$B$22>=1,H$33-$S52+1-$B$22<=8),INDEX($C$27:$J$27,1,H$33-$S52+1-$B$22),0)*$U52*H$34 -> 0 | I52: =IF(AND(I$33-$S52+1-$B$22>=1,I$33-$S52+1-$B$22<=8),INDEX($C$27:$J$27,1,I$33-$S52+1-$B$22),0)*$U52*I$34 -> 0 | J52: =IF(AND(J$33-$S52+1-$B$22>=1,J$33-$S52+1-$B$22<=8),INDEX($C$27:$J$27,1,J$33-$S52+1-$B$22),0)*$U52*J$34 -> 0 | ... Q52: =IF(AND(Q$33-$S52+1-$B$22>=1,Q$33-$S52+1-$B$22<=8),INDEX($C$27:$J$27,1,Q$33-$S52+1-$B$22),0)*$U52*Q$34 -> 0 | S52: =$B$20+10 -> 2037 | T52: =IF($S52>$B$20+Scenarios!$C$8-1,0,$B$19*(1+$B$21*Scenarios!$C$7)^10) -> 0 | U52: =IFERROR($T52/INDEX($C$34:$Q$34,1,MATCH($S52,$C$33:$Q$33,0)),0) -> 0 | V52: =SUMPRODUCT(($C$25:$J$25<=$Q$33-$S52+1-$B$22)*$C$27:$J$27)*$U52 -> 0 | W52: =$U52-$V52 -> 0
A53: Refresher grant 12 | C53: =IF(AND(C$33-$S53+1-$B$22>=1,C$33-$S53+1-$B$22<=8),INDEX($C$27:$J$27,1,C$33-$S53+1-$B$22),0)*$U53*C$34 -> 0 | D53: =IF(AND(D$33-$S53+1-$B$22>=1,D$33-$S53+1-$B$22<=8),INDEX($C$27:$J$27,1,D$33-$S53+1-$B$22),0)*$U53*D$34 -> 0 | E53: =IF(AND(E$33-$S53+1-$B$22>=1,E$33-$S53+1-$B$22<=8),INDEX($C$27:$J$27,1,E$33-$S53+1-$B$22),0)*$U53*E$34 -> 0 | F53: =IF(AND(F$33-$S53+1-$B$22>=1,F$33-$S53+1-$B$22<=8),INDEX($C$27:$J$27,1,F$33-$S53+1-$B$22),0)*$U53*F$34 -> 0 | G53: =IF(AND(G$33-$S53+1-$B$22>=1,G$33-$S53+1-$B$22<=8),INDEX($C$27:$J$27,1,G$33-$S53+1-$B$22),0)*$U53*G$34 -> 0 | H53: =IF(AND(H$33-$S53+1-$B$22>=1,H$33-$S53+1-$B$22<=8),INDEX($C$27:$J$27,1,H$33-$S53+1-$B$22),0)*$U53*H$34 -> 0 | I53: =IF(AND(I$33-$S53+1-$B$22>=1,I$33-$S53+1-$B$22<=8),INDEX($C$27:$J$27,1,I$33-$S53+1-$B$22),0)*$U53*I$34 -> 0 | J53: =IF(AND(J$33-$S53+1-$B$22>=1,J$33-$S53+1-$B$22<=8),INDEX($C$27:$J$27,1,J$33-$S53+1-$B$22),0)*$U53*J$34 -> 0 | ... Q53: =IF(AND(Q$33-$S53+1-$B$22>=1,Q$33-$S53+1-$B$22<=8),INDEX($C$27:$J$27,1,Q$33-$S53+1-$B$22),0)*$U53*Q$34 -> 0 | S53: =$B$20+11 -> 2038 | T53: =IF($S53>$B$20+Scenarios!$C$8-1,0,$B$19*(1+$B$21*Scenarios!$C$7)^11) -> 0 | U53: =IFERROR($T53/INDEX($C$34:$Q$34,1,MATCH($S53,$C$33:$Q$33,0)),0) -> 0 | V53: =SUMPRODUCT(($C$25:$J$25<=$Q$33-$S53+1-$B$22)*$C$27:$J$27)*$U53 -> 0 | W53: =$U53-$V53 -> 0
A55: Initial grant vest ($) | C55: =C41 -> 0 | D55: =D41 -> 160000 | E55: =E41 -> 112000 | F55: =F41 -> 80000 | G55: =G41 -> 48000 | H55: =H41 -> 0 | I55: =I41 -> 0 | J55: =J41 -> 0 | ... Q55: =Q41 -> 0
A56: Refresher vest ($) | C56: =SUM(C42:C53) -> 0 | D56: =SUM(D42:D53) -> 0 | E56: =SUM(E42:E53) -> 37500 | F56: =SUM(F42:F53) -> 75000 | G56: =SUM(G42:G53) -> 112500 | H56: =SUM(H42:H53) -> 150000 | I56: =SUM(I42:I53) -> 112500 | J56: =SUM(J42:J53) -> 75000 | ... Q56: =SUM(Q42:Q53) -> 0
A57: Total equity vest ($) | C57: =C55+C56 -> 0 | D57: =D55+D56 -> 160000 | E57: =E55+E56 -> 149500 | F57: =F55+F56 -> 155000 | G57: =G55+G56 -> 160500 | H57: =H55+H56 -> 150000 | I57: =I55+I56 -> 112500 | J57: =J55+J56 -> 75000 | ... Q57: =Q55+Q56 -> 0
A58: Concurrent grants vesting (count) | C58: =SUMPRODUCT((C41:C53>0)*1) -> 0 | D58: =SUMPRODUCT((D41:D53>0)*1) -> 1 | E58: =SUMPRODUCT((E41:E53>0)*1) -> 2 | F58: =SUMPRODUCT((F41:F53>0)*1) -> 3 | G58: =SUMPRODUCT((G41:G53>0)*1) -> 4 | H58: =SUMPRODUCT((H41:H53>0)*1) -> 4 | I58: =SUMPRODUCT((I41:I53>0)*1) -> 3 | J58: =SUMPRODUCT((J41:J53>0)*1) -> 2 | ... Q58: =SUMPRODUCT((Q41:Q53>0)*1) -> 0
A60: TOTAL GROSS COMPENSATION | C60: =C35+C37+C38+C57 -> 250000 | D60: =D35+D37+D38+D57 -> 446495 | E60: =E35+E37+E38+E57 -> 389542.42 | F60: =F35+F37+F38+F57 -> 398643.06 | G60: =G35+G37+G38+G57 -> 407797.71 | H60: =H35+H37+H38+H57 -> 401007.17 | I60: =I35+I37+I38+I57 -> 367272.28 | J60: =J35+J37+J38+J57 -> 333593.86 | ... Q60: =Q35+Q37+Q38+Q57 -> 286999.09
A61: Cumulative gross | C61: =C60 -> 250000 | D61: =C61+D60 -> 696495 | E61: =D61+E60 -> 1086037.4 | F61: =E61+F60 -> 1484680.5 | G61: =F61+G60 -> 1892478.2 | H61: =G61+H60 -> 2293485.4 | I61: =H61+I60 -> 2660757.6 | J61: =I61+J60 -> 2994351.5 | K61: =J61+K60 -> 3294324.3 | ... Q61: =P61+Q60 -> 4953938.1
A63: Unvested shares at end of horizon | B63: =SUM(W41:W53) -> 0
A64: Unvested equity value at horizon price | B64: =B63*$Q$34 -> 0
A76: SCENARIO: MEDIUM | B76: =Scenarios!D$3 -> Medium
A77: Year index | C77: 1 | D77: 2 | E77: 3 | F77: 4 | G77: 5 | H77: 6 | I77: 7 | J77: 8 | K77: 9 | L77: 10 | M77: 11 | N77: 12 | O77: 13 | P77: 14 | Q77: 15
A78: Calendar year | C78: =$B$6 -> 2026 | D78: =C78+1 -> 2027 | E78: =D78+1 -> 2028 | F78: =E78+1 -> 2029 | G78: =F78+1 -> 2030 | H78: =G78+1 -> 2031 | I78: =H78+1 -> 2032 | J78: =I78+1 -> 2033 | K78: =J78+1 -> 2034 | ... Q78: =P78+1 -> 2040
A79: Share price ($) | C79: =$B$17 -> 150 | D79: =C79*(1+Scenarios!$D$4) -> 160.5 | E79: =D79*(1+Scenarios!$D$4) -> 171.735 | F79: =E79*(1+Scenarios!$D$4) -> 183.75645 | G79: =F79*(1+Scenarios!$D$4) -> 196.6194 | H79: =G79*(1+Scenarios!$D$4) -> 210.38276 | I79: =H79*(1+Scenarios!$D$4) -> 225.10955 | J79: =I79*(1+Scenarios!$D$4) -> 240.86722 | K79: =J79*(1+Scenarios!$D$4) -> 257.72793 | ... Q79: =P79*(1+Scenarios!$D$4) -> 386.78012
A80: Base salary | C80: =$B$7 -> 200000 | D80: =C80*(1+$B$8*Scenarios!$D$5) -> 206000 | E80: =D80*(1+$B$8*Scenarios!$D$5) -> 212180 | F80: =E80*(1+$B$8*Scenarios!$D$5) -> 218545.4 | G80: =F80*(1+$B$8*Scenarios!$D$5) -> 225101.76 | H80: =G80*(1+$B$8*Scenarios!$D$5) -> 231854.81 | I80: =H80*(1+$B$8*Scenarios!$D$5) -> 238810.46 | J80: =I80*(1+$B$8*Scenarios!$D$5) -> 245974.77 | K80: =J80*(1+$B$8*Scenarios!$D$5) -> 253354.02 | ... Q80: =P80*(1+$B$8*Scenarios!$D$5) -> 302517.94
A81: Bonus basis salary | C81: =IF($B$10="Prior",0,C80) -> 200000 | D81: =IF($B$10="Prior",C80,D80) -> 206000 | E81: =IF($B$10="Prior",D80,E80) -> 212180 | F81: =IF($B$10="Prior",E80,F80) -> 218545.4 | G81: =IF($B$10="Prior",F80,G80) -> 225101.76 | H81: =IF($B$10="Prior",G80,H80) -> 231854.81 | I81: =IF($B$10="Prior",H80,I80) -> 238810.46 | J81: =IF($B$10="Prior",I80,J80) -> 245974.77 | K81: =IF($B$10="Prior",J80,K80) -> 253354.02 | ... Q81: =IF($B$10="Prior",P80,Q80) -> 302517.94
A82: Annual bonus | C82: =IF($B$11="No",0,C81*$B$9*Scenarios!$D$6) -> 0 | D82: =D81*$B$9*Scenarios!$D$6 -> 45320 | E82: =E81*$B$9*Scenarios!$D$6 -> 46679.6 | F82: =F81*$B$9*Scenarios!$D$6 -> 48079.988 | G82: =G81*$B$9*Scenarios!$D$6 -> 49522.388 | H82: =H81*$B$9*Scenarios!$D$6 -> 51008.059 | I82: =I81*$B$9*Scenarios!$D$6 -> 52538.301 | J82: =J81*$B$9*Scenarios!$D$6 -> 54114.45 | K82: =K81*$B$9*Scenarios!$D$6 -> 55737.884 | ... Q82: =Q81*$B$9*Scenarios!$D$6 -> 66553.948
A83: Sign-on paid | C83: =$B$12*$B$13 -> 50000 | D83: =$B$12*$B$14 -> 50000 | E83: =$B$12*$B$15 -> 0 | F83: 0 | G83: 0 | H83: 0 | I83: 0 | J83: 0 | K83: 0 | L83: 0 | M83: 0 | N83: 0 | O83: 0 | P83: 0 | Q83: 0
A85: GRANT LEDGER — dollar value vesting each year, one row per grant | S85: Grant year | T85: Grant value ($) | U85: Shares granted | V85: Shares vested in horizon | W85: Unvested shares
A86: Initial grant | C86: =IF(AND(C$78-$S86+1-$B$22>=1,C$78-$S86+1-$B$22<=8),INDEX($C$26:$J$26,1,C$78-$S86+1-$B$22),0)*$U86*C$79 -> 0 | D86: =IF(AND(D$78-$S86+1-$B$22>=1,D$78-$S86+1-$B$22<=8),INDEX($C$26:$J$26,1,D$78-$S86+1-$B$22),0)*$U86*D$79 -> 171200 | E86: =IF(AND(E$78-$S86+1-$B$22>=1,E$78-$S86+1-$B$22<=8),INDEX($C$26:$J$26,1,E$78-$S86+1-$B$22),0)*$U86*E$79 -> 128228.8 | F86: =IF(AND(F$78-$S86+1-$B$22>=1,F$78-$S86+1-$B$22<=8),INDEX($C$26:$J$26,1,F$78-$S86+1-$B$22),0)*$U86*F$79 -> 98003.44 | G86: =IF(AND(G$78-$S86+1-$B$22>=1,G$78-$S86+1-$B$22<=8),INDEX($C$26:$J$26,1,G$78-$S86+1-$B$22),0)*$U86*G$79 -> 62918.208 | H86: =IF(AND(H$78-$S86+1-$B$22>=1,H$78-$S86+1-$B$22<=8),INDEX($C$26:$J$26,1,H$78-$S86+1-$B$22),0)*$U86*H$79 -> 0 | I86: =IF(AND(I$78-$S86+1-$B$22>=1,I$78-$S86+1-$B$22<=8),INDEX($C$26:$J$26,1,I$78-$S86+1-$B$22),0)*$U86*I$79 -> 0 | J86: =IF(AND(J$78-$S86+1-$B$22>=1,J$78-$S86+1-$B$22<=8),INDEX($C$26:$J$26,1,J$78-$S86+1-$B$22),0)*$U86*J$79 -> 0 | ... Q86: =IF(AND(Q$78-$S86+1-$B$22>=1,Q$78-$S86+1-$B$22<=8),INDEX($C$26:$J$26,1,Q$78-$S86+1-$B$22),0)*$U86*Q$79 -> 0 | S86: =$B$6 -> 2026 | T86: =$B$18 -> 400000 | U86: =IFERROR(T86/$B$17,0) -> 2666.6667 | V86: =SUMPRODUCT(($C$25:$J$25<=$Q$78-$S86+1-$B$22)*$C$26:$J$26)*$U86 -> 2666.6667 | W86: =$U86-$V86 -> 0
A87: Refresher grant 1 | C87: =IF(AND(C$78-$S87+1-$B$22>=1,C$78-$S87+1-$B$22<=8),INDEX($C$27:$J$27,1,C$78-$S87+1-$B$22),0)*$U87*C$79 -> 0 | D87: =IF(AND(D$78-$S87+1-$B$22>=1,D$78-$S87+1-$B$22<=8),INDEX($C$27:$J$27,1,D$78-$S87+1-$B$22),0)*$U87*D$79 -> 0 | E87: =IF(AND(E$78-$S87+1-$B$22>=1,E$78-$S87+1-$B$22<=8),INDEX($C$27:$J$27,1,E$78-$S87+1-$B$22),0)*$U87*E$79 -> 40125 | F87: =IF(AND(F$78-$S87+1-$B$22>=1,F$78-$S87+1-$B$22<=8),INDEX($C$27:$J$27,1,F$78-$S87+1-$B$22),0)*$U87*F$79 -> 42933.75 | G87: =IF(AND(G$78-$S87+1-$B$22>=1,G$78-$S87+1-$B$22<=8),INDEX($C$27:$J$27,1,G$78-$S87+1-$B$22),0)*$U87*G$79 -> 45939.113 | H87: =IF(AND(H$78-$S87+1-$B$22>=1,H$78-$S87+1-$B$22<=8),INDEX($C$27:$J$27,1,H$78-$S87+1-$B$22),0)*$U87*H$79 -> 49154.85 | I87: =IF(AND(I$78-$S87+1-$B$22>=1,I$78-$S87+1-$B$22<=8),INDEX($C$27:$J$27,1,I$78-$S87+1-$B$22),0)*$U87*I$79 -> 0 | J87: =IF(AND(J$78-$S87+1-$B$22>=1,J$78-$S87+1-$B$22<=8),INDEX($C$27:$J$27,1,J$78-$S87+1-$B$22),0)*$U87*J$79 -> 0 | ... Q87: =IF(AND(Q$78-$S87+1-$B$22>=1,Q$78-$S87+1-$B$22<=8),INDEX($C$27:$J$27,1,Q$78-$S87+1-$B$22),0)*$U87*Q$79 -> 0 | S87: =$B$20+0 -> 2027 | T87: =IF($S87>$B$20+Scenarios!$D$8-1,0,$B$19*(1+$B$21*Scenarios!$D$7)^0) -> 150000 | U87: =IFERROR($T87/INDEX($C$79:$Q$79,1,MATCH($S87,$C$78:$Q$78,0)),0) -> 934.57944 | V87: =SUMPRODUCT(($C$25:$J$25<=$Q$78-$S87+1-$B$22)*$C$27:$J$27)*$U87 -> 934.57944 | W87: =$U87-$V87 -> 0
A88: Refresher grant 2 | C88: =IF(AND(C$78-$S88+1-$B$22>=1,C$78-$S88+1-$B$22<=8),INDEX($C$27:$J$27,1,C$78-$S88+1-$B$22),0)*$U88*C$79 -> 0 | D88: =IF(AND(D$78-$S88+1-$B$22>=1,D$78-$S88+1-$B$22<=8),INDEX($C$27:$J$27,1,D$78-$S88+1-$B$22),0)*$U88*D$79 -> 0 | E88: =IF(AND(E$78-$S88+1-$B$22>=1,E$78-$S88+1-$B$22<=8),INDEX($C$27:$J$27,1,E$78-$S88+1-$B$22),0)*$U88*E$79 -> 0 | F88: =IF(AND(F$78-$S88+1-$B$22>=1,F$78-$S88+1-$B$22<=8),INDEX($C$27:$J$27,1,F$78-$S88+1-$B$22),0)*$U88*F$79 -> 41328.75 | G88: =IF(AND(G$78-$S88+1-$B$22>=1,G$78-$S88+1-$B$22<=8),INDEX($C$27:$J$27,1,G$78-$S88+1-$B$22),0)*$U88*G$79 -> 44221.762 | H88: =IF(AND(H$78-$S88+1-$B$22>=1,H$78-$S88+1-$B$22<=8),INDEX($C$27:$J$27,1,H$78-$S88+1-$B$22),0)*$U88*H$79 -> 47317.286 | I88: =IF(AND(I$78-$S88+1-$B$22>=1,I$78-$S88+1-$B$22<=8),INDEX($C$27:$J$27,1,I$78-$S88+1-$B$22),0)*$U88*I$79 -> 50629.496 | J88: =IF(AND(J$78-$S88+1-$B$22>=1,J$78-$S88+1-$B$22<=8),INDEX($C$27:$J$27,1,J$78-$S88+1-$B$22),0)*$U88*J$79 -> 0 | ... Q88: =IF(AND(Q$78-$S88+1-$B$22>=1,Q$78-$S88+1-$B$22<=8),INDEX($C$27:$J$27,1,Q$78-$S88+1-$B$22),0)*$U88*Q$79 -> 0 | S88: =$B$20+1 -> 2028 | T88: =IF($S88>$B$20+Scenarios!$D$8-1,0,$B$19*(1+$B$21*Scenarios!$D$7)^1) -> 154500 | U88: =IFERROR($T88/INDEX($C$79:$Q$79,1,MATCH($S88,$C$78:$Q$78,0)),0) -> 899.64189 | V88: =SUMPRODUCT(($C$25:$J$25<=$Q$78-$S88+1-$B$22)*$C$27:$J$27)*$U88 -> 899.64189 | W88: =$U88-$V88 -> 0
A89: Refresher grant 3 | C89: =IF(AND(C$78-$S89+1-$B$22>=1,C$78-$S89+1-$B$22<=8),INDEX($C$27:$J$27,1,C$78-$S89+1-$B$22),0)*$U89*C$79 -> 0 | D89: =IF(AND(D$78-$S89+1-$B$22>=1,D$78-$S89+1-$B$22<=8),INDEX($C$27:$J$27,1,D$78-$S89+1-$B$22),0)*$U89*D$79 -> 0 | E89: =IF(AND(E$78-$S89+1-$B$22>=1,E$78-$S89+1-$B$22<=8),INDEX($C$27:$J$27,1,E$78-$S89+1-$B$22),0)*$U89*E$79 -> 0 | F89: =IF(AND(F$78-$S89+1-$B$22>=1,F$78-$S89+1-$B$22<=8),INDEX($C$27:$J$27,1,F$78-$S89+1-$B$22),0)*$U89*F$79 -> 0 | G89: =IF(AND(G$78-$S89+1-$B$22>=1,G$78-$S89+1-$B$22<=8),INDEX($C$27:$J$27,1,G$78-$S89+1-$B$22),0)*$U89*G$79 -> 42568.613 | H89: =IF(AND(H$78-$S89+1-$B$22>=1,H$78-$S89+1-$B$22<=8),INDEX($C$27:$J$27,1,H$78-$S89+1-$B$22),0)*$U89*H$79 -> 45548.415 | I89: =IF(AND(I$78-$S89+1-$B$22>=1,I$78-$S89+1-$B$22<=8),INDEX($C$27:$J$27,1,I$78-$S89+1-$B$22),0)*$U89*I$79 -> 48736.804 | J89: =IF(AND(J$78-$S89+1-$B$22>=1,J$78-$S89+1-$B$22<=8),INDEX($C$27:$J$27,1,J$78-$S89+1-$B$22),0)*$U89*J$79 -> 52148.381 | ... Q89: =IF(AND(Q$78-$S89+1-$B$22>=1,Q$78-$S89+1-$B$22<=8),INDEX($C$27:$J$27,1,Q$78-$S89+1-$B$22),0)*$U89*Q$79 -> 0 | S89: =$B$20+2 -> 2029 | T89: =IF($S89>$B$20+Scenarios!$D$8-1,0,$B$19*(1+$B$21*Scenarios!$D$7)^2) -> 159135 | U89: =IFERROR($T89/INDEX($C$79:$Q$79,1,MATCH($S89,$C$78:$Q$78,0)),0) -> 866.01042 | V89: =SUMPRODUCT(($C$25:$J$25<=$Q$78-$S89+1-$B$22)*$C$27:$J$27)*$U89 -> 866.01042 | W89: =$U89-$V89 -> 0
A90: Refresher grant 4 | C90: =IF(AND(C$78-$S90+1-$B$22>=1,C$78-$S90+1-$B$22<=8),INDEX($C$27:$J$27,1,C$78-$S90+1-$B$22),0)*$U90*C$79 -> 0 | D90: =IF(AND(D$78-$S90+1-$B$22>=1,D$78-$S90+1-$B$22<=8),INDEX($C$27:$J$27,1,D$78-$S90+1-$B$22),0)*$U90*D$79 -> 0 | E90: =IF(AND(E$78-$S90+1-$B$22>=1,E$78-$S90+1-$B$22<=8),INDEX($C$27:$J$27,1,E$78-$S90+1-$B$22),0)*$U90*E$79 -> 0 | F90: =IF(AND(F$78-$S90+1-$B$22>=1,F$78-$S90+1-$B$22<=8),INDEX($C$27:$J$27,1,F$78-$S90+1-$B$22),0)*$U90*F$79 -> 0 | G90: =IF(AND(G$78-$S90+1-$B$22>=1,G$78-$S90+1-$B$22<=8),INDEX($C$27:$J$27,1,G$78-$S90+1-$B$22),0)*$U90*G$79 -> 0 | H90: =IF(AND(H$78-$S90+1-$B$22>=1,H$78-$S90+1-$B$22<=8),INDEX($C$27:$J$27,1,H$78-$S90+1-$B$22),0)*$U90*H$79 -> 43845.671 | I90: =IF(AND(I$78-$S90+1-$B$22>=1,I$78-$S90+1-$B$22<=8),INDEX($C$27:$J$27,1,I$78-$S90+1-$B$22),0)*$U90*I$79 -> 46914.868 | J90: =IF(AND(J$78-$S90+1-$B$22>=1,J$78-$S90+1-$B$22<=8),INDEX($C$27:$J$27,1,J$78-$S90+1-$B$22),0)*$U90*J$79 -> 50198.909 | ... Q90: =IF(AND(Q$78-$S90+1-$B$22>=1,Q$78-$S90+1-$B$22<=8),INDEX($C$27:$J$27,1,Q$78-$S90+1-$B$22),0)*$U90*Q$79 -> 0 | S90: =$B$20+3 -> 2030 | T90: =IF($S90>$B$20+Scenarios!$D$8-1,0,$B$19*(1+$B$21*Scenarios!$D$7)^3) -> 163909.05 | U90: =IFERROR($T90/INDEX($C$79:$Q$79,1,MATCH($S90,$C$78:$Q$78,0)),0) -> 833.6362 | V90: =SUMPRODUCT(($C$25:$J$25<=$Q$78-$S90+1-$B$22)*$C$27:$J$27)*$U90 -> 833.6362 | W90: =$U90-$V90 -> 0
A91: Refresher grant 5 | C91: =IF(AND(C$78-$S91+1-$B$22>=1,C$78-$S91+1-$B$22<=8),INDEX($C$27:$J$27,1,C$78-$S91+1-$B$22),0)*$U91*C$79 -> 0 | D91: =IF(AND(D$78-$S91+1-$B$22>=1,D$78-$S91+1-$B$22<=8),INDEX($C$27:$J$27,1,D$78-$S91+1-$B$22),0)*$U91*D$79 -> 0 | E91: =IF(AND(E$78-$S91+1-$B$22>=1,E$78-$S91+1-$B$22<=8),INDEX($C$27:$J$27,1,E$78-$S91+1-$B$22),0)*$U91*E$79 -> 0 | F91: =IF(AND(F$78-$S91+1-$B$22>=1,F$78-$S91+1-$B$22<=8),INDEX($C$27:$J$27,1,F$78-$S91+1-$B$22),0)*$U91*F$79 -> 0 | G91: =IF(AND(G$78-$S91+1-$B$22>=1,G$78-$S91+1-$B$22<=8),INDEX($C$27:$J$27,1,G$78-$S91+1-$B$22),0)*$U91*G$79 -> 0 | H91: =IF(AND(H$78-$S91+1-$B$22>=1,H$78-$S91+1-$B$22<=8),INDEX($C$27:$J$27,1,H$78-$S91+1-$B$22),0)*$U91*H$79 -> 0 | I91: =IF(AND(I$78-$S91+1-$B$22>=1,I$78-$S91+1-$B$22<=8),INDEX($C$27:$J$27,1,I$78-$S91+1-$B$22),0)*$U91*I$79 -> 45161.041 | J91: =IF(AND(J$78-$S91+1-$B$22>=1,J$78-$S91+1-$B$22<=8),INDEX($C$27:$J$27,1,J$78-$S91+1-$B$22),0)*$U91*J$79 -> 48322.314 | ... Q91: =IF(AND(Q$78-$S91+1-$B$22>=1,Q$78-$S91+1-$B$22<=8),INDEX($C$27:$J$27,1,Q$78-$S91+1-$B$22),0)*$U91*Q$79 -> 0 | S91: =$B$20+4 -> 2031 | T91: =IF($S91>$B$20+Scenarios!$D$8-1,0,$B$19*(1+$B$21*Scenarios!$D$7)^4) -> 168826.32 | U91: =IFERROR($T91/INDEX($C$79:$Q$79,1,MATCH($S91,$C$78:$Q$78,0)),0) -> 802.47223 | V91: =SUMPRODUCT(($C$25:$J$25<=$Q$78-$S91+1-$B$22)*$C$27:$J$27)*$U91 -> 802.47223 | W91: =$U91-$V91 -> 0
A92: Refresher grant 6 | C92: =IF(AND(C$78-$S92+1-$B$22>=1,C$78-$S92+1-$B$22<=8),INDEX($C$27:$J$27,1,C$78-$S92+1-$B$22),0)*$U92*C$79 -> 0 | D92: =IF(AND(D$78-$S92+1-$B$22>=1,D$78-$S92+1-$B$22<=8),INDEX($C$27:$J$27,1,D$78-$S92+1-$B$22),0)*$U92*D$79 -> 0 | E92: =IF(AND(E$78-$S92+1-$B$22>=1,E$78-$S92+1-$B$22<=8),INDEX($C$27:$J$27,1,E$78-$S92+1-$B$22),0)*$U92*E$79 -> 0 | F92: =IF(AND(F$78-$S92+1-$B$22>=1,F$78-$S92+1-$B$22<=8),INDEX($C$27:$J$27,1,F$78-$S92+1-$B$22),0)*$U92*F$79 -> 0 | G92: =IF(AND(G$78-$S92+1-$B$22>=1,G$78-$S92+1-$B$22<=8),INDEX($C$27:$J$27,1,G$78-$S92+1-$B$22),0)*$U92*G$79 -> 0 | H92: =IF(AND(H$78-$S92+1-$B$22>=1,H$78-$S92+1-$B$22<=8),INDEX($C$27:$J$27,1,H$78-$S92+1-$B$22),0)*$U92*H$79 -> 0 | I92: =IF(AND(I$78-$S92+1-$B$22>=1,I$78-$S92+1-$B$22<=8),INDEX($C$27:$J$27,1,I$78-$S92+1-$B$22),0)*$U92*I$79 -> 0 | J92: =IF(AND(J$78-$S92+1-$B$22>=1,J$78-$S92+1-$B$22<=8),INDEX($C$27:$J$27,1,J$78-$S92+1-$B$22),0)*$U92*J$79 -> 46515.872 | ... Q92: =IF(AND(Q$78-$S92+1-$B$22>=1,Q$78-$S92+1-$B$22<=8),INDEX($C$27:$J$27,1,Q$78-$S92+1-$B$22),0)*$U92*Q$79 -> 0 | S92: =$B$20+5 -> 2032 | T92: =IF($S92>$B$20+Scenarios!$D$8-1,0,$B$19*(1+$B$21*Scenarios!$D$7)^5) -> 173891.11 | U92: =IFERROR($T92/INDEX($C$79:$Q$79,1,MATCH($S92,$C$78:$Q$78,0)),0) -> 772.47326 | V92: =SUMPRODUCT(($C$25:$J$25<=$Q$78-$S92+1-$B$22)*$C$27:$J$27)*$U92 -> 772.47326 | W92: =$U92-$V92 -> 0
A93: Refresher grant 7 | C93: =IF(AND(C$78-$S93+1-$B$22>=1,C$78-$S93+1-$B$22<=8),INDEX($C$27:$J$27,1,C$78-$S93+1-$B$22),0)*$U93*C$79 -> 0 | D93: =IF(AND(D$78-$S93+1-$B$22>=1,D$78-$S93+1-$B$22<=8),INDEX($C$27:$J$27,1,D$78-$S93+1-$B$22),0)*$U93*D$79 -> 0 | E93: =IF(AND(E$78-$S93+1-$B$22>=1,E$78-$S93+1-$B$22<=8),INDEX($C$27:$J$27,1,E$78-$S93+1-$B$22),0)*$U93*E$79 -> 0 | F93: =IF(AND(F$78-$S93+1-$B$22>=1,F$78-$S93+1-$B$22<=8),INDEX($C$27:$J$27,1,F$78-$S93+1-$B$22),0)*$U93*F$79 -> 0 | G93: =IF(AND(G$78-$S93+1-$B$22>=1,G$78-$S93+1-$B$22<=8),INDEX($C$27:$J$27,1,G$78-$S93+1-$B$22),0)*$U93*G$79 -> 0 | H93: =IF(AND(H$78-$S93+1-$B$22>=1,H$78-$S93+1-$B$22<=8),INDEX($C$27:$J$27,1,H$78-$S93+1-$B$22),0)*$U93*H$79 -> 0 | I93: =IF(AND(I$78-$S93+1-$B$22>=1,I$78-$S93+1-$B$22<=8),INDEX($C$27:$J$27,1,I$78-$S93+1-$B$22),0)*$U93*I$79 -> 0 | J93: =IF(AND(J$78-$S93+1-$B$22>=1,J$78-$S93+1-$B$22<=8),INDEX($C$27:$J$27,1,J$78-$S93+1-$B$22),0)*$U93*J$79 -> 0 | ... Q93: =IF(AND(Q$78-$S93+1-$B$22>=1,Q$78-$S93+1-$B$22<=8),INDEX($C$27:$J$27,1,Q$78-$S93+1-$B$22),0)*$U93*Q$79 -> 0 | S93: =$B$20+6 -> 2033 | T93: =IF($S93>$B$20+Scenarios!$D$8-1,0,$B$19*(1+$B$21*Scenarios!$D$7)^6) -> 179107.84 | U93: =IFERROR($T93/INDEX($C$79:$Q$79,1,MATCH($S93,$C$78:$Q$78,0)),0) -> 743.59576 | V93: =SUMPRODUCT(($C$25:$J$25<=$Q$78-$S93+1-$B$22)*$C$27:$J$27)*$U93 -> 743.59576 | W93: =$U93-$V93 -> 0
A94: Refresher grant 8 | C94: =IF(AND(C$78-$S94+1-$B$22>=1,C$78-$S94+1-$B$22<=8),INDEX($C$27:$J$27,1,C$78-$S94+1-$B$22),0)*$U94*C$79 -> 0 | D94: =IF(AND(D$78-$S94+1-$B$22>=1,D$78-$S94+1-$B$22<=8),INDEX($C$27:$J$27,1,D$78-$S94+1-$B$22),0)*$U94*D$79 -> 0 | E94: =IF(AND(E$78-$S94+1-$B$22>=1,E$78-$S94+1-$B$22<=8),INDEX($C$27:$J$27,1,E$78-$S94+1-$B$22),0)*$U94*E$79 -> 0 | F94: =IF(AND(F$78-$S94+1-$B$22>=1,F$78-$S94+1-$B$22<=8),INDEX($C$27:$J$27,1,F$78-$S94+1-$B$22),0)*$U94*F$79 -> 0 | G94: =IF(AND(G$78-$S94+1-$B$22>=1,G$78-$S94+1-$B$22<=8),INDEX($C$27:$J$27,1,G$78-$S94+1-$B$22),0)*$U94*G$79 -> 0 | H94: =IF(AND(H$78-$S94+1-$B$22>=1,H$78-$S94+1-$B$22<=8),INDEX($C$27:$J$27,1,H$78-$S94+1-$B$22),0)*$U94*H$79 -> 0 | I94: =IF(AND(I$78-$S94+1-$B$22>=1,I$78-$S94+1-$B$22<=8),INDEX($C$27:$J$27,1,I$78-$S94+1-$B$22),0)*$U94*I$79 -> 0 | J94: =IF(AND(J$78-$S94+1-$B$22>=1,J$78-$S94+1-$B$22<=8),INDEX($C$27:$J$27,1,J$78-$S94+1-$B$22),0)*$U94*J$79 -> 0 | ... Q94: =IF(AND(Q$78-$S94+1-$B$22>=1,Q$78-$S94+1-$B$22<=8),INDEX($C$27:$J$27,1,Q$78-$S94+1-$B$22),0)*$U94*Q$79 -> 0 | S94: =$B$20+7 -> 2034 | T94: =IF($S94>$B$20+Scenarios!$D$8-1,0,$B$19*(1+$B$21*Scenarios!$D$7)^7) -> 184481.08 | U94: =IFERROR($T94/INDEX($C$79:$Q$79,1,MATCH($S94,$C$78:$Q$78,0)),0) -> 715.79779 | V94: =SUMPRODUCT(($C$25:$J$25<=$Q$78-$S94+1-$B$22)*$C$27:$J$27)*$U94 -> 715.79779 | W94: =$U94-$V94 -> 0
A95: Refresher grant 9 | C95: =IF(AND(C$78-$S95+1-$B$22>=1,C$78-$S95+1-$B$22<=8),INDEX($C$27:$J$27,1,C$78-$S95+1-$B$22),0)*$U95*C$79 -> 0 | D95: =IF(AND(D$78-$S95+1-$B$22>=1,D$78-$S95+1-$B$22<=8),INDEX($C$27:$J$27,1,D$78-$S95+1-$B$22),0)*$U95*D$79 -> 0 | E95: =IF(AND(E$78-$S95+1-$B$22>=1,E$78-$S95+1-$B$22<=8),INDEX($C$27:$J$27,1,E$78-$S95+1-$B$22),0)*$U95*E$79 -> 0 | F95: =IF(AND(F$78-$S95+1-$B$22>=1,F$78-$S95+1-$B$22<=8),INDEX($C$27:$J$27,1,F$78-$S95+1-$B$22),0)*$U95*F$79 -> 0 | G95: =IF(AND(G$78-$S95+1-$B$22>=1,G$78-$S95+1-$B$22<=8),INDEX($C$27:$J$27,1,G$78-$S95+1-$B$22),0)*$U95*G$79 -> 0 | H95: =IF(AND(H$78-$S95+1-$B$22>=1,H$78-$S95+1-$B$22<=8),INDEX($C$27:$J$27,1,H$78-$S95+1-$B$22),0)*$U95*H$79 -> 0 | I95: =IF(AND(I$78-$S95+1-$B$22>=1,I$78-$S95+1-$B$22<=8),INDEX($C$27:$J$27,1,I$78-$S95+1-$B$22),0)*$U95*I$79 -> 0 | J95: =IF(AND(J$78-$S95+1-$B$22>=1,J$78-$S95+1-$B$22<=8),INDEX($C$27:$J$27,1,J$78-$S95+1-$B$22),0)*$U95*J$79 -> 0 | ... Q95: =IF(AND(Q$78-$S95+1-$B$22>=1,Q$78-$S95+1-$B$22<=8),INDEX($C$27:$J$27,1,Q$78-$S95+1-$B$22),0)*$U95*Q$79 -> 0 | S95: =$B$20+8 -> 2035 | T95: =IF($S95>$B$20+Scenarios!$D$8-1,0,$B$19*(1+$B$21*Scenarios!$D$7)^8) -> 190015.51 | U95: =IFERROR($T95/INDEX($C$79:$Q$79,1,MATCH($S95,$C$78:$Q$78,0)),0) -> 689.03899 | V95: =SUMPRODUCT(($C$25:$J$25<=$Q$78-$S95+1-$B$22)*$C$27:$J$27)*$U95 -> 689.03899 | W95: =$U95-$V95 -> 0
A96: Refresher grant 10 | C96: =IF(AND(C$78-$S96+1-$B$22>=1,C$78-$S96+1-$B$22<=8),INDEX($C$27:$J$27,1,C$78-$S96+1-$B$22),0)*$U96*C$79 -> 0 | D96: =IF(AND(D$78-$S96+1-$B$22>=1,D$78-$S96+1-$B$22<=8),INDEX($C$27:$J$27,1,D$78-$S96+1-$B$22),0)*$U96*D$79 -> 0 | E96: =IF(AND(E$78-$S96+1-$B$22>=1,E$78-$S96+1-$B$22<=8),INDEX($C$27:$J$27,1,E$78-$S96+1-$B$22),0)*$U96*E$79 -> 0 | F96: =IF(AND(F$78-$S96+1-$B$22>=1,F$78-$S96+1-$B$22<=8),INDEX($C$27:$J$27,1,F$78-$S96+1-$B$22),0)*$U96*F$79 -> 0 | G96: =IF(AND(G$78-$S96+1-$B$22>=1,G$78-$S96+1-$B$22<=8),INDEX($C$27:$J$27,1,G$78-$S96+1-$B$22),0)*$U96*G$79 -> 0 | H96: =IF(AND(H$78-$S96+1-$B$22>=1,H$78-$S96+1-$B$22<=8),INDEX($C$27:$J$27,1,H$78-$S96+1-$B$22),0)*$U96*H$79 -> 0 | I96: =IF(AND(I$78-$S96+1-$B$22>=1,I$78-$S96+1-$B$22<=8),INDEX($C$27:$J$27,1,I$78-$S96+1-$B$22),0)*$U96*I$79 -> 0 | J96: =IF(AND(J$78-$S96+1-$B$22>=1,J$78-$S96+1-$B$22<=8),INDEX($C$27:$J$27,1,J$78-$S96+1-$B$22),0)*$U96*J$79 -> 0 | ... Q96: =IF(AND(Q$78-$S96+1-$B$22>=1,Q$78-$S96+1-$B$22<=8),INDEX($C$27:$J$27,1,Q$78-$S96+1-$B$22),0)*$U96*Q$79 -> 64135.931 | S96: =$B$20+9 -> 2036 | T96: =IF($S96>$B$20+Scenarios!$D$8-1,0,$B$19*(1+$B$21*Scenarios!$D$7)^9) -> 195715.98 | U96: =IFERROR($T96/INDEX($C$79:$Q$79,1,MATCH($S96,$C$78:$Q$78,0)),0) -> 663.28052 | V96: =SUMPRODUCT(($C$25:$J$25<=$Q$78-$S96+1-$B$22)*$C$27:$J$27)*$U96 -> 663.28052 | W96: =$U96-$V96 -> 0
A97: Refresher grant 11 | C97: =IF(AND(C$78-$S97+1-$B$22>=1,C$78-$S97+1-$B$22<=8),INDEX($C$27:$J$27,1,C$78-$S97+1-$B$22),0)*$U97*C$79 -> 0 | D97: =IF(AND(D$78-$S97+1-$B$22>=1,D$78-$S97+1-$B$22<=8),INDEX($C$27:$J$27,1,D$78-$S97+1-$B$22),0)*$U97*D$79 -> 0 | E97: =IF(AND(E$78-$S97+1-$B$22>=1,E$78-$S97+1-$B$22<=8),INDEX($C$27:$J$27,1,E$78-$S97+1-$B$22),0)*$U97*E$79 -> 0 | F97: =IF(AND(F$78-$S97+1-$B$22>=1,F$78-$S97+1-$B$22<=8),INDEX($C$27:$J$27,1,F$78-$S97+1-$B$22),0)*$U97*F$79 -> 0 | G97: =IF(AND(G$78-$S97+1-$B$22>=1,G$78-$S97+1-$B$22<=8),INDEX($C$27:$J$27,1,G$78-$S97+1-$B$22),0)*$U97*G$79 -> 0 | H97: =IF(AND(H$78-$S97+1-$B$22>=1,H$78-$S97+1-$B$22<=8),INDEX($C$27:$J$27,1,H$78-$S97+1-$B$22),0)*$U97*H$79 -> 0 | I97: =IF(AND(I$78-$S97+1-$B$22>=1,I$78-$S97+1-$B$22<=8),INDEX($C$27:$J$27,1,I$78-$S97+1-$B$22),0)*$U97*I$79 -> 0 | J97: =IF(AND(J$78-$S97+1-$B$22>=1,J$78-$S97+1-$B$22<=8),INDEX($C$27:$J$27,1,J$78-$S97+1-$B$22),0)*$U97*J$79 -> 0 | ... Q97: =IF(AND(Q$78-$S97+1-$B$22>=1,Q$78-$S97+1-$B$22<=8),INDEX($C$27:$J$27,1,Q$78-$S97+1-$B$22),0)*$U97*Q$79 -> 61738.326 | S97: =$B$20+10 -> 2037 | T97: =IF($S97>$B$20+Scenarios!$D$8-1,0,$B$19*(1+$B$21*Scenarios!$D$7)^10) -> 201587.46 | U97: =IFERROR($T97/INDEX($C$79:$Q$79,1,MATCH($S97,$C$78:$Q$78,0)),0) -> 638.48499 | V97: =SUMPRODUCT(($C$25:$J$25<=$Q$78-$S97+1-$B$22)*$C$27:$J$27)*$U97 -> 478.86374 | W97: =$U97-$V97 -> 159.62125
A98: Refresher grant 12 | C98: =IF(AND(C$78-$S98+1-$B$22>=1,C$78-$S98+1-$B$22<=8),INDEX($C$27:$J$27,1,C$78-$S98+1-$B$22),0)*$U98*C$79 -> 0 | D98: =IF(AND(D$78-$S98+1-$B$22>=1,D$78-$S98+1-$B$22<=8),INDEX($C$27:$J$27,1,D$78-$S98+1-$B$22),0)*$U98*D$79 -> 0 | E98: =IF(AND(E$78-$S98+1-$B$22>=1,E$78-$S98+1-$B$22<=8),INDEX($C$27:$J$27,1,E$78-$S98+1-$B$22),0)*$U98*E$79 -> 0 | F98: =IF(AND(F$78-$S98+1-$B$22>=1,F$78-$S98+1-$B$22<=8),INDEX($C$27:$J$27,1,F$78-$S98+1-$B$22),0)*$U98*F$79 -> 0 | G98: =IF(AND(G$78-$S98+1-$B$22>=1,G$78-$S98+1-$B$22<=8),INDEX($C$27:$J$27,1,G$78-$S98+1-$B$22),0)*$U98*G$79 -> 0 | H98: =IF(AND(H$78-$S98+1-$B$22>=1,H$78-$S98+1-$B$22<=8),INDEX($C$27:$J$27,1,H$78-$S98+1-$B$22),0)*$U98*H$79 -> 0 | I98: =IF(AND(I$78-$S98+1-$B$22>=1,I$78-$S98+1-$B$22<=8),INDEX($C$27:$J$27,1,I$78-$S98+1-$B$22),0)*$U98*I$79 -> 0 | J98: =IF(AND(J$78-$S98+1-$B$22>=1,J$78-$S98+1-$B$22<=8),INDEX($C$27:$J$27,1,J$78-$S98+1-$B$22),0)*$U98*J$79 -> 0 | ... Q98: =IF(AND(Q$78-$S98+1-$B$22>=1,Q$78-$S98+1-$B$22<=8),INDEX($C$27:$J$27,1,Q$78-$S98+1-$B$22),0)*$U98*Q$79 -> 59430.351 | S98: =$B$20+11 -> 2038 | T98: =IF($S98>$B$20+Scenarios!$D$8-1,0,$B$19*(1+$B$21*Scenarios!$D$7)^11) -> 207635.08 | U98: =IFERROR($T98/INDEX($C$79:$Q$79,1,MATCH($S98,$C$78:$Q$78,0)),0) -> 614.61639 | V98: =SUMPRODUCT(($C$25:$J$25<=$Q$78-$S98+1-$B$22)*$C$27:$J$27)*$U98 -> 307.3082 | W98: =$U98-$V98 -> 307.3082
A100: Initial grant vest ($) | C100: =C86 -> 0 | D100: =D86 -> 171200 | E100: =E86 -> 128228.8 | F100: =F86 -> 98003.44 | G100: =G86 -> 62918.208 | H100: =H86 -> 0 | I100: =I86 -> 0 | J100: =J86 -> 0 | ... Q100: =Q86 -> 0
A101: Refresher vest ($) | C101: =SUM(C87:C98) -> 0 | D101: =SUM(D87:D98) -> 0 | E101: =SUM(E87:E98) -> 40125 | F101: =SUM(F87:F98) -> 84262.5 | G101: =SUM(G87:G98) -> 132729.49 | H101: =SUM(H87:H98) -> 185866.22 | I101: =SUM(I87:I98) -> 191442.21 | J101: =SUM(J87:J98) -> 197185.48 | ... Q101: =SUM(Q87:Q98) -> 185304.61
A102: Total equity vest ($) | C102: =C100+C101 -> 0 | D102: =D100+D101 -> 171200 | E102: =E100+E101 -> 168353.8 | F102: =F100+F101 -> 182265.94 | G102: =G100+G101 -> 195647.7 | H102: =H100+H101 -> 185866.22 | I102: =I100+I101 -> 191442.21 | J102: =J100+J101 -> 197185.48 | ... Q102: =Q100+Q101 -> 185304.61
A103: Concurrent grants vesting (count) | C103: =SUMPRODUCT((C86:C98>0)*1) -> 0 | D103: =SUMPRODUCT((D86:D98>0)*1) -> 1 | E103: =SUMPRODUCT((E86:E98>0)*1) -> 2 | F103: =SUMPRODUCT((F86:F98>0)*1) -> 3 | G103: =SUMPRODUCT((G86:G98>0)*1) -> 4 | H103: =SUMPRODUCT((H86:H98>0)*1) -> 4 | I103: =SUMPRODUCT((I86:I98>0)*1) -> 4 | J103: =SUMPRODUCT((J86:J98>0)*1) -> 4 | ... Q103: =SUMPRODUCT((Q86:Q98>0)*1) -> 3
A105: TOTAL GROSS COMPENSATION | C105: =C80+C82+C83+C102 -> 250000 | D105: =D80+D82+D83+D102 -> 472520 | E105: =E80+E82+E83+E102 -> 427213.4 | F105: =F80+F82+F83+F102 -> 448891.33 | G105: =G80+G82+G83+G102 -> 470271.85 | H105: =H80+H82+H83+H102 -> 468729.1 | I105: =I80+I82+I83+I102 -> 482790.97 | J105: =J80+J82+J83+J102 -> 497274.7 | ... Q105: =Q80+Q82+Q83+Q102 -> 554376.5
A106: Cumulative gross | C106: =C105 -> 250000 | D106: =C106+D105 -> 722520 | E106: =D106+E105 -> 1149733.4 | F106: =E106+F105 -> 1598624.7 | G106: =F106+G105 -> 2068896.6 | H106: =G106+H105 -> 2537625.7 | I106: =H106+I105 -> 3020416.6 | J106: =I106+J105 -> 3517691.3 | K106: =J106+K105 -> 4029884.3 | ... Q106: =P106+Q105 -> 7385141.7
A108: Unvested shares at end of horizon | B108: =SUM(W86:W98) -> 466.92944
A109: Unvested equity value at horizon price | B109: =B108*$Q$79 -> 180599.03
A121: SCENARIO: AGGRESSIVE | B121: =Scenarios!E$3 -> Aggressive
A122: Year index | C122: 1 | D122: 2 | E122: 3 | F122: 4 | G122: 5 | H122: 6 | I122: 7 | J122: 8 | K122: 9 | L122: 10 | M122: 11 | N122: 12 | O122: 13 | P122: 14 | Q122: 15
A123: Calendar year | C123: =$B$6 -> 2026 | D123: =C123+1 -> 2027 | E123: =D123+1 -> 2028 | F123: =E123+1 -> 2029 | G123: =F123+1 -> 2030 | H123: =G123+1 -> 2031 | I123: =H123+1 -> 2032 | J123: =I123+1 -> 2033 | K123: =J123+1 -> 2034 | ... Q123: =P123+1 -> 2040
A124: Share price ($) | C124: =$B$17 -> 150 | D124: =C124*(1+Scenarios!$E$4) -> 172.5 | E124: =D124*(1+Scenarios!$E$4) -> 198.375 | F124: =E124*(1+Scenarios!$E$4) -> 228.13125 | G124: =F124*(1+Scenarios!$E$4) -> 262.35094 | H124: =G124*(1+Scenarios!$E$4) -> 301.70358 | I124: =H124*(1+Scenarios!$E$4) -> 346.95911 | J124: =I124*(1+Scenarios!$E$4) -> 399.00298 | K124: =J124*(1+Scenarios!$E$4) -> 458.85343 | ... Q124: =P124*(1+Scenarios!$E$4) -> 1061.3559
A125: Base salary | C125: =$B$7 -> 200000 | D125: =C125*(1+$B$8*Scenarios!$E$5) -> 209000 | E125: =D125*(1+$B$8*Scenarios!$E$5) -> 218405 | F125: =E125*(1+$B$8*Scenarios!$E$5) -> 228233.23 | G125: =F125*(1+$B$8*Scenarios!$E$5) -> 238503.72 | H125: =G125*(1+$B$8*Scenarios!$E$5) -> 249236.39 | I125: =H125*(1+$B$8*Scenarios!$E$5) -> 260452.02 | J125: =I125*(1+$B$8*Scenarios!$E$5) -> 272172.37 | K125: =J125*(1+$B$8*Scenarios!$E$5) -> 284420.12 | ... Q125: =P125*(1+$B$8*Scenarios!$E$5) -> 370388.98
A126: Bonus basis salary | C126: =IF($B$10="Prior",0,C125) -> 200000 | D126: =IF($B$10="Prior",C125,D125) -> 209000 | E126: =IF($B$10="Prior",D125,E125) -> 218405 | F126: =IF($B$10="Prior",E125,F125) -> 228233.23 | G126: =IF($B$10="Prior",F125,G125) -> 238503.72 | H126: =IF($B$10="Prior",G125,H125) -> 249236.39 | I126: =IF($B$10="Prior",H125,I125) -> 260452.02 | J126: =IF($B$10="Prior",I125,J125) -> 272172.37 | K126: =IF($B$10="Prior",J125,K125) -> 284420.12 | ... Q126: =IF($B$10="Prior",P125,Q125) -> 370388.98
A127: Annual bonus | C127: =IF($B$11="No",0,C126*$B$9*Scenarios!$E$6) -> 0 | D127: =D126*$B$9*Scenarios!$E$6 -> 57475 | E127: =E126*$B$9*Scenarios!$E$6 -> 60061.375 | F127: =F126*$B$9*Scenarios!$E$6 -> 62764.137 | G127: =G126*$B$9*Scenarios!$E$6 -> 65588.523 | H127: =H126*$B$9*Scenarios!$E$6 -> 68540.007 | I127: =I126*$B$9*Scenarios!$E$6 -> 71624.307 | J127: =J126*$B$9*Scenarios!$E$6 -> 74847.401 | K127: =K126*$B$9*Scenarios!$E$6 -> 78215.534 | ... Q127: =Q126*$B$9*Scenarios!$E$6 -> 101856.97
A128: Sign-on paid | C128: =$B$12*$B$13 -> 50000 | D128: =$B$12*$B$14 -> 50000 | E128: =$B$12*$B$15 -> 0 | F128: 0 | G128: 0 | H128: 0 | I128: 0 | J128: 0 | K128: 0 | L128: 0 | M128: 0 | N128: 0 | O128: 0 | P128: 0 | Q128: 0
A130: GRANT LEDGER — dollar value vesting each year, one row per grant | S130: Grant year | T130: Grant value ($) | U130: Shares granted | V130: Shares vested in horizon | W130: Unvested shares
A131: Initial grant | C131: =IF(AND(C$123-$S131+1-$B$22>=1,C$123-$S131+1-$B$22<=8),INDEX($C$26:$J$26,1,C$123-$S131+1-$B$22),0)*$U131*C$124 -> 0 | D131: =IF(AND(D$123-$S131+1-$B$22>=1,D$123-$S131+1-$B$22<=8),INDEX($C$26:$J$26,1,D$123-$S131+1-$B$22),0)*$U131*D$124 -> 184000 | E131: =IF(AND(E$123-$S131+1-$B$22>=1,E$123-$S131+1-$B$22<=8),INDEX($C$26:$J$26,1,E$123-$S131+1-$B$22),0)*$U131*E$124 -> 148120 | F131: =IF(AND(F$123-$S131+1-$B$22>=1,F$123-$S131+1-$B$22<=8),INDEX($C$26:$J$26,1,F$123-$S131+1-$B$22),0)*$U131*F$124 -> 121670 | G131: =IF(AND(G$123-$S131+1-$B$22>=1,G$123-$S131+1-$B$22<=8),INDEX($C$26:$J$26,1,G$123-$S131+1-$B$22),0)*$U131*G$124 -> 83952.3 | H131: =IF(AND(H$123-$S131+1-$B$22>=1,H$123-$S131+1-$B$22<=8),INDEX($C$26:$J$26,1,H$123-$S131+1-$B$22),0)*$U131*H$124 -> 0 | I131: =IF(AND(I$123-$S131+1-$B$22>=1,I$123-$S131+1-$B$22<=8),INDEX($C$26:$J$26,1,I$123-$S131+1-$B$22),0)*$U131*I$124 -> 0 | J131: =IF(AND(J$123-$S131+1-$B$22>=1,J$123-$S131+1-$B$22<=8),INDEX($C$26:$J$26,1,J$123-$S131+1-$B$22),0)*$U131*J$124 -> 0 | ... Q131: =IF(AND(Q$123-$S131+1-$B$22>=1,Q$123-$S131+1-$B$22<=8),INDEX($C$26:$J$26,1,Q$123-$S131+1-$B$22),0)*$U131*Q$124 -> 0 | S131: =$B$6 -> 2026 | T131: =$B$18 -> 400000 | U131: =IFERROR(T131/$B$17,0) -> 2666.6667 | V131: =SUMPRODUCT(($C$25:$J$25<=$Q$123-$S131+1-$B$22)*$C$26:$J$26)*$U131 -> 2666.6667 | W131: =$U131-$V131 -> 0
A132: Refresher grant 1 | C132: =IF(AND(C$123-$S132+1-$B$22>=1,C$123-$S132+1-$B$22<=8),INDEX($C$27:$J$27,1,C$123-$S132+1-$B$22),0)*$U132*C$124 -> 0 | D132: =IF(AND(D$123-$S132+1-$B$22>=1,D$123-$S132+1-$B$22<=8),INDEX($C$27:$J$27,1,D$123-$S132+1-$B$22),0)*$U132*D$124 -> 0 | E132: =IF(AND(E$123-$S132+1-$B$22>=1,E$123-$S132+1-$B$22<=8),INDEX($C$27:$J$27,1,E$123-$S132+1-$B$22),0)*$U132*E$124 -> 43125 | F132: =IF(AND(F$123-$S132+1-$B$22>=1,F$123-$S132+1-$B$22<=8),INDEX($C$27:$J$27,1,F$123-$S132+1-$B$22),0)*$U132*F$124 -> 49593.75 | G132: =IF(AND(G$123-$S132+1-$B$22>=1,G$123-$S132+1-$B$22<=8),INDEX($C$27:$J$27,1,G$123-$S132+1-$B$22),0)*$U132*G$124 -> 57032.812 | H132: =IF(AND(H$123-$S132+1-$B$22>=1,H$123-$S132+1-$B$22<=8),INDEX($C$27:$J$27,1,H$123-$S132+1-$B$22),0)*$U132*H$124 -> 65587.734 | I132: =IF(AND(I$123-$S132+1-$B$22>=1,I$123-$S132+1-$B$22<=8),INDEX($C$27:$J$27,1,I$123-$S132+1-$B$22),0)*$U132*I$124 -> 0 | J132: =IF(AND(J$123-$S132+1-$B$22>=1,J$123-$S132+1-$B$22<=8),INDEX($C$27:$J$27,1,J$123-$S132+1-$B$22),0)*$U132*J$124 -> 0 | ... Q132: =IF(AND(Q$123-$S132+1-$B$22>=1,Q$123-$S132+1-$B$22<=8),INDEX($C$27:$J$27,1,Q$123-$S132+1-$B$22),0)*$U132*Q$124 -> 0 | S132: =$B$20+0 -> 2027 | T132: =IF($S132>$B$20+Scenarios!$E$8-1,0,$B$19*(1+$B$21*Scenarios!$E$7)^0) -> 150000 | U132: =IFERROR($T132/INDEX($C$124:$Q$124,1,MATCH($S132,$C$123:$Q$123,0)),0) -> 869.56522 | V132: =SUMPRODUCT(($C$25:$J$25<=$Q$123-$S132+1-$B$22)*$C$27:$J$27)*$U132 -> 869.56522 | W132: =$U132-$V132 -> 0
A133: Refresher grant 2 | C133: =IF(AND(C$123-$S133+1-$B$22>=1,C$123-$S133+1-$B$22<=8),INDEX($C$27:$J$27,1,C$123-$S133+1-$B$22),0)*$U133*C$124 -> 0 | D133: =IF(AND(D$123-$S133+1-$B$22>=1,D$123-$S133+1-$B$22<=8),INDEX($C$27:$J$27,1,D$123-$S133+1-$B$22),0)*$U133*D$124 -> 0 | E133: =IF(AND(E$123-$S133+1-$B$22>=1,E$123-$S133+1-$B$22<=8),INDEX($C$27:$J$27,1,E$123-$S133+1-$B$22),0)*$U133*E$124 -> 0 | F133: =IF(AND(F$123-$S133+1-$B$22>=1,F$123-$S133+1-$B$22<=8),INDEX($C$27:$J$27,1,F$123-$S133+1-$B$22),0)*$U133*F$124 -> 44418.75 | G133: =IF(AND(G$123-$S133+1-$B$22>=1,G$123-$S133+1-$B$22<=8),INDEX($C$27:$J$27,1,G$123-$S133+1-$B$22),0)*$U133*G$124 -> 51081.562 | H133: =IF(AND(H$123-$S133+1-$B$22>=1,H$123-$S133+1-$B$22<=8),INDEX($C$27:$J$27,1,H$123-$S133+1-$B$22),0)*$U133*H$124 -> 58743.797 | I133: =IF(AND(I$123-$S133+1-$B$22>=1,I$123-$S133+1-$B$22<=8),INDEX($C$27:$J$27,1,I$123-$S133+1-$B$22),0)*$U133*I$124 -> 67555.366 | J133: =IF(AND(J$123-$S133+1-$B$22>=1,J$123-$S133+1-$B$22<=8),INDEX($C$27:$J$27,1,J$123-$S133+1-$B$22),0)*$U133*J$124 -> 0 | ... Q133: =IF(AND(Q$123-$S133+1-$B$22>=1,Q$123-$S133+1-$B$22<=8),INDEX($C$27:$J$27,1,Q$123-$S133+1-$B$22),0)*$U133*Q$124 -> 0 | S133: =$B$20+1 -> 2028 | T133: =IF($S133>$B$20+Scenarios!$E$8-1,0,$B$19*(1+$B$21*Scenarios!$E$7)^1) -> 154500 | U133: =IFERROR($T133/INDEX($C$124:$Q$124,1,MATCH($S133,$C$123:$Q$123,0)),0) -> 778.82798 | V133: =SUMPRODUCT(($C$25:$J$25<=$Q$123-$S133+1-$B$22)*$C$27:$J$27)*$U133 -> 778.82798 | W133: =$U133-$V133 -> 0
...

Sheet Offer_2
A1: OFFER 2
A2: Blue = you edit. Black = formula, do not edit. Green = link to another tab. Yellow = key assumption.
A3: INPUTS
A4: Company name | B4: Company B
A5: Ticker | B5: TICKB
A6: Start calendar year | B6: 2026
A7: Base salary at start | B7: 210000
A8: Merit increase %/yr | B8: 0.03
A9: Bonus target % of base | B9: 0.2
A10: Bonus basis (Current or Prior) | B10: Current
A11: Bonus paid in Year 1? (Yes/No) | B11: No
A12: Sign-on total | B12: 75000
A13: Sign-on % paid Year 1 | B13: 0.5
A14: Sign-on % paid Year 2 | B14: 0.5
A15: Sign-on % paid Year 3 | B15: 0
A16: Sign-on check (must equal 100%) | B16: =SUM(B13:B15) -> 1 | C16: =IF(ROUND(B16,6)=1,"OK","ERROR - must total 100%") -> OK
A17: Grant-date share price | B17: 400
A18: Initial grant value ($) | B18: 350000
A19: Refresher value, first grant ($) | B19: 120000
A20: First refresher calendar year | B20: 2027
A21: Refresher grant growth %/yr | B21: 0.03
A22: First vest timing (0 = grant year, 1 = year after) | B22: 1
A23: Share price is entered manually. Replace with a market data lookup in the web app. The original workbook vested in the grant year itself (offset 0); real grants usually vest a year later (offset 1).
A24: VESTING SCHEDULES — % of the grant that vests in each year AFTER the grant date
A25: Years after grant | C25: 1 | D25: 2 | E25: 3 | F25: 4 | G25: 5 | H25: 6 | I25: 7 | J25: 8 | K25: Total
A26: Initial grant | C26: 0.25 | D26: 0.25 | E26: 0.25 | F26: 0.25 | G26: 0 | H26: 0 | I26: 0 | J26: 0 | K26: =SUM(C26:J26) -> 1 | L26: =IF(ROUND(K26,6)=1,"OK","ERROR - must total 100%") -> OK
A27: Refresher grants | C27: 0.25 | D27: 0.25 | E27: 0.25 | F27: 0.25 | G27: 0 | H27: 0 | I27: 0 | J27: 0 | K27: =SUM(C27:J27) -> 1 | L27: =IF(ROUND(K27,6)=1,"OK","ERROR - must total 100%") -> OK
A28: Annual granularity. Sub-annual (quarterly/monthly) vesting and cliffs are handled in the web app, not here.
A31: SCENARIO: CONSERVATIVE | B31: =Scenarios!C$3 -> Conservative
A32: Year index | C32: 1 | D32: 2 | E32: 3 | F32: 4 | G32: 5 | H32: 6 | I32: 7 | J32: 8 | K32: 9 | L32: 10 | M32: 11 | N32: 12 | O32: 13 | P32: 14 | Q32: 15
A33: Calendar year | C33: =$B$6 -> 2026 | D33: =C33+1 -> 2027 | E33: =D33+1 -> 2028 | F33: =E33+1 -> 2029 | G33: =F33+1 -> 2030 | H33: =G33+1 -> 2031 | I33: =H33+1 -> 2032 | J33: =I33+1 -> 2033 | K33: =J33+1 -> 2034 | ... Q33: =P33+1 -> 2040
A34: Share price ($) | C34: =$B$17 -> 400 | D34: =C34*(1+Scenarios!$C$4) -> 400 | E34: =D34*(1+Scenarios!$C$4) -> 400 | F34: =E34*(1+Scenarios!$C$4) -> 400 | G34: =F34*(1+Scenarios!$C$4) -> 400 | H34: =G34*(1+Scenarios!$C$4) -> 400 | I34: =H34*(1+Scenarios!$C$4) -> 400 | J34: =I34*(1+Scenarios!$C$4) -> 400 | K34: =J34*(1+Scenarios!$C$4) -> 400 | ... Q34: =P34*(1+Scenarios!$C$4) -> 400
A35: Base salary | C35: =$B$7 -> 210000 | D35: =C35*(1+$B$8*Scenarios!$C$5) -> 213150 | E35: =D35*(1+$B$8*Scenarios!$C$5) -> 216347.25 | F35: =E35*(1+$B$8*Scenarios!$C$5) -> 219592.46 | G35: =F35*(1+$B$8*Scenarios!$C$5) -> 222886.35 | H35: =G35*(1+$B$8*Scenarios!$C$5) -> 226229.64 | I35: =H35*(1+$B$8*Scenarios!$C$5) -> 229623.09 | J35: =I35*(1+$B$8*Scenarios!$C$5) -> 233067.43 | K35: =J35*(1+$B$8*Scenarios!$C$5) -> 236563.44 | ... Q35: =P35*(1+$B$8*Scenarios!$C$5) -> 258668.7
A36: Bonus basis salary | C36: =IF($B$10="Prior",0,C35) -> 210000 | D36: =IF($B$10="Prior",C35,D35) -> 213150 | E36: =IF($B$10="Prior",D35,E35) -> 216347.25 | F36: =IF($B$10="Prior",E35,F35) -> 219592.46 | G36: =IF($B$10="Prior",F35,G35) -> 222886.35 | H36: =IF($B$10="Prior",G35,H35) -> 226229.64 | I36: =IF($B$10="Prior",H35,I35) -> 229623.09 | J36: =IF($B$10="Prior",I35,J35) -> 233067.43 | K36: =IF($B$10="Prior",J35,K35) -> 236563.44 | ... Q36: =IF($B$10="Prior",P35,Q35) -> 258668.7
A37: Annual bonus | C37: =IF($B$11="No",0,C36*$B$9*Scenarios!$C$6) -> 0 | D37: =D36*$B$9*Scenarios!$C$6 -> 31972.5 | E37: =E36*$B$9*Scenarios!$C$6 -> 32452.088 | F37: =F36*$B$9*Scenarios!$C$6 -> 32938.869 | G37: =G36*$B$9*Scenarios!$C$6 -> 33432.952 | H37: =H36*$B$9*Scenarios!$C$6 -> 33934.446 | I37: =I36*$B$9*Scenarios!$C$6 -> 34443.463 | J37: =J36*$B$9*Scenarios!$C$6 -> 34960.115 | K37: =K36*$B$9*Scenarios!$C$6 -> 35484.516 | ... Q37: =Q36*$B$9*Scenarios!$C$6 -> 38800.306
A38: Sign-on paid | C38: =$B$12*$B$13 -> 37500 | D38: =$B$12*$B$14 -> 37500 | E38: =$B$12*$B$15 -> 0 | F38: 0 | G38: 0 | H38: 0 | I38: 0 | J38: 0 | K38: 0 | L38: 0 | M38: 0 | N38: 0 | O38: 0 | P38: 0 | Q38: 0
A40: GRANT LEDGER — dollar value vesting each year, one row per grant | S40: Grant year | T40: Grant value ($) | U40: Shares granted | V40: Shares vested in horizon | W40: Unvested shares
A41: Initial grant | C41: =IF(AND(C$33-$S41+1-$B$22>=1,C$33-$S41+1-$B$22<=8),INDEX($C$26:$J$26,1,C$33-$S41+1-$B$22),0)*$U41*C$34 -> 0 | D41: =IF(AND(D$33-$S41+1-$B$22>=1,D$33-$S41+1-$B$22<=8),INDEX($C$26:$J$26,1,D$33-$S41+1-$B$22),0)*$U41*D$34 -> 87500 | E41: =IF(AND(E$33-$S41+1-$B$22>=1,E$33-$S41+1-$B$22<=8),INDEX($C$26:$J$26,1,E$33-$S41+1-$B$22),0)*$U41*E$34 -> 87500 | F41: =IF(AND(F$33-$S41+1-$B$22>=1,F$33-$S41+1-$B$22<=8),INDEX($C$26:$J$26,1,F$33-$S41+1-$B$22),0)*$U41*F$34 -> 87500 | G41: =IF(AND(G$33-$S41+1-$B$22>=1,G$33-$S41+1-$B$22<=8),INDEX($C$26:$J$26,1,G$33-$S41+1-$B$22),0)*$U41*G$34 -> 87500 | H41: =IF(AND(H$33-$S41+1-$B$22>=1,H$33-$S41+1-$B$22<=8),INDEX($C$26:$J$26,1,H$33-$S41+1-$B$22),0)*$U41*H$34 -> 0 | I41: =IF(AND(I$33-$S41+1-$B$22>=1,I$33-$S41+1-$B$22<=8),INDEX($C$26:$J$26,1,I$33-$S41+1-$B$22),0)*$U41*I$34 -> 0 | J41: =IF(AND(J$33-$S41+1-$B$22>=1,J$33-$S41+1-$B$22<=8),INDEX($C$26:$J$26,1,J$33-$S41+1-$B$22),0)*$U41*J$34 -> 0 | ... Q41: =IF(AND(Q$33-$S41+1-$B$22>=1,Q$33-$S41+1-$B$22<=8),INDEX($C$26:$J$26,1,Q$33-$S41+1-$B$22),0)*$U41*Q$34 -> 0 | S41: =$B$6 -> 2026 | T41: =$B$18 -> 350000 | U41: =IFERROR(T41/$B$17,0) -> 875 | V41: =SUMPRODUCT(($C$25:$J$25<=$Q$33-$S41+1-$B$22)*$C$26:$J$26)*$U41 -> 875 | W41: =$U41-$V41 -> 0
A42: Refresher grant 1 | C42: =IF(AND(C$33-$S42+1-$B$22>=1,C$33-$S42+1-$B$22<=8),INDEX($C$27:$J$27,1,C$33-$S42+1-$B$22),0)*$U42*C$34 -> 0 | D42: =IF(AND(D$33-$S42+1-$B$22>=1,D$33-$S42+1-$B$22<=8),INDEX($C$27:$J$27,1,D$33-$S42+1-$B$22),0)*$U42*D$34 -> 0 | E42: =IF(AND(E$33-$S42+1-$B$22>=1,E$33-$S42+1-$B$22<=8),INDEX($C$27:$J$27,1,E$33-$S42+1-$B$22),0)*$U42*E$34 -> 30000 | F42: =IF(AND(F$33-$S42+1-$B$22>=1,F$33-$S42+1-$B$22<=8),INDEX($C$27:$J$27,1,F$33-$S42+1-$B$22),0)*$U42*F$34 -> 30000 | G42: =IF(AND(G$33-$S42+1-$B$22>=1,G$33-$S42+1-$B$22<=8),INDEX($C$27:$J$27,1,G$33-$S42+1-$B$22),0)*$U42*G$34 -> 30000 | H42: =IF(AND(H$33-$S42+1-$B$22>=1,H$33-$S42+1-$B$22<=8),INDEX($C$27:$J$27,1,H$33-$S42+1-$B$22),0)*$U42*H$34 -> 30000 | I42: =IF(AND(I$33-$S42+1-$B$22>=1,I$33-$S42+1-$B$22<=8),INDEX($C$27:$J$27,1,I$33-$S42+1-$B$22),0)*$U42*I$34 -> 0 | J42: =IF(AND(J$33-$S42+1-$B$22>=1,J$33-$S42+1-$B$22<=8),INDEX($C$27:$J$27,1,J$33-$S42+1-$B$22),0)*$U42*J$34 -> 0 | ... Q42: =IF(AND(Q$33-$S42+1-$B$22>=1,Q$33-$S42+1-$B$22<=8),INDEX($C$27:$J$27,1,Q$33-$S42+1-$B$22),0)*$U42*Q$34 -> 0 | S42: =$B$20+0 -> 2027 | T42: =IF($S42>$B$20+Scenarios!$C$8-1,0,$B$19*(1+$B$21*Scenarios!$C$7)^0) -> 120000 | U42: =IFERROR($T42/INDEX($C$34:$Q$34,1,MATCH($S42,$C$33:$Q$33,0)),0) -> 300 | V42: =SUMPRODUCT(($C$25:$J$25<=$Q$33-$S42+1-$B$22)*$C$27:$J$27)*$U42 -> 300 | W42: =$U42-$V42 -> 0
A43: Refresher grant 2 | C43: =IF(AND(C$33-$S43+1-$B$22>=1,C$33-$S43+1-$B$22<=8),INDEX($C$27:$J$27,1,C$33-$S43+1-$B$22),0)*$U43*C$34 -> 0 | D43: =IF(AND(D$33-$S43+1-$B$22>=1,D$33-$S43+1-$B$22<=8),INDEX($C$27:$J$27,1,D$33-$S43+1-$B$22),0)*$U43*D$34 -> 0 | E43: =IF(AND(E$33-$S43+1-$B$22>=1,E$33-$S43+1-$B$22<=8),INDEX($C$27:$J$27,1,E$33-$S43+1-$B$22),0)*$U43*E$34 -> 0 | F43: =IF(AND(F$33-$S43+1-$B$22>=1,F$33-$S43+1-$B$22<=8),INDEX($C$27:$J$27,1,F$33-$S43+1-$B$22),0)*$U43*F$34 -> 30000 | G43: =IF(AND(G$33-$S43+1-$B$22>=1,G$33-$S43+1-$B$22<=8),INDEX($C$27:$J$27,1,G$33-$S43+1-$B$22),0)*$U43*G$34 -> 30000 | H43: =IF(AND(H$33-$S43+1-$B$22>=1,H$33-$S43+1-$B$22<=8),INDEX($C$27:$J$27,1,H$33-$S43+1-$B$22),0)*$U43*H$34 -> 30000 | I43: =IF(AND(I$33-$S43+1-$B$22>=1,I$33-$S43+1-$B$22<=8),INDEX($C$27:$J$27,1,I$33-$S43+1-$B$22),0)*$U43*I$34 -> 30000 | J43: =IF(AND(J$33-$S43+1-$B$22>=1,J$33-$S43+1-$B$22<=8),INDEX($C$27:$J$27,1,J$33-$S43+1-$B$22),0)*$U43*J$34 -> 0 | ... Q43: =IF(AND(Q$33-$S43+1-$B$22>=1,Q$33-$S43+1-$B$22<=8),INDEX($C$27:$J$27,1,Q$33-$S43+1-$B$22),0)*$U43*Q$34 -> 0 | S43: =$B$20+1 -> 2028 | T43: =IF($S43>$B$20+Scenarios!$C$8-1,0,$B$19*(1+$B$21*Scenarios!$C$7)^1) -> 120000 | U43: =IFERROR($T43/INDEX($C$34:$Q$34,1,MATCH($S43,$C$33:$Q$33,0)),0) -> 300 | V43: =SUMPRODUCT(($C$25:$J$25<=$Q$33-$S43+1-$B$22)*$C$27:$J$27)*$U43 -> 300 | W43: =$U43-$V43 -> 0
A44: Refresher grant 3 | C44: =IF(AND(C$33-$S44+1-$B$22>=1,C$33-$S44+1-$B$22<=8),INDEX($C$27:$J$27,1,C$33-$S44+1-$B$22),0)*$U44*C$34 -> 0 | D44: =IF(AND(D$33-$S44+1-$B$22>=1,D$33-$S44+1-$B$22<=8),INDEX($C$27:$J$27,1,D$33-$S44+1-$B$22),0)*$U44*D$34 -> 0 | E44: =IF(AND(E$33-$S44+1-$B$22>=1,E$33-$S44+1-$B$22<=8),INDEX($C$27:$J$27,1,E$33-$S44+1-$B$22),0)*$U44*E$34 -> 0 | F44: =IF(AND(F$33-$S44+1-$B$22>=1,F$33-$S44+1-$B$22<=8),INDEX($C$27:$J$27,1,F$33-$S44+1-$B$22),0)*$U44*F$34 -> 0 | G44: =IF(AND(G$33-$S44+1-$B$22>=1,G$33-$S44+1-$B$22<=8),INDEX($C$27:$J$27,1,G$33-$S44+1-$B$22),0)*$U44*G$34 -> 30000 | H44: =IF(AND(H$33-$S44+1-$B$22>=1,H$33-$S44+1-$B$22<=8),INDEX($C$27:$J$27,1,H$33-$S44+1-$B$22),0)*$U44*H$34 -> 30000 | I44: =IF(AND(I$33-$S44+1-$B$22>=1,I$33-$S44+1-$B$22<=8),INDEX($C$27:$J$27,1,I$33-$S44+1-$B$22),0)*$U44*I$34 -> 30000 | J44: =IF(AND(J$33-$S44+1-$B$22>=1,J$33-$S44+1-$B$22<=8),INDEX($C$27:$J$27,1,J$33-$S44+1-$B$22),0)*$U44*J$34 -> 30000 | ... Q44: =IF(AND(Q$33-$S44+1-$B$22>=1,Q$33-$S44+1-$B$22<=8),INDEX($C$27:$J$27,1,Q$33-$S44+1-$B$22),0)*$U44*Q$34 -> 0 | S44: =$B$20+2 -> 2029 | T44: =IF($S44>$B$20+Scenarios!$C$8-1,0,$B$19*(1+$B$21*Scenarios!$C$7)^2) -> 120000 | U44: =IFERROR($T44/INDEX($C$34:$Q$34,1,MATCH($S44,$C$33:$Q$33,0)),0) -> 300 | V44: =SUMPRODUCT(($C$25:$J$25<=$Q$33-$S44+1-$B$22)*$C$27:$J$27)*$U44 -> 300 | W44: =$U44-$V44 -> 0
A45: Refresher grant 4 | C45: =IF(AND(C$33-$S45+1-$B$22>=1,C$33-$S45+1-$B$22<=8),INDEX($C$27:$J$27,1,C$33-$S45+1-$B$22),0)*$U45*C$34 -> 0 | D45: =IF(AND(D$33-$S45+1-$B$22>=1,D$33-$S45+1-$B$22<=8),INDEX($C$27:$J$27,1,D$33-$S45+1-$B$22),0)*$U45*D$34 -> 0 | E45: =IF(AND(E$33-$S45+1-$B$22>=1,E$33-$S45+1-$B$22<=8),INDEX($C$27:$J$27,1,E$33-$S45+1-$B$22),0)*$U45*E$34 -> 0 | F45: =IF(AND(F$33-$S45+1-$B$22>=1,F$33-$S45+1-$B$22<=8),INDEX($C$27:$J$27,1,F$33-$S45+1-$B$22),0)*$U45*F$34 -> 0 | G45: =IF(AND(G$33-$S45+1-$B$22>=1,G$33-$S45+1-$B$22<=8),INDEX($C$27:$J$27,1,G$33-$S45+1-$B$22),0)*$U45*G$34 -> 0 | H45: =IF(AND(H$33-$S45+1-$B$22>=1,H$33-$S45+1-$B$22<=8),INDEX($C$27:$J$27,1,H$33-$S45+1-$B$22),0)*$U45*H$34 -> 30000 | I45: =IF(AND(I$33-$S45+1-$B$22>=1,I$33-$S45+1-$B$22<=8),INDEX($C$27:$J$27,1,I$33-$S45+1-$B$22),0)*$U45*I$34 -> 30000 | J45: =IF(AND(J$33-$S45+1-$B$22>=1,J$33-$S45+1-$B$22<=8),INDEX($C$27:$J$27,1,J$33-$S45+1-$B$22),0)*$U45*J$34 -> 30000 | ... Q45: =IF(AND(Q$33-$S45+1-$B$22>=1,Q$33-$S45+1-$B$22<=8),INDEX($C$27:$J$27,1,Q$33-$S45+1-$B$22),0)*$U45*Q$34 -> 0 | S45: =$B$20+3 -> 2030 | T45: =IF($S45>$B$20+Scenarios!$C$8-1,0,$B$19*(1+$B$21*Scenarios!$C$7)^3) -> 120000 | U45: =IFERROR($T45/INDEX($C$34:$Q$34,1,MATCH($S45,$C$33:$Q$33,0)),0) -> 300 | V45: =SUMPRODUCT(($C$25:$J$25<=$Q$33-$S45+1-$B$22)*$C$27:$J$27)*$U45 -> 300 | W45: =$U45-$V45 -> 0
A46: Refresher grant 5 | C46: =IF(AND(C$33-$S46+1-$B$22>=1,C$33-$S46+1-$B$22<=8),INDEX($C$27:$J$27,1,C$33-$S46+1-$B$22),0)*$U46*C$34 -> 0 | D46: =IF(AND(D$33-$S46+1-$B$22>=1,D$33-$S46+1-$B$22<=8),INDEX($C$27:$J$27,1,D$33-$S46+1-$B$22),0)*$U46*D$34 -> 0 | E46: =IF(AND(E$33-$S46+1-$B$22>=1,E$33-$S46+1-$B$22<=8),INDEX($C$27:$J$27,1,E$33-$S46+1-$B$22),0)*$U46*E$34 -> 0 | F46: =IF(AND(F$33-$S46+1-$B$22>=1,F$33-$S46+1-$B$22<=8),INDEX($C$27:$J$27,1,F$33-$S46+1-$B$22),0)*$U46*F$34 -> 0 | G46: =IF(AND(G$33-$S46+1-$B$22>=1,G$33-$S46+1-$B$22<=8),INDEX($C$27:$J$27,1,G$33-$S46+1-$B$22),0)*$U46*G$34 -> 0 | H46: =IF(AND(H$33-$S46+1-$B$22>=1,H$33-$S46+1-$B$22<=8),INDEX($C$27:$J$27,1,H$33-$S46+1-$B$22),0)*$U46*H$34 -> 0 | I46: =IF(AND(I$33-$S46+1-$B$22>=1,I$33-$S46+1-$B$22<=8),INDEX($C$27:$J$27,1,I$33-$S46+1-$B$22),0)*$U46*I$34 -> 0 | J46: =IF(AND(J$33-$S46+1-$B$22>=1,J$33-$S46+1-$B$22<=8),INDEX($C$27:$J$27,1,J$33-$S46+1-$B$22),0)*$U46*J$34 -> 0 | ... Q46: =IF(AND(Q$33-$S46+1-$B$22>=1,Q$33-$S46+1-$B$22<=8),INDEX($C$27:$J$27,1,Q$33-$S46+1-$B$22),0)*$U46*Q$34 -> 0 | S46: =$B$20+4 -> 2031 | T46: =IF($S46>$B$20+Scenarios!$C$8-1,0,$B$19*(1+$B$21*Scenarios!$C$7)^4) -> 0 | U46: =IFERROR($T46/INDEX($C$34:$Q$34,1,MATCH($S46,$C$33:$Q$33,0)),0) -> 0 | V46: =SUMPRODUCT(($C$25:$J$25<=$Q$33-$S46+1-$B$22)*$C$27:$J$27)*$U46 -> 0 | W46: =$U46-$V46 -> 0
A47: Refresher grant 6 | C47: =IF(AND(C$33-$S47+1-$B$22>=1,C$33-$S47+1-$B$22<=8),INDEX($C$27:$J$27,1,C$33-$S47+1-$B$22),0)*$U47*C$34 -> 0 | D47: =IF(AND(D$33-$S47+1-$B$22>=1,D$33-$S47+1-$B$22<=8),INDEX($C$27:$J$27,1,D$33-$S47+1-$B$22),0)*$U47*D$34 -> 0 | E47: =IF(AND(E$33-$S47+1-$B$22>=1,E$33-$S47+1-$B$22<=8),INDEX($C$27:$J$27,1,E$33-$S47+1-$B$22),0)*$U47*E$34 -> 0 | F47: =IF(AND(F$33-$S47+1-$B$22>=1,F$33-$S47+1-$B$22<=8),INDEX($C$27:$J$27,1,F$33-$S47+1-$B$22),0)*$U47*F$34 -> 0 | G47: =IF(AND(G$33-$S47+1-$B$22>=1,G$33-$S47+1-$B$22<=8),INDEX($C$27:$J$27,1,G$33-$S47+1-$B$22),0)*$U47*G$34 -> 0 | H47: =IF(AND(H$33-$S47+1-$B$22>=1,H$33-$S47+1-$B$22<=8),INDEX($C$27:$J$27,1,H$33-$S47+1-$B$22),0)*$U47*H$34 -> 0 | I47: =IF(AND(I$33-$S47+1-$B$22>=1,I$33-$S47+1-$B$22<=8),INDEX($C$27:$J$27,1,I$33-$S47+1-$B$22),0)*$U47*I$34 -> 0 | J47: =IF(AND(J$33-$S47+1-$B$22>=1,J$33-$S47+1-$B$22<=8),INDEX($C$27:$J$27,1,J$33-$S47+1-$B$22),0)*$U47*J$34 -> 0 | ... Q47: =IF(AND(Q$33-$S47+1-$B$22>=1,Q$33-$S47+1-$B$22<=8),INDEX($C$27:$J$27,1,Q$33-$S47+1-$B$22),0)*$U47*Q$34 -> 0 | S47: =$B$20+5 -> 2032 | T47: =IF($S47>$B$20+Scenarios!$C$8-1,0,$B$19*(1+$B$21*Scenarios!$C$7)^5) -> 0 | U47: =IFERROR($T47/INDEX($C$34:$Q$34,1,MATCH($S47,$C$33:$Q$33,0)),0) -> 0 | V47: =SUMPRODUCT(($C$25:$J$25<=$Q$33-$S47+1-$B$22)*$C$27:$J$27)*$U47 -> 0 | W47: =$U47-$V47 -> 0
A48: Refresher grant 7 | C48: =IF(AND(C$33-$S48+1-$B$22>=1,C$33-$S48+1-$B$22<=8),INDEX($C$27:$J$27,1,C$33-$S48+1-$B$22),0)*$U48*C$34 -> 0 | D48: =IF(AND(D$33-$S48+1-$B$22>=1,D$33-$S48+1-$B$22<=8),INDEX($C$27:$J$27,1,D$33-$S48+1-$B$22),0)*$U48*D$34 -> 0 | E48: =IF(AND(E$33-$S48+1-$B$22>=1,E$33-$S48+1-$B$22<=8),INDEX($C$27:$J$27,1,E$33-$S48+1-$B$22),0)*$U48*E$34 -> 0 | F48: =IF(AND(F$33-$S48+1-$B$22>=1,F$33-$S48+1-$B$22<=8),INDEX($C$27:$J$27,1,F$33-$S48+1-$B$22),0)*$U48*F$34 -> 0 | G48: =IF(AND(G$33-$S48+1-$B$22>=1,G$33-$S48+1-$B$22<=8),INDEX($C$27:$J$27,1,G$33-$S48+1-$B$22),0)*$U48*G$34 -> 0 | H48: =IF(AND(H$33-$S48+1-$B$22>=1,H$33-$S48+1-$B$22<=8),INDEX($C$27:$J$27,1,H$33-$S48+1-$B$22),0)*$U48*H$34 -> 0 | I48: =IF(AND(I$33-$S48+1-$B$22>=1,I$33-$S48+1-$B$22<=8),INDEX($C$27:$J$27,1,I$33-$S48+1-$B$22),0)*$U48*I$34 -> 0 | J48: =IF(AND(J$33-$S48+1-$B$22>=1,J$33-$S48+1-$B$22<=8),INDEX($C$27:$J$27,1,J$33-$S48+1-$B$22),0)*$U48*J$34 -> 0 | ... Q48: =IF(AND(Q$33-$S48+1-$B$22>=1,Q$33-$S48+1-$B$22<=8),INDEX($C$27:$J$27,1,Q$33-$S48+1-$B$22),0)*$U48*Q$34 -> 0 | S48: =$B$20+6 -> 2033 | T48: =IF($S48>$B$20+Scenarios!$C$8-1,0,$B$19*(1+$B$21*Scenarios!$C$7)^6) -> 0 | U48: =IFERROR($T48/INDEX($C$34:$Q$34,1,MATCH($S48,$C$33:$Q$33,0)),0) -> 0 | V48: =SUMPRODUCT(($C$25:$J$25<=$Q$33-$S48+1-$B$22)*$C$27:$J$27)*$U48 -> 0 | W48: =$U48-$V48 -> 0
A49: Refresher grant 8 | C49: =IF(AND(C$33-$S49+1-$B$22>=1,C$33-$S49+1-$B$22<=8),INDEX($C$27:$J$27,1,C$33-$S49+1-$B$22),0)*$U49*C$34 -> 0 | D49: =IF(AND(D$33-$S49+1-$B$22>=1,D$33-$S49+1-$B$22<=8),INDEX($C$27:$J$27,1,D$33-$S49+1-$B$22),0)*$U49*D$34 -> 0 | E49: =IF(AND(E$33-$S49+1-$B$22>=1,E$33-$S49+1-$B$22<=8),INDEX($C$27:$J$27,1,E$33-$S49+1-$B$22),0)*$U49*E$34 -> 0 | F49: =IF(AND(F$33-$S49+1-$B$22>=1,F$33-$S49+1-$B$22<=8),INDEX($C$27:$J$27,1,F$33-$S49+1-$B$22),0)*$U49*F$34 -> 0 | G49: =IF(AND(G$33-$S49+1-$B$22>=1,G$33-$S49+1-$B$22<=8),INDEX($C$27:$J$27,1,G$33-$S49+1-$B$22),0)*$U49*G$34 -> 0 | H49: =IF(AND(H$33-$S49+1-$B$22>=1,H$33-$S49+1-$B$22<=8),INDEX($C$27:$J$27,1,H$33-$S49+1-$B$22),0)*$U49*H$34 -> 0 | I49: =IF(AND(I$33-$S49+1-$B$22>=1,I$33-$S49+1-$B$22<=8),INDEX($C$27:$J$27,1,I$33-$S49+1-$B$22),0)*$U49*I$34 -> 0 | J49: =IF(AND(J$33-$S49+1-$B$22>=1,J$33-$S49+1-$B$22<=8),INDEX($C$27:$J$27,1,J$33-$S49+1-$B$22),0)*$U49*J$34 -> 0 | ... Q49: =IF(AND(Q$33-$S49+1-$B$22>=1,Q$33-$S49+1-$B$22<=8),INDEX($C$27:$J$27,1,Q$33-$S49+1-$B$22),0)*$U49*Q$34 -> 0 | S49: =$B$20+7 -> 2034 | T49: =IF($S49>$B$20+Scenarios!$C$8-1,0,$B$19*(1+$B$21*Scenarios!$C$7)^7) -> 0 | U49: =IFERROR($T49/INDEX($C$34:$Q$34,1,MATCH($S49,$C$33:$Q$33,0)),0) -> 0 | V49: =SUMPRODUCT(($C$25:$J$25<=$Q$33-$S49+1-$B$22)*$C$27:$J$27)*$U49 -> 0 | W49: =$U49-$V49 -> 0
A50: Refresher grant 9 | C50: =IF(AND(C$33-$S50+1-$B$22>=1,C$33-$S50+1-$B$22<=8),INDEX($C$27:$J$27,1,C$33-$S50+1-$B$22),0)*$U50*C$34 -> 0 | D50: =IF(AND(D$33-$S50+1-$B$22>=1,D$33-$S50+1-$B$22<=8),INDEX($C$27:$J$27,1,D$33-$S50+1-$B$22),0)*$U50*D$34 -> 0 | E50: =IF(AND(E$33-$S50+1-$B$22>=1,E$33-$S50+1-$B$22<=8),INDEX($C$27:$J$27,1,E$33-$S50+1-$B$22),0)*$U50*E$34 -> 0 | F50: =IF(AND(F$33-$S50+1-$B$22>=1,F$33-$S50+1-$B$22<=8),INDEX($C$27:$J$27,1,F$33-$S50+1-$B$22),0)*$U50*F$34 -> 0 | G50: =IF(AND(G$33-$S50+1-$B$22>=1,G$33-$S50+1-$B$22<=8),INDEX($C$27:$J$27,1,G$33-$S50+1-$B$22),0)*$U50*G$34 -> 0 | H50: =IF(AND(H$33-$S50+1-$B$22>=1,H$33-$S50+1-$B$22<=8),INDEX($C$27:$J$27,1,H$33-$S50+1-$B$22),0)*$U50*H$34 -> 0 | I50: =IF(AND(I$33-$S50+1-$B$22>=1,I$33-$S50+1-$B$22<=8),INDEX($C$27:$J$27,1,I$33-$S50+1-$B$22),0)*$U50*I$34 -> 0 | J50: =IF(AND(J$33-$S50+1-$B$22>=1,J$33-$S50+1-$B$22<=8),INDEX($C$27:$J$27,1,J$33-$S50+1-$B$22),0)*$U50*J$34 -> 0 | ... Q50: =IF(AND(Q$33-$S50+1-$B$22>=1,Q$33-$S50+1-$B$22<=8),INDEX($C$27:$J$27,1,Q$33-$S50+1-$B$22),0)*$U50*Q$34 -> 0 | S50: =$B$20+8 -> 2035 | T50: =IF($S50>$B$20+Scenarios!$C$8-1,0,$B$19*(1+$B$21*Scenarios!$C$7)^8) -> 0 | U50: =IFERROR($T50/INDEX($C$34:$Q$34,1,MATCH($S50,$C$33:$Q$33,0)),0) -> 0 | V50: =SUMPRODUCT(($C$25:$J$25<=$Q$33-$S50+1-$B$22)*$C$27:$J$27)*$U50 -> 0 | W50: =$U50-$V50 -> 0
A51: Refresher grant 10 | C51: =IF(AND(C$33-$S51+1-$B$22>=1,C$33-$S51+1-$B$22<=8),INDEX($C$27:$J$27,1,C$33-$S51+1-$B$22),0)*$U51*C$34 -> 0 | D51: =IF(AND(D$33-$S51+1-$B$22>=1,D$33-$S51+1-$B$22<=8),INDEX($C$27:$J$27,1,D$33-$S51+1-$B$22),0)*$U51*D$34 -> 0 | E51: =IF(AND(E$33-$S51+1-$B$22>=1,E$33-$S51+1-$B$22<=8),INDEX($C$27:$J$27,1,E$33-$S51+1-$B$22),0)*$U51*E$34 -> 0 | F51: =IF(AND(F$33-$S51+1-$B$22>=1,F$33-$S51+1-$B$22<=8),INDEX($C$27:$J$27,1,F$33-$S51+1-$B$22),0)*$U51*F$34 -> 0 | G51: =IF(AND(G$33-$S51+1-$B$22>=1,G$33-$S51+1-$B$22<=8),INDEX($C$27:$J$27,1,G$33-$S51+1-$B$22),0)*$U51*G$34 -> 0 | H51: =IF(AND(H$33-$S51+1-$B$22>=1,H$33-$S51+1-$B$22<=8),INDEX($C$27:$J$27,1,H$33-$S51+1-$B$22),0)*$U51*H$34 -> 0 | I51: =IF(AND(I$33-$S51+1-$B$22>=1,I$33-$S51+1-$B$22<=8),INDEX($C$27:$J$27,1,I$33-$S51+1-$B$22),0)*$U51*I$34 -> 0 | J51: =IF(AND(J$33-$S51+1-$B$22>=1,J$33-$S51+1-$B$22<=8),INDEX($C$27:$J$27,1,J$33-$S51+1-$B$22),0)*$U51*J$34 -> 0 | ... Q51: =IF(AND(Q$33-$S51+1-$B$22>=1,Q$33-$S51+1-$B$22<=8),INDEX($C$27:$J$27,1,Q$33-$S51+1-$B$22),0)*$U51*Q$34 -> 0 | S51: =$B$20+9 -> 2036 | T51: =IF($S51>$B$20+Scenarios!$C$8-1,0,$B$19*(1+$B$21*Scenarios!$C$7)^9) -> 0 | U51: =IFERROR($T51/INDEX($C$34:$Q$34,1,MATCH($S51,$C$33:$Q$33,0)),0) -> 0 | V51: =SUMPRODUCT(($C$25:$J$25<=$Q$33-$S51+1-$B$22)*$C$27:$J$27)*$U51 -> 0 | W51: =$U51-$V51 -> 0
A52: Refresher grant 11 | C52: =IF(AND(C$33-$S52+1-$B$22>=1,C$33-$S52+1-$B$22<=8),INDEX($C$27:$J$27,1,C$33-$S52+1-$B$22),0)*$U52*C$34 -> 0 | D52: =IF(AND(D$33-$S52+1-$B$22>=1,D$33-$S52+1-$B$22<=8),INDEX($C$27:$J$27,1,D$33-$S52+1-$B$22),0)*$U52*D$34 -> 0 | E52: =IF(AND(E$33-$S52+1-$B$22>=1,E$33-$S52+1-$B$22<=8),INDEX($C$27:$J$27,1,E$33-$S52+1-$B$22),0)*$U52*E$34 -> 0 | F52: =IF(AND(F$33-$S52+1-$B$22>=1,F$33-$S52+1-$B$22<=8),INDEX($C$27:$J$27,1,F$33-$S52+1-$B$22),0)*$U52*F$34 -> 0 | G52: =IF(AND(G$33-$S52+1-$B$22>=1,G$33-$S52+1-$B$22<=8),INDEX($C$27:$J$27,1,G$33-$S52+1-$B$22),0)*$U52*G$34 -> 0 | H52: =IF(AND(H$33-$S52+1-$B$22>=1,H$33-$S52+1-$B$22<=8),INDEX($C$27:$J$27,1,H$33-$S52+1-$B$22),0)*$U52*H$34 -> 0 | I52: =IF(AND(I$33-$S52+1-$B$22>=1,I$33-$S52+1-$B$22<=8),INDEX($C$27:$J$27,1,I$33-$S52+1-$B$22),0)*$U52*I$34 -> 0 | J52: =IF(AND(J$33-$S52+1-$B$22>=1,J$33-$S52+1-$B$22<=8),INDEX($C$27:$J$27,1,J$33-$S52+1-$B$22),0)*$U52*J$34 -> 0 | ... Q52: =IF(AND(Q$33-$S52+1-$B$22>=1,Q$33-$S52+1-$B$22<=8),INDEX($C$27:$J$27,1,Q$33-$S52+1-$B$22),0)*$U52*Q$34 -> 0 | S52: =$B$20+10 -> 2037 | T52: =IF($S52>$B$20+Scenarios!$C$8-1,0,$B$19*(1+$B$21*Scenarios!$C$7)^10) -> 0 | U52: =IFERROR($T52/INDEX($C$34:$Q$34,1,MATCH($S52,$C$33:$Q$33,0)),0) -> 0 | V52: =SUMPRODUCT(($C$25:$J$25<=$Q$33-$S52+1-$B$22)*$C$27:$J$27)*$U52 -> 0 | W52: =$U52-$V52 -> 0
A53: Refresher grant 12 | C53: =IF(AND(C$33-$S53+1-$B$22>=1,C$33-$S53+1-$B$22<=8),INDEX($C$27:$J$27,1,C$33-$S53+1-$B$22),0)*$U53*C$34 -> 0 | D53: =IF(AND(D$33-$S53+1-$B$22>=1,D$33-$S53+1-$B$22<=8),INDEX($C$27:$J$27,1,D$33-$S53+1-$B$22),0)*$U53*D$34 -> 0 | E53: =IF(AND(E$33-$S53+1-$B$22>=1,E$33-$S53+1-$B$22<=8),INDEX($C$27:$J$27,1,E$33-$S53+1-$B$22),0)*$U53*E$34 -> 0 | F53: =IF(AND(F$33-$S53+1-$B$22>=1,F$33-$S53+1-$B$22<=8),INDEX($C$27:$J$27,1,F$33-$S53+1-$B$22),0)*$U53*F$34 -> 0 | G53: =IF(AND(G$33-$S53+1-$B$22>=1,G$33-$S53+1-$B$22<=8),INDEX($C$27:$J$27,1,G$33-$S53+1-$B$22),0)*$U53*G$34 -> 0 | H53: =IF(AND(H$33-$S53+1-$B$22>=1,H$33-$S53+1-$B$22<=8),INDEX($C$27:$J$27,1,H$33-$S53+1-$B$22),0)*$U53*H$34 -> 0 | I53: =IF(AND(I$33-$S53+1-$B$22>=1,I$33-$S53+1-$B$22<=8),INDEX($C$27:$J$27,1,I$33-$S53+1-$B$22),0)*$U53*I$34 -> 0 | J53: =IF(AND(J$33-$S53+1-$B$22>=1,J$33-$S53+1-$B$22<=8),INDEX($C$27:$J$27,1,J$33-$S53+1-$B$22),0)*$U53*J$34 -> 0 | ... Q53: =IF(AND(Q$33-$S53+1-$B$22>=1,Q$33-$S53+1-$B$22<=8),INDEX($C$27:$J$27,1,Q$33-$S53+1-$B$22),0)*$U53*Q$34 -> 0 | S53: =$B$20+11 -> 2038 | T53: =IF($S53>$B$20+Scenarios!$C$8-1,0,$B$19*(1+$B$21*Scenarios!$C$7)^11) -> 0 | U53: =IFERROR($T53/INDEX($C$34:$Q$34,1,MATCH($S53,$C$33:$Q$33,0)),0) -> 0 | V53: =SUMPRODUCT(($C$25:$J$25<=$Q$33-$S53+1-$B$22)*$C$27:$J$27)*$U53 -> 0 | W53: =$U53-$V53 -> 0
A55: Initial grant vest ($) | C55: =C41 -> 0 | D55: =D41 -> 87500 | E55: =E41 -> 87500 | F55: =F41 -> 87500 | G55: =G41 -> 87500 | H55: =H41 -> 0 | I55: =I41 -> 0 | J55: =J41 -> 0 | ... Q55: =Q41 -> 0
A56: Refresher vest ($) | C56: =SUM(C42:C53) -> 0 | D56: =SUM(D42:D53) -> 0 | E56: =SUM(E42:E53) -> 30000 | F56: =SUM(F42:F53) -> 60000 | G56: =SUM(G42:G53) -> 90000 | H56: =SUM(H42:H53) -> 120000 | I56: =SUM(I42:I53) -> 90000 | J56: =SUM(J42:J53) -> 60000 | ... Q56: =SUM(Q42:Q53) -> 0
A57: Total equity vest ($) | C57: =C55+C56 -> 0 | D57: =D55+D56 -> 87500 | E57: =E55+E56 -> 117500 | F57: =F55+F56 -> 147500 | G57: =G55+G56 -> 177500 | H57: =H55+H56 -> 120000 | I57: =I55+I56 -> 90000 | J57: =J55+J56 -> 60000 | ... Q57: =Q55+Q56 -> 0
A58: Concurrent grants vesting (count) | C58: =SUMPRODUCT((C41:C53>0)*1) -> 0 | D58: =SUMPRODUCT((D41:D53>0)*1) -> 1 | E58: =SUMPRODUCT((E41:E53>0)*1) -> 2 | F58: =SUMPRODUCT((F41:F53>0)*1) -> 3 | G58: =SUMPRODUCT((G41:G53>0)*1) -> 4 | H58: =SUMPRODUCT((H41:H53>0)*1) -> 4 | I58: =SUMPRODUCT((I41:I53>0)*1) -> 3 | J58: =SUMPRODUCT((J41:J53>0)*1) -> 2 | ... Q58: =SUMPRODUCT((Q41:Q53>0)*1) -> 0
A60: TOTAL GROSS COMPENSATION | C60: =C35+C37+C38+C57 -> 247500 | D60: =D35+D37+D38+D57 -> 370122.5 | E60: =E35+E37+E38+E57 -> 366299.34 | F60: =F35+F37+F38+F57 -> 400031.33 | G60: =G35+G37+G38+G57 -> 433819.3 | H60: =H35+H37+H38+H57 -> 380164.09 | I60: =I35+I37+I38+I57 -> 354066.55 | J60: =J35+J37+J38+J57 -> 328027.55 | ... Q60: =Q35+Q37+Q38+Q57 -> 297469.01
A61: Cumulative gross | C61: =C60 -> 247500 | D61: =C61+D60 -> 617622.5 | E61: =D61+E60 -> 983921.84 | F61: =E61+F60 -> 1383953.2 | G61: =F61+G60 -> 1817772.5 | H61: =G61+H60 -> 2197936.5 | I61: =H61+I60 -> 2552003.1 | J61: =I61+J60 -> 2880030.6 | K61: =J61+K60 -> 3182078.6 | ... Q61: =P61+Q60 -> 4902236.3
A63: Unvested shares at end of horizon | B63: =SUM(W41:W53) -> 0
A64: Unvested equity value at horizon price | B64: =B63*$Q$34 -> 0
A76: SCENARIO: MEDIUM | B76: =Scenarios!D$3 -> Medium
A77: Year index | C77: 1 | D77: 2 | E77: 3 | F77: 4 | G77: 5 | H77: 6 | I77: 7 | J77: 8 | K77: 9 | L77: 10 | M77: 11 | N77: 12 | O77: 13 | P77: 14 | Q77: 15
A78: Calendar year | C78: =$B$6 -> 2026 | D78: =C78+1 -> 2027 | E78: =D78+1 -> 2028 | F78: =E78+1 -> 2029 | G78: =F78+1 -> 2030 | H78: =G78+1 -> 2031 | I78: =H78+1 -> 2032 | J78: =I78+1 -> 2033 | K78: =J78+1 -> 2034 | ... Q78: =P78+1 -> 2040
A79: Share price ($) | C79: =$B$17 -> 400 | D79: =C79*(1+Scenarios!$D$4) -> 428 | E79: =D79*(1+Scenarios!$D$4) -> 457.96 | F79: =E79*(1+Scenarios!$D$4) -> 490.0172 | G79: =F79*(1+Scenarios!$D$4) -> 524.3184 | H79: =G79*(1+Scenarios!$D$4) -> 561.02069 | I79: =H79*(1+Scenarios!$D$4) -> 600.29214 | J79: =I79*(1+Scenarios!$D$4) -> 642.31259 | K79: =J79*(1+Scenarios!$D$4) -> 687.27447 | ... Q79: =P79*(1+Scenarios!$D$4) -> 1031.4137
A80: Base salary | C80: =$B$7 -> 210000 | D80: =C80*(1+$B$8*Scenarios!$D$5) -> 216300 | E80: =D80*(1+$B$8*Scenarios!$D$5) -> 222789 | F80: =E80*(1+$B$8*Scenarios!$D$5) -> 229472.67 | G80: =F80*(1+$B$8*Scenarios!$D$5) -> 236356.85 | H80: =G80*(1+$B$8*Scenarios!$D$5) -> 243447.56 | I80: =H80*(1+$B$8*Scenarios!$D$5) -> 250750.98 | J80: =I80*(1+$B$8*Scenarios!$D$5) -> 258273.51 | K80: =J80*(1+$B$8*Scenarios!$D$5) -> 266021.72 | ... Q80: =P80*(1+$B$8*Scenarios!$D$5) -> 317643.84
A81: Bonus basis salary | C81: =IF($B$10="Prior",0,C80) -> 210000 | D81: =IF($B$10="Prior",C80,D80) -> 216300 | E81: =IF($B$10="Prior",D80,E80) -> 222789 | F81: =IF($B$10="Prior",E80,F80) -> 229472.67 | G81: =IF($B$10="Prior",F80,G80) -> 236356.85 | H81: =IF($B$10="Prior",G80,H80) -> 243447.56 | I81: =IF($B$10="Prior",H80,I80) -> 250750.98 | J81: =IF($B$10="Prior",I80,J80) -> 258273.51 | K81: =IF($B$10="Prior",J80,K80) -> 266021.72 | ... Q81: =IF($B$10="Prior",P80,Q80) -> 317643.84
A82: Annual bonus | C82: =IF($B$11="No",0,C81*$B$9*Scenarios!$D$6) -> 0 | D82: =D81*$B$9*Scenarios!$D$6 -> 43260 | E82: =E81*$B$9*Scenarios!$D$6 -> 44557.8 | F82: =F81*$B$9*Scenarios!$D$6 -> 45894.534 | G82: =G81*$B$9*Scenarios!$D$6 -> 47271.37 | H82: =H81*$B$9*Scenarios!$D$6 -> 48689.511 | I82: =I81*$B$9*Scenarios!$D$6 -> 50150.196 | J82: =J81*$B$9*Scenarios!$D$6 -> 51654.702 | K82: =K81*$B$9*Scenarios!$D$6 -> 53204.343 | ... Q82: =Q81*$B$9*Scenarios!$D$6 -> 63528.768
A83: Sign-on paid | C83: =$B$12*$B$13 -> 37500 | D83: =$B$12*$B$14 -> 37500 | E83: =$B$12*$B$15 -> 0 | F83: 0 | G83: 0 | H83: 0 | I83: 0 | J83: 0 | K83: 0 | L83: 0 | M83: 0 | N83: 0 | O83: 0 | P83: 0 | Q83: 0
A85: GRANT LEDGER — dollar value vesting each year, one row per grant | S85: Grant year | T85: Grant value ($) | U85: Shares granted | V85: Shares vested in horizon | W85: Unvested shares
A86: Initial grant | C86: =IF(AND(C$78-$S86+1-$B$22>=1,C$78-$S86+1-$B$22<=8),INDEX($C$26:$J$26,1,C$78-$S86+1-$B$22),0)*$U86*C$79 -> 0 | D86: =IF(AND(D$78-$S86+1-$B$22>=1,D$78-$S86+1-$B$22<=8),INDEX($C$26:$J$26,1,D$78-$S86+1-$B$22),0)*$U86*D$79 -> 93625 | E86: =IF(AND(E$78-$S86+1-$B$22>=1,E$78-$S86+1-$B$22<=8),INDEX($C$26:$J$26,1,E$78-$S86+1-$B$22),0)*$U86*E$79 -> 100178.75 | F86: =IF(AND(F$78-$S86+1-$B$22>=1,F$78-$S86+1-$B$22<=8),INDEX($C$26:$J$26,1,F$78-$S86+1-$B$22),0)*$U86*F$79 -> 107191.26 | G86: =IF(AND(G$78-$S86+1-$B$22>=1,G$78-$S86+1-$B$22<=8),INDEX($C$26:$J$26,1,G$78-$S86+1-$B$22),0)*$U86*G$79 -> 114694.65 | H86: =IF(AND(H$78-$S86+1-$B$22>=1,H$78-$S86+1-$B$22<=8),INDEX($C$26:$J$26,1,H$78-$S86+1-$B$22),0)*$U86*H$79 -> 0 | I86: =IF(AND(I$78-$S86+1-$B$22>=1,I$78-$S86+1-$B$22<=8),INDEX($C$26:$J$26,1,I$78-$S86+1-$B$22),0)*$U86*I$79 -> 0 | J86: =IF(AND(J$78-$S86+1-$B$22>=1,J$78-$S86+1-$B$22<=8),INDEX($C$26:$J$26,1,J$78-$S86+1-$B$22),0)*$U86*J$79 -> 0 | ... Q86: =IF(AND(Q$78-$S86+1-$B$22>=1,Q$78-$S86+1-$B$22<=8),INDEX($C$26:$J$26,1,Q$78-$S86+1-$B$22),0)*$U86*Q$79 -> 0 | S86: =$B$6 -> 2026 | T86: =$B$18 -> 350000 | U86: =IFERROR(T86/$B$17,0) -> 875 | V86: =SUMPRODUCT(($C$25:$J$25<=$Q$78-$S86+1-$B$22)*$C$26:$J$26)*$U86 -> 875 | W86: =$U86-$V86 -> 0
A87: Refresher grant 1 | C87: =IF(AND(C$78-$S87+1-$B$22>=1,C$78-$S87+1-$B$22<=8),INDEX($C$27:$J$27,1,C$78-$S87+1-$B$22),0)*$U87*C$79 -> 0 | D87: =IF(AND(D$78-$S87+1-$B$22>=1,D$78-$S87+1-$B$22<=8),INDEX($C$27:$J$27,1,D$78-$S87+1-$B$22),0)*$U87*D$79 -> 0 | E87: =IF(AND(E$78-$S87+1-$B$22>=1,E$78-$S87+1-$B$22<=8),INDEX($C$27:$J$27,1,E$78-$S87+1-$B$22),0)*$U87*E$79 -> 32100 | F87: =IF(AND(F$78-$S87+1-$B$22>=1,F$78-$S87+1-$B$22<=8),INDEX($C$27:$J$27,1,F$78-$S87+1-$B$22),0)*$U87*F$79 -> 34347 | G87: =IF(AND(G$78-$S87+1-$B$22>=1,G$78-$S87+1-$B$22<=8),INDEX($C$27:$J$27,1,G$78-$S87+1-$B$22),0)*$U87*G$79 -> 36751.29 | H87: =IF(AND(H$78-$S87+1-$B$22>=1,H$78-$S87+1-$B$22<=8),INDEX($C$27:$J$27,1,H$78-$S87+1-$B$22),0)*$U87*H$79 -> 39323.88 | I87: =IF(AND(I$78-$S87+1-$B$22>=1,I$78-$S87+1-$B$22<=8),INDEX($C$27:$J$27,1,I$78-$S87+1-$B$22),0)*$U87*I$79 -> 0 | J87: =IF(AND(J$78-$S87+1-$B$22>=1,J$78-$S87+1-$B$22<=8),INDEX($C$27:$J$27,1,J$78-$S87+1-$B$22),0)*$U87*J$79 -> 0 | ... Q87: =IF(AND(Q$78-$S87+1-$B$22>=1,Q$78-$S87+1-$B$22<=8),INDEX($C$27:$J$27,1,Q$78-$S87+1-$B$22),0)*$U87*Q$79 -> 0 | S87: =$B$20+0 -> 2027 | T87: =IF($S87>$B$20+Scenarios!$D$8-1,0,$B$19*(1+$B$21*Scenarios!$D$7)^0) -> 120000 | U87: =IFERROR($T87/INDEX($C$79:$Q$79,1,MATCH($S87,$C$78:$Q$78,0)),0) -> 280.37383 | V87: =SUMPRODUCT(($C$25:$J$25<=$Q$78-$S87+1-$B$22)*$C$27:$J$27)*$U87 -> 280.37383 | W87: =$U87-$V87 -> 0
A88: Refresher grant 2 | C88: =IF(AND(C$78-$S88+1-$B$22>=1,C$78-$S88+1-$B$22<=8),INDEX($C$27:$J$27,1,C$78-$S88+1-$B$22),0)*$U88*C$79 -> 0 | D88: =IF(AND(D$78-$S88+1-$B$22>=1,D$78-$S88+1-$B$22<=8),INDEX($C$27:$J$27,1,D$78-$S88+1-$B$22),0)*$U88*D$79 -> 0 | E88: =IF(AND(E$78-$S88+1-$B$22>=1,E$78-$S88+1-$B$22<=8),INDEX($C$27:$J$27,1,E$78-$S88+1-$B$22),0)*$U88*E$79 -> 0 | F88: =IF(AND(F$78-$S88+1-$B$22>=1,F$78-$S88+1-$B$22<=8),INDEX($C$27:$J$27,1,F$78-$S88+1-$B$22),0)*$U88*F$79 -> 33063 | G88: =IF(AND(G$78-$S88+1-$B$22>=1,G$78-$S88+1-$B$22<=8),INDEX($C$27:$J$27,1,G$78-$S88+1-$B$22),0)*$U88*G$79 -> 35377.41 | H88: =IF(AND(H$78-$S88+1-$B$22>=1,H$78-$S88+1-$B$22<=8),INDEX($C$27:$J$27,1,H$78-$S88+1-$B$22),0)*$U88*H$79 -> 37853.829 | I88: =IF(AND(I$78-$S88+1-$B$22>=1,I$78-$S88+1-$B$22<=8),INDEX($C$27:$J$27,1,I$78-$S88+1-$B$22),0)*$U88*I$79 -> 40503.597 | J88: =IF(AND(J$78-$S88+1-$B$22>=1,J$78-$S88+1-$B$22<=8),INDEX($C$27:$J$27,1,J$78-$S88+1-$B$22),0)*$U88*J$79 -> 0 | ... Q88: =IF(AND(Q$78-$S88+1-$B$22>=1,Q$78-$S88+1-$B$22<=8),INDEX($C$27:$J$27,1,Q$78-$S88+1-$B$22),0)*$U88*Q$79 -> 0 | S88: =$B$20+1 -> 2028 | T88: =IF($S88>$B$20+Scenarios!$D$8-1,0,$B$19*(1+$B$21*Scenarios!$D$7)^1) -> 123600 | U88: =IFERROR($T88/INDEX($C$79:$Q$79,1,MATCH($S88,$C$78:$Q$78,0)),0) -> 269.89257 | V88: =SUMPRODUCT(($C$25:$J$25<=$Q$78-$S88+1-$B$22)*$C$27:$J$27)*$U88 -> 269.89257 | W88: =$U88-$V88 -> 0
A89: Refresher grant 3 | C89: =IF(AND(C$78-$S89+1-$B$22>=1,C$78-$S89+1-$B$22<=8),INDEX($C$27:$J$27,1,C$78-$S89+1-$B$22),0)*$U89*C$79 -> 0 | D89: =IF(AND(D$78-$S89+1-$B$22>=1,D$78-$S89+1-$B$22<=8),INDEX($C$27:$J$27,1,D$78-$S89+1-$B$22),0)*$U89*D$79 -> 0 | E89: =IF(AND(E$78-$S89+1-$B$22>=1,E$78-$S89+1-$B$22<=8),INDEX($C$27:$J$27,1,E$78-$S89+1-$B$22),0)*$U89*E$79 -> 0 | F89: =IF(AND(F$78-$S89+1-$B$22>=1,F$78-$S89+1-$B$22<=8),INDEX($C$27:$J$27,1,F$78-$S89+1-$B$22),0)*$U89*F$79 -> 0 | G89: =IF(AND(G$78-$S89+1-$B$22>=1,G$78-$S89+1-$B$22<=8),INDEX($C$27:$J$27,1,G$78-$S89+1-$B$22),0)*$U89*G$79 -> 34054.89 | H89: =IF(AND(H$78-$S89+1-$B$22>=1,H$78-$S89+1-$B$22<=8),INDEX($C$27:$J$27,1,H$78-$S89+1-$B$22),0)*$U89*H$79 -> 36438.732 | I89: =IF(AND(I$78-$S89+1-$B$22>=1,I$78-$S89+1-$B$22<=8),INDEX($C$27:$J$27,1,I$78-$S89+1-$B$22),0)*$U89*I$79 -> 38989.444 | J89: =IF(AND(J$78-$S89+1-$B$22>=1,J$78-$S89+1-$B$22<=8),INDEX($C$27:$J$27,1,J$78-$S89+1-$B$22),0)*$U89*J$79 -> 41718.705 | ... Q89: =IF(AND(Q$78-$S89+1-$B$22>=1,Q$78-$S89+1-$B$22<=8),INDEX($C$27:$J$27,1,Q$78-$S89+1-$B$22),0)*$U89*Q$79 -> 0 | S89: =$B$20+2 -> 2029 | T89: =IF($S89>$B$20+Scenarios!$D$8-1,0,$B$19*(1+$B$21*Scenarios!$D$7)^2) -> 127308 | U89: =IFERROR($T89/INDEX($C$79:$Q$79,1,MATCH($S89,$C$78:$Q$78,0)),0) -> 259.80313 | V89: =SUMPRODUCT(($C$25:$J$25<=$Q$78-$S89+1-$B$22)*$C$27:$J$27)*$U89 -> 259.80313 | W89: =$U89-$V89 -> 0
A90: Refresher grant 4 | C90: =IF(AND(C$78-$S90+1-$B$22>=1,C$78-$S90+1-$B$22<=8),INDEX($C$27:$J$27,1,C$78-$S90+1-$B$22),0)*$U90*C$79 -> 0 | D90: =IF(AND(D$78-$S90+1-$B$22>=1,D$78-$S90+1-$B$22<=8),INDEX($C$27:$J$27,1,D$78-$S90+1-$B$22),0)*$U90*D$79 -> 0 | E90: =IF(AND(E$78-$S90+1-$B$22>=1,E$78-$S90+1-$B$22<=8),INDEX($C$27:$J$27,1,E$78-$S90+1-$B$22),0)*$U90*E$79 -> 0 | F90: =IF(AND(F$78-$S90+1-$B$22>=1,F$78-$S90+1-$B$22<=8),INDEX($C$27:$J$27,1,F$78-$S90+1-$B$22),0)*$U90*F$79 -> 0 | G90: =IF(AND(G$78-$S90+1-$B$22>=1,G$78-$S90+1-$B$22<=8),INDEX($C$27:$J$27,1,G$78-$S90+1-$B$22),0)*$U90*G$79 -> 0 | H90: =IF(AND(H$78-$S90+1-$B$22>=1,H$78-$S90+1-$B$22<=8),INDEX($C$27:$J$27,1,H$78-$S90+1-$B$22),0)*$U90*H$79 -> 35076.537 | I90: =IF(AND(I$78-$S90+1-$B$22>=1,I$78-$S90+1-$B$22<=8),INDEX($C$27:$J$27,1,I$78-$S90+1-$B$22),0)*$U90*I$79 -> 37531.894 | J90: =IF(AND(J$78-$S90+1-$B$22>=1,J$78-$S90+1-$B$22<=8),INDEX($C$27:$J$27,1,J$78-$S90+1-$B$22),0)*$U90*J$79 -> 40159.127 | ... Q90: =IF(AND(Q$78-$S90+1-$B$22>=1,Q$78-$S90+1-$B$22<=8),INDEX($C$27:$J$27,1,Q$78-$S90+1-$B$22),0)*$U90*Q$79 -> 0 | S90: =$B$20+3 -> 2030 | T90: =IF($S90>$B$20+Scenarios!$D$8-1,0,$B$19*(1+$B$21*Scenarios!$D$7)^3) -> 131127.24 | U90: =IFERROR($T90/INDEX($C$79:$Q$79,1,MATCH($S90,$C$78:$Q$78,0)),0) -> 250.09086 | V90: =SUMPRODUCT(($C$25:$J$25<=$Q$78-$S90+1-$B$22)*$C$27:$J$27)*$U90 -> 250.09086 | W90: =$U90-$V90 -> 0
A91: Refresher grant 5 | C91: =IF(AND(C$78-$S91+1-$B$22>=1,C$78-$S91+1-$B$22<=8),INDEX($C$27:$J$27,1,C$78-$S91+1-$B$22),0)*$U91*C$79 -> 0 | D91: =IF(AND(D$78-$S91+1-$B$22>=1,D$78-$S91+1-$B$22<=8),INDEX($C$27:$J$27,1,D$78-$S91+1-$B$22),0)*$U91*D$79 -> 0 | E91: =IF(AND(E$78-$S91+1-$B$22>=1,E$78-$S91+1-$B$22<=8),INDEX($C$27:$J$27,1,E$78-$S91+1-$B$22),0)*$U91*E$79 -> 0 | F91: =IF(AND(F$78-$S91+1-$B$22>=1,F$78-$S91+1-$B$22<=8),INDEX($C$27:$J$27,1,F$78-$S91+1-$B$22),0)*$U91*F$79 -> 0 | G91: =IF(AND(G$78-$S91+1-$B$22>=1,G$78-$S91+1-$B$22<=8),INDEX($C$27:$J$27,1,G$78-$S91+1-$B$22),0)*$U91*G$79 -> 0 | H91: =IF(AND(H$78-$S91+1-$B$22>=1,H$78-$S91+1-$B$22<=8),INDEX($C$27:$J$27,1,H$78-$S91+1-$B$22),0)*$U91*H$79 -> 0 | I91: =IF(AND(I$78-$S91+1-$B$22>=1,I$78-$S91+1-$B$22<=8),INDEX($C$27:$J$27,1,I$78-$S91+1-$B$22),0)*$U91*I$79 -> 36128.833 | J91: =IF(AND(J$78-$S91+1-$B$22>=1,J$78-$S91+1-$B$22<=8),INDEX($C$27:$J$27,1,J$78-$S91+1-$B$22),0)*$U91*J$79 -> 38657.851 | ... Q91: =IF(AND(Q$78-$S91+1-$B$22>=1,Q$78-$S91+1-$B$22<=8),INDEX($C$27:$J$27,1,Q$78-$S91+1-$B$22),0)*$U91*Q$79 -> 0 | S91: =$B$20+4 -> 2031 | T91: =IF($S91>$B$20+Scenarios!$D$8-1,0,$B$19*(1+$B$21*Scenarios!$D$7)^4) -> 135061.06 | U91: =IFERROR($T91/INDEX($C$79:$Q$79,1,MATCH($S91,$C$78:$Q$78,0)),0) -> 240.74167 | V91: =SUMPRODUCT(($C$25:$J$25<=$Q$78-$S91+1-$B$22)*$C$27:$J$27)*$U91 -> 240.74167 | W91: =$U91-$V91 -> 0
A92: Refresher grant 6 | C92: =IF(AND(C$78-$S92+1-$B$22>=1,C$78-$S92+1-$B$22<=8),INDEX($C$27:$J$27,1,C$78-$S92+1-$B$22),0)*$U92*C$79 -> 0 | D92: =IF(AND(D$78-$S92+1-$B$22>=1,D$78-$S92+1-$B$22<=8),INDEX($C$27:$J$27,1,D$78-$S92+1-$B$22),0)*$U92*D$79 -> 0 | E92: =IF(AND(E$78-$S92+1-$B$22>=1,E$78-$S92+1-$B$22<=8),INDEX($C$27:$J$27,1,E$78-$S92+1-$B$22),0)*$U92*E$79 -> 0 | F92: =IF(AND(F$78-$S92+1-$B$22>=1,F$78-$S92+1-$B$22<=8),INDEX($C$27:$J$27,1,F$78-$S92+1-$B$22),0)*$U92*F$79 -> 0 | G92: =IF(AND(G$78-$S92+1-$B$22>=1,G$78-$S92+1-$B$22<=8),INDEX($C$27:$J$27,1,G$78-$S92+1-$B$22),0)*$U92*G$79 -> 0 | H92: =IF(AND(H$78-$S92+1-$B$22>=1,H$78-$S92+1-$B$22<=8),INDEX($C$27:$J$27,1,H$78-$S92+1-$B$22),0)*$U92*H$79 -> 0 | I92: =IF(AND(I$78-$S92+1-$B$22>=1,I$78-$S92+1-$B$22<=8),INDEX($C$27:$J$27,1,I$78-$S92+1-$B$22),0)*$U92*I$79 -> 0 | J92: =IF(AND(J$78-$S92+1-$B$22>=1,J$78-$S92+1-$B$22<=8),INDEX($C$27:$J$27,1,J$78-$S92+1-$B$22),0)*$U92*J$79 -> 37212.698 | ... Q92: =IF(AND(Q$78-$S92+1-$B$22>=1,Q$78-$S92+1-$B$22<=8),INDEX($C$27:$J$27,1,Q$78-$S92+1-$B$22),0)*$U92*Q$79 -> 0 | S92: =$B$20+5 -> 2032 | T92: =IF($S92>$B$20+Scenarios!$D$8-1,0,$B$19*(1+$B$21*Scenarios!$D$7)^5) -> 139112.89 | U92: =IFERROR($T92/INDEX($C$79:$Q$79,1,MATCH($S92,$C$78:$Q$78,0)),0) -> 231.74198 | V92: =SUMPRODUCT(($C$25:$J$25<=$Q$78-$S92+1-$B$22)*$C$27:$J$27)*$U92 -> 231.74198 | W92: =$U92-$V92 -> 0
A93: Refresher grant 7 | C93: =IF(AND(C$78-$S93+1-$B$22>=1,C$78-$S93+1-$B$22<=8),INDEX($C$27:$J$27,1,C$78-$S93+1-$B$22),0)*$U93*C$79 -> 0 | D93: =IF(AND(D$78-$S93+1-$B$22>=1,D$78-$S93+1-$B$22<=8),INDEX($C$27:$J$27,1,D$78-$S93+1-$B$22),0)*$U93*D$79 -> 0 | E93: =IF(AND(E$78-$S93+1-$B$22>=1,E$78-$S93+1-$B$22<=8),INDEX($C$27:$J$27,1,E$78-$S93+1-$B$22),0)*$U93*E$79 -> 0 | F93: =IF(AND(F$78-$S93+1-$B$22>=1,F$78-$S93+1-$B$22<=8),INDEX($C$27:$J$27,1,F$78-$S93+1-$B$22),0)*$U93*F$79 -> 0 | G93: =IF(AND(G$78-$S93+1-$B$22>=1,G$78-$S93+1-$B$22<=8),INDEX($C$27:$J$27,1,G$78-$S93+1-$B$22),0)*$U93*G$79 -> 0 | H93: =IF(AND(H$78-$S93+1-$B$22>=1,H$78-$S93+1-$B$22<=8),INDEX($C$27:$J$27,1,H$78-$S93+1-$B$22),0)*$U93*H$79 -> 0 | I93: =IF(AND(I$78-$S93+1-$B$22>=1,I$78-$S93+1-$B$22<=8),INDEX($C$27:$J$27,1,I$78-$S93+1-$B$22),0)*$U93*I$79 -> 0 | J93: =IF(AND(J$78-$S93+1-$B$22>=1,J$78-$S93+1-$B$22<=8),INDEX($C$27:$J$27,1,J$78-$S93+1-$B$22),0)*$U93*J$79 -> 0 | ... Q93: =IF(AND(Q$78-$S93+1-$B$22>=1,Q$78-$S93+1-$B$22<=8),INDEX($C$27:$J$27,1,Q$78-$S93+1-$B$22),0)*$U93*Q$79 -> 0 | S93: =$B$20+6 -> 2033 | T93: =IF($S93>$B$20+Scenarios!$D$8-1,0,$B$19*(1+$B$21*Scenarios!$D$7)^6) -> 143286.28 | U93: =IFERROR($T93/INDEX($C$79:$Q$79,1,MATCH($S93,$C$78:$Q$78,0)),0) -> 223.07873 | V93: =SUMPRODUCT(($C$25:$J$25<=$Q$78-$S93+1-$B$22)*$C$27:$J$27)*$U93 -> 223.07873 | W93: =$U93-$V93 -> 0
A94: Refresher grant 8 | C94: =IF(AND(C$78-$S94+1-$B$22>=1,C$78-$S94+1-$B$22<=8),INDEX($C$27:$J$27,1,C$78-$S94+1-$B$22),0)*$U94*C$79 -> 0 | D94: =IF(AND(D$78-$S94+1-$B$22>=1,D$78-$S94+1-$B$22<=8),INDEX($C$27:$J$27,1,D$78-$S94+1-$B$22),0)*$U94*D$79 -> 0 | E94: =IF(AND(E$78-$S94+1-$B$22>=1,E$78-$S94+1-$B$22<=8),INDEX($C$27:$J$27,1,E$78-$S94+1-$B$22),0)*$U94*E$79 -> 0 | F94: =IF(AND(F$78-$S94+1-$B$22>=1,F$78-$S94+1-$B$22<=8),INDEX($C$27:$J$27,1,F$78-$S94+1-$B$22),0)*$U94*F$79 -> 0 | G94: =IF(AND(G$78-$S94+1-$B$22>=1,G$78-$S94+1-$B$22<=8),INDEX($C$27:$J$27,1,G$78-$S94+1-$B$22),0)*$U94*G$79 -> 0 | H94: =IF(AND(H$78-$S94+1-$B$22>=1,H$78-$S94+1-$B$22<=8),INDEX($C$27:$J$27,1,H$78-$S94+1-$B$22),0)*$U94*H$79 -> 0 | I94: =IF(AND(I$78-$S94+1-$B$22>=1,I$78-$S94+1-$B$22<=8),INDEX($C$27:$J$27,1,I$78-$S94+1-$B$22),0)*$U94*I$79 -> 0 | J94: =IF(AND(J$78-$S94+1-$B$22>=1,J$78-$S94+1-$B$22<=8),INDEX($C$27:$J$27,1,J$78-$S94+1-$B$22),0)*$U94*J$79 -> 0 | ... Q94: =IF(AND(Q$78-$S94+1-$B$22>=1,Q$78-$S94+1-$B$22<=8),INDEX($C$27:$J$27,1,Q$78-$S94+1-$B$22),0)*$U94*Q$79 -> 0 | S94: =$B$20+7 -> 2034 | T94: =IF($S94>$B$20+Scenarios!$D$8-1,0,$B$19*(1+$B$21*Scenarios!$D$7)^7) -> 147584.86 | U94: =IFERROR($T94/INDEX($C$79:$Q$79,1,MATCH($S94,$C$78:$Q$78,0)),0) -> 214.73934 | V94: =SUMPRODUCT(($C$25:$J$25<=$Q$78-$S94+1-$B$22)*$C$27:$J$27)*$U94 -> 214.73934 | W94: =$U94-$V94 -> 0
A95: Refresher grant 9 | C95: =IF(AND(C$78-$S95+1-$B$22>=1,C$78-$S95+1-$B$22<=8),INDEX($C$27:$J$27,1,C$78-$S95+1-$B$22),0)*$U95*C$79 -> 0 | D95: =IF(AND(D$78-$S95+1-$B$22>=1,D$78-$S95+1-$B$22<=8),INDEX($C$27:$J$27,1,D$78-$S95+1-$B$22),0)*$U95*D$79 -> 0 | E95: =IF(AND(E$78-$S95+1-$B$22>=1,E$78-$S95+1-$B$22<=8),INDEX($C$27:$J$27,1,E$78-$S95+1-$B$22),0)*$U95*E$79 -> 0 | F95: =IF(AND(F$78-$S95+1-$B$22>=1,F$78-$S95+1-$B$22<=8),INDEX($C$27:$J$27,1,F$78-$S95+1-$B$22),0)*$U95*F$79 -> 0 | G95: =IF(AND(G$78-$S95+1-$B$22>=1,G$78-$S95+1-$B$22<=8),INDEX($C$27:$J$27,1,G$78-$S95+1-$B$22),0)*$U95*G$79 -> 0 | H95: =IF(AND(H$78-$S95+1-$B$22>=1,H$78-$S95+1-$B$22<=8),INDEX($C$27:$J$27,1,H$78-$S95+1-$B$22),0)*$U95*H$79 -> 0 | I95: =IF(AND(I$78-$S95+1-$B$22>=1,I$78-$S95+1-$B$22<=8),INDEX($C$27:$J$27,1,I$78-$S95+1-$B$22),0)*$U95*I$79 -> 0 | J95: =IF(AND(J$78-$S95+1-$B$22>=1,J$78-$S95+1-$B$22<=8),INDEX($C$27:$J$27,1,J$78-$S95+1-$B$22),0)*$U95*J$79 -> 0 | ... Q95: =IF(AND(Q$78-$S95+1-$B$22>=1,Q$78-$S95+1-$B$22<=8),INDEX($C$27:$J$27,1,Q$78-$S95+1-$B$22),0)*$U95*Q$79 -> 0 | S95: =$B$20+8 -> 2035 | T95: =IF($S95>$B$20+Scenarios!$D$8-1,0,$B$19*(1+$B$21*Scenarios!$D$7)^8) -> 152012.41 | U95: =IFERROR($T95/INDEX($C$79:$Q$79,1,MATCH($S95,$C$78:$Q$78,0)),0) -> 206.7117 | V95: =SUMPRODUCT(($C$25:$J$25<=$Q$78-$S95+1-$B$22)*$C$27:$J$27)*$U95 -> 206.7117 | W95: =$U95-$V95 -> 0
A96: Refresher grant 10 | C96: =IF(AND(C$78-$S96+1-$B$22>=1,C$78-$S96+1-$B$22<=8),INDEX($C$27:$J$27,1,C$78-$S96+1-$B$22),0)*$U96*C$79 -> 0 | D96: =IF(AND(D$78-$S96+1-$B$22>=1,D$78-$S96+1-$B$22<=8),INDEX($C$27:$J$27,1,D$78-$S96+1-$B$22),0)*$U96*D$79 -> 0 | E96: =IF(AND(E$78-$S96+1-$B$22>=1,E$78-$S96+1-$B$22<=8),INDEX($C$27:$J$27,1,E$78-$S96+1-$B$22),0)*$U96*E$79 -> 0 | F96: =IF(AND(F$78-$S96+1-$B$22>=1,F$78-$S96+1-$B$22<=8),INDEX($C$27:$J$27,1,F$78-$S96+1-$B$22),0)*$U96*F$79 -> 0 | G96: =IF(AND(G$78-$S96+1-$B$22>=1,G$78-$S96+1-$B$22<=8),INDEX($C$27:$J$27,1,G$78-$S96+1-$B$22),0)*$U96*G$79 -> 0 | H96: =IF(AND(H$78-$S96+1-$B$22>=1,H$78-$S96+1-$B$22<=8),INDEX($C$27:$J$27,1,H$78-$S96+1-$B$22),0)*$U96*H$79 -> 0 | I96: =IF(AND(I$78-$S96+1-$B$22>=1,I$78-$S96+1-$B$22<=8),INDEX($C$27:$J$27,1,I$78-$S96+1-$B$22),0)*$U96*I$79 -> 0 | J96: =IF(AND(J$78-$S96+1-$B$22>=1,J$78-$S96+1-$B$22<=8),INDEX($C$27:$J$27,1,J$78-$S96+1-$B$22),0)*$U96*J$79 -> 0 | ... Q96: =IF(AND(Q$78-$S96+1-$B$22>=1,Q$78-$S96+1-$B$22<=8),INDEX($C$27:$J$27,1,Q$78-$S96+1-$B$22),0)*$U96*Q$79 -> 51308.744 | S96: =$B$20+9 -> 2036 | T96: =IF($S96>$B$20+Scenarios!$D$8-1,0,$B$19*(1+$B$21*Scenarios!$D$7)^9) -> 156572.78 | U96: =IFERROR($T96/INDEX($C$79:$Q$79,1,MATCH($S96,$C$78:$Q$78,0)),0) -> 198.98416 | V96: =SUMPRODUCT(($C$25:$J$25<=$Q$78-$S96+1-$B$22)*$C$27:$J$27)*$U96 -> 198.98416 | W96: =$U96-$V96 -> 0
A97: Refresher grant 11 | C97: =IF(AND(C$78-$S97+1-$B$22>=1,C$78-$S97+1-$B$22<=8),INDEX($C$27:$J$27,1,C$78-$S97+1-$B$22),0)*$U97*C$79 -> 0 | D97: =IF(AND(D$78-$S97+1-$B$22>=1,D$78-$S97+1-$B$22<=8),INDEX($C$27:$J$27,1,D$78-$S97+1-$B$22),0)*$U97*D$79 -> 0 | E97: =IF(AND(E$78-$S97+1-$B$22>=1,E$78-$S97+1-$B$22<=8),INDEX($C$27:$J$27,1,E$78-$S97+1-$B$22),0)*$U97*E$79 -> 0 | F97: =IF(AND(F$78-$S97+1-$B$22>=1,F$78-$S97+1-$B$22<=8),INDEX($C$27:$J$27,1,F$78-$S97+1-$B$22),0)*$U97*F$79 -> 0 | G97: =IF(AND(G$78-$S97+1-$B$22>=1,G$78-$S97+1-$B$22<=8),INDEX($C$27:$J$27,1,G$78-$S97+1-$B$22),0)*$U97*G$79 -> 0 | H97: =IF(AND(H$78-$S97+1-$B$22>=1,H$78-$S97+1-$B$22<=8),INDEX($C$27:$J$27,1,H$78-$S97+1-$B$22),0)*$U97*H$79 -> 0 | I97: =IF(AND(I$78-$S97+1-$B$22>=1,I$78-$S97+1-$B$22<=8),INDEX($C$27:$J$27,1,I$78-$S97+1-$B$22),0)*$U97*I$79 -> 0 | J97: =IF(AND(J$78-$S97+1-$B$22>=1,J$78-$S97+1-$B$22<=8),INDEX($C$27:$J$27,1,J$78-$S97+1-$B$22),0)*$U97*J$79 -> 0 | ... Q97: =IF(AND(Q$78-$S97+1-$B$22>=1,Q$78-$S97+1-$B$22<=8),INDEX($C$27:$J$27,1,Q$78-$S97+1-$B$22),0)*$U97*Q$79 -> 49390.661 | S97: =$B$20+10 -> 2037 | T97: =IF($S97>$B$20+Scenarios!$D$8-1,0,$B$19*(1+$B$21*Scenarios!$D$7)^10) -> 161269.97 | U97: =IFERROR($T97/INDEX($C$79:$Q$79,1,MATCH($S97,$C$78:$Q$78,0)),0) -> 191.5455 | V97: =SUMPRODUCT(($C$25:$J$25<=$Q$78-$S97+1-$B$22)*$C$27:$J$27)*$U97 -> 143.65912 | W97: =$U97-$V97 -> 47.886374
A98: Refresher grant 12 | C98: =IF(AND(C$78-$S98+1-$B$22>=1,C$78-$S98+1-$B$22<=8),INDEX($C$27:$J$27,1,C$78-$S98+1-$B$22),0)*$U98*C$79 -> 0 | D98: =IF(AND(D$78-$S98+1-$B$22>=1,D$78-$S98+1-$B$22<=8),INDEX($C$27:$J$27,1,D$78-$S98+1-$B$22),0)*$U98*D$79 -> 0 | E98: =IF(AND(E$78-$S98+1-$B$22>=1,E$78-$S98+1-$B$22<=8),INDEX($C$27:$J$27,1,E$78-$S98+1-$B$22),0)*$U98*E$79 -> 0 | F98: =IF(AND(F$78-$S98+1-$B$22>=1,F$78-$S98+1-$B$22<=8),INDEX($C$27:$J$27,1,F$78-$S98+1-$B$22),0)*$U98*F$79 -> 0 | G98: =IF(AND(G$78-$S98+1-$B$22>=1,G$78-$S98+1-$B$22<=8),INDEX($C$27:$J$27,1,G$78-$S98+1-$B$22),0)*$U98*G$79 -> 0 | H98: =IF(AND(H$78-$S98+1-$B$22>=1,H$78-$S98+1-$B$22<=8),INDEX($C$27:$J$27,1,H$78-$S98+1-$B$22),0)*$U98*H$79 -> 0 | I98: =IF(AND(I$78-$S98+1-$B$22>=1,I$78-$S98+1-$B$22<=8),INDEX($C$27:$J$27,1,I$78-$S98+1-$B$22),0)*$U98*I$79 -> 0 | J98: =IF(AND(J$78-$S98+1-$B$22>=1,J$78-$S98+1-$B$22<=8),INDEX($C$27:$J$27,1,J$78-$S98+1-$B$22),0)*$U98*J$79 -> 0 | ... Q98: =IF(AND(Q$78-$S98+1-$B$22>=1,Q$78-$S98+1-$B$22<=8),INDEX($C$27:$J$27,1,Q$78-$S98+1-$B$22),0)*$U98*Q$79 -> 47544.281 | S98: =$B$20+11 -> 2038 | T98: =IF($S98>$B$20+Scenarios!$D$8-1,0,$B$19*(1+$B$21*Scenarios!$D$7)^11) -> 166108.06 | U98: =IFERROR($T98/INDEX($C$79:$Q$79,1,MATCH($S98,$C$78:$Q$78,0)),0) -> 184.38492 | V98: =SUMPRODUCT(($C$25:$J$25<=$Q$78-$S98+1-$B$22)*$C$27:$J$27)*$U98 -> 92.192459 | W98: =$U98-$V98 -> 92.192459
A100: Initial grant vest ($) | C100: =C86 -> 0 | D100: =D86 -> 93625 | E100: =E86 -> 100178.75 | F100: =F86 -> 107191.26 | G100: =G86 -> 114694.65 | H100: =H86 -> 0 | I100: =I86 -> 0 | J100: =J86 -> 0 | ... Q100: =Q86 -> 0
A101: Refresher vest ($) | C101: =SUM(C87:C98) -> 0 | D101: =SUM(D87:D98) -> 0 | E101: =SUM(E87:E98) -> 32100 | F101: =SUM(F87:F98) -> 67410 | G101: =SUM(G87:G98) -> 106183.59 | H101: =SUM(H87:H98) -> 148692.98 | I101: =SUM(I87:I98) -> 153153.77 | J101: =SUM(J87:J98) -> 157748.38 | ... Q101: =SUM(Q87:Q98) -> 148243.69
A102: Total equity vest ($) | C102: =C100+C101 -> 0 | D102: =D100+D101 -> 93625 | E102: =E100+E101 -> 132278.75 | F102: =F100+F101 -> 174601.26 | G102: =G100+G101 -> 220878.24 | H102: =H100+H101 -> 148692.98 | I102: =I100+I101 -> 153153.77 | J102: =J100+J101 -> 157748.38 | ... Q102: =Q100+Q101 -> 148243.69
A103: Concurrent grants vesting (count) | C103: =SUMPRODUCT((C86:C98>0)*1) -> 0 | D103: =SUMPRODUCT((D86:D98>0)*1) -> 1 | E103: =SUMPRODUCT((E86:E98>0)*1) -> 2 | F103: =SUMPRODUCT((F86:F98>0)*1) -> 3 | G103: =SUMPRODUCT((G86:G98>0)*1) -> 4 | H103: =SUMPRODUCT((H86:H98>0)*1) -> 4 | I103: =SUMPRODUCT((I86:I98>0)*1) -> 4 | J103: =SUMPRODUCT((J86:J98>0)*1) -> 4 | ... Q103: =SUMPRODUCT((Q86:Q98>0)*1) -> 3
A105: TOTAL GROSS COMPENSATION | C105: =C80+C82+C83+C102 -> 247500 | D105: =D80+D82+D83+D102 -> 390685 | E105: =E80+E82+E83+E102 -> 399625.55 | F105: =F80+F82+F83+F102 -> 449968.47 | G105: =G80+G82+G83+G102 -> 504506.46 | H105: =H80+H82+H83+H102 -> 440830.04 | I105: =I80+I82+I83+I102 -> 454054.95 | J105: =J80+J82+J83+J102 -> 467676.59 | ... Q105: =Q80+Q82+Q83+Q102 -> 529416.3
A106: Cumulative gross | C106: =C105 -> 247500 | D106: =C106+D105 -> 638185 | E106: =D106+E105 -> 1037810.6 | F106: =E106+F105 -> 1487779 | G106: =F106+G105 -> 1992285.5 | H106: =G106+H105 -> 2433115.5 | I106: =H106+I105 -> 2887170.5 | J106: =I106+J105 -> 3354847.1 | K106: =J106+K105 -> 3836554 | ... Q106: =P106+Q105 -> 7000141
A108: Unvested shares at end of horizon | B108: =SUM(W86:W98) -> 140.07883
A109: Unvested equity value at horizon price | B109: =B108*$Q$79 -> 144479.22
A121: SCENARIO: AGGRESSIVE | B121: =Scenarios!E$3 -> Aggressive
A122: Year index | C122: 1 | D122: 2 | E122: 3 | F122: 4 | G122: 5 | H122: 6 | I122: 7 | J122: 8 | K122: 9 | L122: 10 | M122: 11 | N122: 12 | O122: 13 | P122: 14 | Q122: 15
A123: Calendar year | C123: =$B$6 -> 2026 | D123: =C123+1 -> 2027 | E123: =D123+1 -> 2028 | F123: =E123+1 -> 2029 | G123: =F123+1 -> 2030 | H123: =G123+1 -> 2031 | I123: =H123+1 -> 2032 | J123: =I123+1 -> 2033 | K123: =J123+1 -> 2034 | ... Q123: =P123+1 -> 2040
A124: Share price ($) | C124: =$B$17 -> 400 | D124: =C124*(1+Scenarios!$E$4) -> 460 | E124: =D124*(1+Scenarios!$E$4) -> 529 | F124: =E124*(1+Scenarios!$E$4) -> 608.35 | G124: =F124*(1+Scenarios!$E$4) -> 699.6025 | H124: =G124*(1+Scenarios!$E$4) -> 804.54287 | I124: =H124*(1+Scenarios!$E$4) -> 925.22431 | J124: =I124*(1+Scenarios!$E$4) -> 1064.008 | K124: =J124*(1+Scenarios!$E$4) -> 1223.6091 | ... Q124: =P124*(1+Scenarios!$E$4) -> 2830.2823
A125: Base salary | C125: =$B$7 -> 210000 | D125: =C125*(1+$B$8*Scenarios!$E$5) -> 219450 | E125: =D125*(1+$B$8*Scenarios!$E$5) -> 229325.25 | F125: =E125*(1+$B$8*Scenarios!$E$5) -> 239644.89 | G125: =F125*(1+$B$8*Scenarios!$E$5) -> 250428.91 | H125: =G125*(1+$B$8*Scenarios!$E$5) -> 261698.21 | I125: =H125*(1+$B$8*Scenarios!$E$5) -> 273474.63 | J125: =I125*(1+$B$8*Scenarios!$E$5) -> 285780.98 | K125: =J125*(1+$B$8*Scenarios!$E$5) -> 298641.13 | ... Q125: =P125*(1+$B$8*Scenarios!$E$5) -> 388908.43
A126: Bonus basis salary | C126: =IF($B$10="Prior",0,C125) -> 210000 | D126: =IF($B$10="Prior",C125,D125) -> 219450 | E126: =IF($B$10="Prior",D125,E125) -> 229325.25 | F126: =IF($B$10="Prior",E125,F125) -> 239644.89 | G126: =IF($B$10="Prior",F125,G125) -> 250428.91 | H126: =IF($B$10="Prior",G125,H125) -> 261698.21 | I126: =IF($B$10="Prior",H125,I125) -> 273474.63 | J126: =IF($B$10="Prior",I125,J125) -> 285780.98 | K126: =IF($B$10="Prior",J125,K125) -> 298641.13 | ... Q126: =IF($B$10="Prior",P125,Q125) -> 388908.43
A127: Annual bonus | C127: =IF($B$11="No",0,C126*$B$9*Scenarios!$E$6) -> 0 | D127: =D126*$B$9*Scenarios!$E$6 -> 54862.5 | E127: =E126*$B$9*Scenarios!$E$6 -> 57331.312 | F127: =F126*$B$9*Scenarios!$E$6 -> 59911.222 | G127: =G126*$B$9*Scenarios!$E$6 -> 62607.227 | H127: =H126*$B$9*Scenarios!$E$6 -> 65424.552 | I127: =I126*$B$9*Scenarios!$E$6 -> 68368.657 | J127: =J126*$B$9*Scenarios!$E$6 -> 71445.246 | K127: =K126*$B$9*Scenarios!$E$6 -> 74660.282 | ... Q127: =Q126*$B$9*Scenarios!$E$6 -> 97227.108
A128: Sign-on paid | C128: =$B$12*$B$13 -> 37500 | D128: =$B$12*$B$14 -> 37500 | E128: =$B$12*$B$15 -> 0 | F128: 0 | G128: 0 | H128: 0 | I128: 0 | J128: 0 | K128: 0 | L128: 0 | M128: 0 | N128: 0 | O128: 0 | P128: 0 | Q128: 0
A130: GRANT LEDGER — dollar value vesting each year, one row per grant | S130: Grant year | T130: Grant value ($) | U130: Shares granted | V130: Shares vested in horizon | W130: Unvested shares
A131: Initial grant | C131: =IF(AND(C$123-$S131+1-$B$22>=1,C$123-$S131+1-$B$22<=8),INDEX($C$26:$J$26,1,C$123-$S131+1-$B$22),0)*$U131*C$124 -> 0 | D131: =IF(AND(D$123-$S131+1-$B$22>=1,D$123-$S131+1-$B$22<=8),INDEX($C$26:$J$26,1,D$123-$S131+1-$B$22),0)*$U131*D$124 -> 100625 | E131: =IF(AND(E$123-$S131+1-$B$22>=1,E$123-$S131+1-$B$22<=8),INDEX($C$26:$J$26,1,E$123-$S131+1-$B$22),0)*$U131*E$124 -> 115718.75 | F131: =IF(AND(F$123-$S131+1-$B$22>=1,F$123-$S131+1-$B$22<=8),INDEX($C$26:$J$26,1,F$123-$S131+1-$B$22),0)*$U131*F$124 -> 133076.56 | G131: =IF(AND(G$123-$S131+1-$B$22>=1,G$123-$S131+1-$B$22<=8),INDEX($C$26:$J$26,1,G$123-$S131+1-$B$22),0)*$U131*G$124 -> 153038.05 | H131: =IF(AND(H$123-$S131+1-$B$22>=1,H$123-$S131+1-$B$22<=8),INDEX($C$26:$J$26,1,H$123-$S131+1-$B$22),0)*$U131*H$124 -> 0 | I131: =IF(AND(I$123-$S131+1-$B$22>=1,I$123-$S131+1-$B$22<=8),INDEX($C$26:$J$26,1,I$123-$S131+1-$B$22),0)*$U131*I$124 -> 0 | J131: =IF(AND(J$123-$S131+1-$B$22>=1,J$123-$S131+1-$B$22<=8),INDEX($C$26:$J$26,1,J$123-$S131+1-$B$22),0)*$U131*J$124 -> 0 | ... Q131: =IF(AND(Q$123-$S131+1-$B$22>=1,Q$123-$S131+1-$B$22<=8),INDEX($C$26:$J$26,1,Q$123-$S131+1-$B$22),0)*$U131*Q$124 -> 0 | S131: =$B$6 -> 2026 | T131: =$B$18 -> 350000 | U131: =IFERROR(T131/$B$17,0) -> 875 | V131: =SUMPRODUCT(($C$25:$J$25<=$Q$123-$S131+1-$B$22)*$C$26:$J$26)*$U131 -> 875 | W131: =$U131-$V131 -> 0
A132: Refresher grant 1 | C132: =IF(AND(C$123-$S132+1-$B$22>=1,C$123-$S132+1-$B$22<=8),INDEX($C$27:$J$27,1,C$123-$S132+1-$B$22),0)*$U132*C$124 -> 0 | D132: =IF(AND(D$123-$S132+1-$B$22>=1,D$123-$S132+1-$B$22<=8),INDEX($C$27:$J$27,1,D$123-$S132+1-$B$22),0)*$U132*D$124 -> 0 | E132: =IF(AND(E$123-$S132+1-$B$22>=1,E$123-$S132+1-$B$22<=8),INDEX($C$27:$J$27,1,E$123-$S132+1-$B$22),0)*$U132*E$124 -> 34500 | F132: =IF(AND(F$123-$S132+1-$B$22>=1,F$123-$S132+1-$B$22<=8),INDEX($C$27:$J$27,1,F$123-$S132+1-$B$22),0)*$U132*F$124 -> 39675 | G132: =IF(AND(G$123-$S132+1-$B$22>=1,G$123-$S132+1-$B$22<=8),INDEX($C$27:$J$27,1,G$123-$S132+1-$B$22),0)*$U132*G$124 -> 45626.25 | H132: =IF(AND(H$123-$S132+1-$B$22>=1,H$123-$S132+1-$B$22<=8),INDEX($C$27:$J$27,1,H$123-$S132+1-$B$22),0)*$U132*H$124 -> 52470.188 | I132: =IF(AND(I$123-$S132+1-$B$22>=1,I$123-$S132+1-$B$22<=8),INDEX($C$27:$J$27,1,I$123-$S132+1-$B$22),0)*$U132*I$124 -> 0 | J132: =IF(AND(J$123-$S132+1-$B$22>=1,J$123-$S132+1-$B$22<=8),INDEX($C$27:$J$27,1,J$123-$S132+1-$B$22),0)*$U132*J$124 -> 0 | ... Q132: =IF(AND(Q$123-$S132+1-$B$22>=1,Q$123-$S132+1-$B$22<=8),INDEX($C$27:$J$27,1,Q$123-$S132+1-$B$22),0)*$U132*Q$124 -> 0 | S132: =$B$20+0 -> 2027 | T132: =IF($S132>$B$20+Scenarios!$E$8-1,0,$B$19*(1+$B$21*Scenarios!$E$7)^0) -> 120000 | U132: =IFERROR($T132/INDEX($C$124:$Q$124,1,MATCH($S132,$C$123:$Q$123,0)),0) -> 260.86957 | V132: =SUMPRODUCT(($C$25:$J$25<=$Q$123-$S132+1-$B$22)*$C$27:$J$27)*$U132 -> 260.86957 | W132: =$U132-$V132 -> 0
A133: Refresher grant 2 | C133: =IF(AND(C$123-$S133+1-$B$22>=1,C$123-$S133+1-$B$22<=8),INDEX($C$27:$J$27,1,C$123-$S133+1-$B$22),0)*$U133*C$124 -> 0 | D133: =IF(AND(D$123-$S133+1-$B$22>=1,D$123-$S133+1-$B$22<=8),INDEX($C$27:$J$27,1,D$123-$S133+1-$B$22),0)*$U133*D$124 -> 0 | E133: =IF(AND(E$123-$S133+1-$B$22>=1,E$123-$S133+1-$B$22<=8),INDEX($C$27:$J$27,1,E$123-$S133+1-$B$22),0)*$U133*E$124 -> 0 | F133: =IF(AND(F$123-$S133+1-$B$22>=1,F$123-$S133+1-$B$22<=8),INDEX($C$27:$J$27,1,F$123-$S133+1-$B$22),0)*$U133*F$124 -> 35535 | G133: =IF(AND(G$123-$S133+1-$B$22>=1,G$123-$S133+1-$B$22<=8),INDEX($C$27:$J$27,1,G$123-$S133+1-$B$22),0)*$U133*G$124 -> 40865.25 | H133: =IF(AND(H$123-$S133+1-$B$22>=1,H$123-$S133+1-$B$22<=8),INDEX($C$27:$J$27,1,H$123-$S133+1-$B$22),0)*$U133*H$124 -> 46995.037 | I133: =IF(AND(I$123-$S133+1-$B$22>=1,I$123-$S133+1-$B$22<=8),INDEX($C$27:$J$27,1,I$123-$S133+1-$B$22),0)*$U133*I$124 -> 54044.293 | J133: =IF(AND(J$123-$S133+1-$B$22>=1,J$123-$S133+1-$B$22<=8),INDEX($C$27:$J$27,1,J$123-$S133+1-$B$22),0)*$U133*J$124 -> 0 | ... Q133: =IF(AND(Q$123-$S133+1-$B$22>=1,Q$123-$S133+1-$B$22<=8),INDEX($C$27:$J$27,1,Q$123-$S133+1-$B$22),0)*$U133*Q$124 -> 0 | S133: =$B$20+1 -> 2028 | T133: =IF($S133>$B$20+Scenarios!$E$8-1,0,$B$19*(1+$B$21*Scenarios!$E$7)^1) -> 123600 | U133: =IFERROR($T133/INDEX($C$124:$Q$124,1,MATCH($S133,$C$123:$Q$123,0)),0) -> 233.64839 | V133: =SUMPRODUCT(($C$25:$J$25<=$Q$123-$S133+1-$B$22)*$C$27:$J$27)*$U133 -> 233.64839 | W133: =$U133-$V133 -> 0
...

Sheet Offer_3
A1: OFFER 3
A2: Blue = you edit. Black = formula, do not edit. Green = link to another tab. Yellow = key assumption.
A3: INPUTS
A4: Company name | B4: Company C
A5: Ticker | B5: TICKC
A6: Start calendar year | B6: 2026
A7: Base salary at start | B7: 190000
A8: Merit increase %/yr | B8: 0.03
A9: Bonus target % of base | B9: 0.15
A10: Bonus basis (Current or Prior) | B10: Current
A11: Bonus paid in Year 1? (Yes/No) | B11: No
A12: Sign-on total | B12: 50000
A13: Sign-on % paid Year 1 | B13: 0.5
A14: Sign-on % paid Year 2 | B14: 0.5
A15: Sign-on % paid Year 3 | B15: 0
A16: Sign-on check (must equal 100%) | B16: =SUM(B13:B15) -> 1 | C16: =IF(ROUND(B16,6)=1,"OK","ERROR - must total 100%") -> OK
A17: Grant-date share price | B17: 180
A18: Initial grant value ($) | B18: 500000
A19: Refresher value, first grant ($) | B19: 100000
A20: First refresher calendar year | B20: 2027
A21: Refresher grant growth %/yr | B21: 0.03
A22: First vest timing (0 = grant year, 1 = year after) | B22: 1
A23: Share price is entered manually. Replace with a market data lookup in the web app. The original workbook vested in the grant year itself (offset 0); real grants usually vest a year later (offset 1).
A24: VESTING SCHEDULES — % of the grant that vests in each year AFTER the grant date
A25: Years after grant | C25: 1 | D25: 2 | E25: 3 | F25: 4 | G25: 5 | H25: 6 | I25: 7 | J25: 8 | K25: Total
A26: Initial grant | C26: 0.2 | D26: 0.2 | E26: 0.2 | F26: 0.2 | G26: 0.2 | H26: 0 | I26: 0 | J26: 0 | K26: =SUM(C26:J26) -> 1 | L26: =IF(ROUND(K26,6)=1,"OK","ERROR - must total 100%") -> OK
A27: Refresher grants | C27: 0.2 | D27: 0.2 | E27: 0.2 | F27: 0.2 | G27: 0.2 | H27: 0 | I27: 0 | J27: 0 | K27: =SUM(C27:J27) -> 1 | L27: =IF(ROUND(K27,6)=1,"OK","ERROR - must total 100%") -> OK
A28: Annual granularity. Sub-annual (quarterly/monthly) vesting and cliffs are handled in the web app, not here.
A31: SCENARIO: CONSERVATIVE | B31: =Scenarios!C$3 -> Conservative
A32: Year index | C32: 1 | D32: 2 | E32: 3 | F32: 4 | G32: 5 | H32: 6 | I32: 7 | J32: 8 | K32: 9 | L32: 10 | M32: 11 | N32: 12 | O32: 13 | P32: 14 | Q32: 15
A33: Calendar year | C33: =$B$6 -> 2026 | D33: =C33+1 -> 2027 | E33: =D33+1 -> 2028 | F33: =E33+1 -> 2029 | G33: =F33+1 -> 2030 | H33: =G33+1 -> 2031 | I33: =H33+1 -> 2032 | J33: =I33+1 -> 2033 | K33: =J33+1 -> 2034 | ... Q33: =P33+1 -> 2040
A34: Share price ($) | C34: =$B$17 -> 180 | D34: =C34*(1+Scenarios!$C$4) -> 180 | E34: =D34*(1+Scenarios!$C$4) -> 180 | F34: =E34*(1+Scenarios!$C$4) -> 180 | G34: =F34*(1+Scenarios!$C$4) -> 180 | H34: =G34*(1+Scenarios!$C$4) -> 180 | I34: =H34*(1+Scenarios!$C$4) -> 180 | J34: =I34*(1+Scenarios!$C$4) -> 180 | K34: =J34*(1+Scenarios!$C$4) -> 180 | ... Q34: =P34*(1+Scenarios!$C$4) -> 180
A35: Base salary | C35: =$B$7 -> 190000 | D35: =C35*(1+$B$8*Scenarios!$C$5) -> 192850 | E35: =D35*(1+$B$8*Scenarios!$C$5) -> 195742.75 | F35: =E35*(1+$B$8*Scenarios!$C$5) -> 198678.89 | G35: =F35*(1+$B$8*Scenarios!$C$5) -> 201659.07 | H35: =G35*(1+$B$8*Scenarios!$C$5) -> 204683.96 | I35: =H35*(1+$B$8*Scenarios!$C$5) -> 207754.22 | J35: =I35*(1+$B$8*Scenarios!$C$5) -> 210870.53 | K35: =J35*(1+$B$8*Scenarios!$C$5) -> 214033.59 | ... Q35: =P35*(1+$B$8*Scenarios!$C$5) -> 234033.59
A36: Bonus basis salary | C36: =IF($B$10="Prior",0,C35) -> 190000 | D36: =IF($B$10="Prior",C35,D35) -> 192850 | E36: =IF($B$10="Prior",D35,E35) -> 195742.75 | F36: =IF($B$10="Prior",E35,F35) -> 198678.89 | G36: =IF($B$10="Prior",F35,G35) -> 201659.07 | H36: =IF($B$10="Prior",G35,H35) -> 204683.96 | I36: =IF($B$10="Prior",H35,I35) -> 207754.22 | J36: =IF($B$10="Prior",I35,J35) -> 210870.53 | K36: =IF($B$10="Prior",J35,K35) -> 214033.59 | ... Q36: =IF($B$10="Prior",P35,Q35) -> 234033.59
A37: Annual bonus | C37: =IF($B$11="No",0,C36*$B$9*Scenarios!$C$6) -> 0 | D37: =D36*$B$9*Scenarios!$C$6 -> 21695.625 | E37: =E36*$B$9*Scenarios!$C$6 -> 22021.059 | F37: =F36*$B$9*Scenarios!$C$6 -> 22351.375 | G37: =G36*$B$9*Scenarios!$C$6 -> 22686.646 | H37: =H36*$B$9*Scenarios!$C$6 -> 23026.946 | I37: =I36*$B$9*Scenarios!$C$6 -> 23372.35 | J37: =J36*$B$9*Scenarios!$C$6 -> 23722.935 | K37: =K36*$B$9*Scenarios!$C$6 -> 24078.779 | ... Q37: =Q36*$B$9*Scenarios!$C$6 -> 26328.779
A38: Sign-on paid | C38: =$B$12*$B$13 -> 25000 | D38: =$B$12*$B$14 -> 25000 | E38: =$B$12*$B$15 -> 0 | F38: 0 | G38: 0 | H38: 0 | I38: 0 | J38: 0 | K38: 0 | L38: 0 | M38: 0 | N38: 0 | O38: 0 | P38: 0 | Q38: 0
A40: GRANT LEDGER — dollar value vesting each year, one row per grant | S40: Grant year | T40: Grant value ($) | U40: Shares granted | V40: Shares vested in horizon | W40: Unvested shares
A41: Initial grant | C41: =IF(AND(C$33-$S41+1-$B$22>=1,C$33-$S41+1-$B$22<=8),INDEX($C$26:$J$26,1,C$33-$S41+1-$B$22),0)*$U41*C$34 -> 0 | D41: =IF(AND(D$33-$S41+1-$B$22>=1,D$33-$S41+1-$B$22<=8),INDEX($C$26:$J$26,1,D$33-$S41+1-$B$22),0)*$U41*D$34 -> 100000 | E41: =IF(AND(E$33-$S41+1-$B$22>=1,E$33-$S41+1-$B$22<=8),INDEX($C$26:$J$26,1,E$33-$S41+1-$B$22),0)*$U41*E$34 -> 100000 | F41: =IF(AND(F$33-$S41+1-$B$22>=1,F$33-$S41+1-$B$22<=8),INDEX($C$26:$J$26,1,F$33-$S41+1-$B$22),0)*$U41*F$34 -> 100000 | G41: =IF(AND(G$33-$S41+1-$B$22>=1,G$33-$S41+1-$B$22<=8),INDEX($C$26:$J$26,1,G$33-$S41+1-$B$22),0)*$U41*G$34 -> 100000 | H41: =IF(AND(H$33-$S41+1-$B$22>=1,H$33-$S41+1-$B$22<=8),INDEX($C$26:$J$26,1,H$33-$S41+1-$B$22),0)*$U41*H$34 -> 100000 | I41: =IF(AND(I$33-$S41+1-$B$22>=1,I$33-$S41+1-$B$22<=8),INDEX($C$26:$J$26,1,I$33-$S41+1-$B$22),0)*$U41*I$34 -> 0 | J41: =IF(AND(J$33-$S41+1-$B$22>=1,J$33-$S41+1-$B$22<=8),INDEX($C$26:$J$26,1,J$33-$S41+1-$B$22),0)*$U41*J$34 -> 0 | ... Q41: =IF(AND(Q$33-$S41+1-$B$22>=1,Q$33-$S41+1-$B$22<=8),INDEX($C$26:$J$26,1,Q$33-$S41+1-$B$22),0)*$U41*Q$34 -> 0 | S41: =$B$6 -> 2026 | T41: =$B$18 -> 500000 | U41: =IFERROR(T41/$B$17,0) -> 2777.7778 | V41: =SUMPRODUCT(($C$25:$J$25<=$Q$33-$S41+1-$B$22)*$C$26:$J$26)*$U41 -> 2777.7778 | W41: =$U41-$V41 -> 0
A42: Refresher grant 1 | C42: =IF(AND(C$33-$S42+1-$B$22>=1,C$33-$S42+1-$B$22<=8),INDEX($C$27:$J$27,1,C$33-$S42+1-$B$22),0)*$U42*C$34 -> 0 | D42: =IF(AND(D$33-$S42+1-$B$22>=1,D$33-$S42+1-$B$22<=8),INDEX($C$27:$J$27,1,D$33-$S42+1-$B$22),0)*$U42*D$34 -> 0 | E42: =IF(AND(E$33-$S42+1-$B$22>=1,E$33-$S42+1-$B$22<=8),INDEX($C$27:$J$27,1,E$33-$S42+1-$B$22),0)*$U42*E$34 -> 20000 | F42: =IF(AND(F$33-$S42+1-$B$22>=1,F$33-$S42+1-$B$22<=8),INDEX($C$27:$J$27,1,F$33-$S42+1-$B$22),0)*$U42*F$34 -> 20000 | G42: =IF(AND(G$33-$S42+1-$B$22>=1,G$33-$S42+1-$B$22<=8),INDEX($C$27:$J$27,1,G$33-$S42+1-$B$22),0)*$U42*G$34 -> 20000 | H42: =IF(AND(H$33-$S42+1-$B$22>=1,H$33-$S42+1-$B$22<=8),INDEX($C$27:$J$27,1,H$33-$S42+1-$B$22),0)*$U42*H$34 -> 20000 | I42: =IF(AND(I$33-$S42+1-$B$22>=1,I$33-$S42+1-$B$22<=8),INDEX($C$27:$J$27,1,I$33-$S42+1-$B$22),0)*$U42*I$34 -> 20000 | J42: =IF(AND(J$33-$S42+1-$B$22>=1,J$33-$S42+1-$B$22<=8),INDEX($C$27:$J$27,1,J$33-$S42+1-$B$22),0)*$U42*J$34 -> 0 | ... Q42: =IF(AND(Q$33-$S42+1-$B$22>=1,Q$33-$S42+1-$B$22<=8),INDEX($C$27:$J$27,1,Q$33-$S42+1-$B$22),0)*$U42*Q$34 -> 0 | S42: =$B$20+0 -> 2027 | T42: =IF($S42>$B$20+Scenarios!$C$8-1,0,$B$19*(1+$B$21*Scenarios!$C$7)^0) -> 100000 | U42: =IFERROR($T42/INDEX($C$34:$Q$34,1,MATCH($S42,$C$33:$Q$33,0)),0) -> 555.55556 | V42: =SUMPRODUCT(($C$25:$J$25<=$Q$33-$S42+1-$B$22)*$C$27:$J$27)*$U42 -> 555.55556 | W42: =$U42-$V42 -> 0
A43: Refresher grant 2 | C43: =IF(AND(C$33-$S43+1-$B$22>=1,C$33-$S43+1-$B$22<=8),INDEX($C$27:$J$27,1,C$33-$S43+1-$B$22),0)*$U43*C$34 -> 0 | D43: =IF(AND(D$33-$S43+1-$B$22>=1,D$33-$S43+1-$B$22<=8),INDEX($C$27:$J$27,1,D$33-$S43+1-$B$22),0)*$U43*D$34 -> 0 | E43: =IF(AND(E$33-$S43+1-$B$22>=1,E$33-$S43+1-$B$22<=8),INDEX($C$27:$J$27,1,E$33-$S43+1-$B$22),0)*$U43*E$34 -> 0 | F43: =IF(AND(F$33-$S43+1-$B$22>=1,F$33-$S43+1-$B$22<=8),INDEX($C$27:$J$27,1,F$33-$S43+1-$B$22),0)*$U43*F$34 -> 20000 | G43: =IF(AND(G$33-$S43+1-$B$22>=1,G$33-$S43+1-$B$22<=8),INDEX($C$27:$J$27,1,G$33-$S43+1-$B$22),0)*$U43*G$34 -> 20000 | H43: =IF(AND(H$33-$S43+1-$B$22>=1,H$33-$S43+1-$B$22<=8),INDEX($C$27:$J$27,1,H$33-$S43+1-$B$22),0)*$U43*H$34 -> 20000 | I43: =IF(AND(I$33-$S43+1-$B$22>=1,I$33-$S43+1-$B$22<=8),INDEX($C$27:$J$27,1,I$33-$S43+1-$B$22),0)*$U43*I$34 -> 20000 | J43: =IF(AND(J$33-$S43+1-$B$22>=1,J$33-$S43+1-$B$22<=8),INDEX($C$27:$J$27,1,J$33-$S43+1-$B$22),0)*$U43*J$34 -> 20000 | ... Q43: =IF(AND(Q$33-$S43+1-$B$22>=1,Q$33-$S43+1-$B$22<=8),INDEX($C$27:$J$27,1,Q$33-$S43+1-$B$22),0)*$U43*Q$34 -> 0 | S43: =$B$20+1 -> 2028 | T43: =IF($S43>$B$20+Scenarios!$C$8-1,0,$B$19*(1+$B$21*Scenarios!$C$7)^1) -> 100000 | U43: =IFERROR($T43/INDEX($C$34:$Q$34,1,MATCH($S43,$C$33:$Q$33,0)),0) -> 555.55556 | V43: =SUMPRODUCT(($C$25:$J$25<=$Q$33-$S43+1-$B$22)*$C$27:$J$27)*$U43 -> 555.55556 | W43: =$U43-$V43 -> 0
A44: Refresher grant 3 | C44: =IF(AND(C$33-$S44+1-$B$22>=1,C$33-$S44+1-$B$22<=8),INDEX($C$27:$J$27,1,C$33-$S44+1-$B$22),0)*$U44*C$34 -> 0 | D44: =IF(AND(D$33-$S44+1-$B$22>=1,D$33-$S44+1-$B$22<=8),INDEX($C$27:$J$27,1,D$33-$S44+1-$B$22),0)*$U44*D$34 -> 0 | E44: =IF(AND(E$33-$S44+1-$B$22>=1,E$33-$S44+1-$B$22<=8),INDEX($C$27:$J$27,1,E$33-$S44+1-$B$22),0)*$U44*E$34 -> 0 | F44: =IF(AND(F$33-$S44+1-$B$22>=1,F$33-$S44+1-$B$22<=8),INDEX($C$27:$J$27,1,F$33-$S44+1-$B$22),0)*$U44*F$34 -> 0 | G44: =IF(AND(G$33-$S44+1-$B$22>=1,G$33-$S44+1-$B$22<=8),INDEX($C$27:$J$27,1,G$33-$S44+1-$B$22),0)*$U44*G$34 -> 20000 | H44: =IF(AND(H$33-$S44+1-$B$22>=1,H$33-$S44+1-$B$22<=8),INDEX($C$27:$J$27,1,H$33-$S44+1-$B$22),0)*$U44*H$34 -> 20000 | I44: =IF(AND(I$33-$S44+1-$B$22>=1,I$33-$S44+1-$B$22<=8),INDEX($C$27:$J$27,1,I$33-$S44+1-$B$22),0)*$U44*I$34 -> 20000 | J44: =IF(AND(J$33-$S44+1-$B$22>=1,J$33-$S44+1-$B$22<=8),INDEX($C$27:$J$27,1,J$33-$S44+1-$B$22),0)*$U44*J$34 -> 20000 | ... Q44: =IF(AND(Q$33-$S44+1-$B$22>=1,Q$33-$S44+1-$B$22<=8),INDEX($C$27:$J$27,1,Q$33-$S44+1-$B$22),0)*$U44*Q$34 -> 0 | S44: =$B$20+2 -> 2029 | T44: =IF($S44>$B$20+Scenarios!$C$8-1,0,$B$19*(1+$B$21*Scenarios!$C$7)^2) -> 100000 | U44: =IFERROR($T44/INDEX($C$34:$Q$34,1,MATCH($S44,$C$33:$Q$33,0)),0) -> 555.55556 | V44: =SUMPRODUCT(($C$25:$J$25<=$Q$33-$S44+1-$B$22)*$C$27:$J$27)*$U44 -> 555.55556 | W44: =$U44-$V44 -> 0
A45: Refresher grant 4 | C45: =IF(AND(C$33-$S45+1-$B$22>=1,C$33-$S45+1-$B$22<=8),INDEX($C$27:$J$27,1,C$33-$S45+1-$B$22),0)*$U45*C$34 -> 0 | D45: =IF(AND(D$33-$S45+1-$B$22>=1,D$33-$S45+1-$B$22<=8),INDEX($C$27:$J$27,1,D$33-$S45+1-$B$22),0)*$U45*D$34 -> 0 | E45: =IF(AND(E$33-$S45+1-$B$22>=1,E$33-$S45+1-$B$22<=8),INDEX($C$27:$J$27,1,E$33-$S45+1-$B$22),0)*$U45*E$34 -> 0 | F45: =IF(AND(F$33-$S45+1-$B$22>=1,F$33-$S45+1-$B$22<=8),INDEX($C$27:$J$27,1,F$33-$S45+1-$B$22),0)*$U45*F$34 -> 0 | G45: =IF(AND(G$33-$S45+1-$B$22>=1,G$33-$S45+1-$B$22<=8),INDEX($C$27:$J$27,1,G$33-$S45+1-$B$22),0)*$U45*G$34 -> 0 | H45: =IF(AND(H$33-$S45+1-$B$22>=1,H$33-$S45+1-$B$22<=8),INDEX($C$27:$J$27,1,H$33-$S45+1-$B$22),0)*$U45*H$34 -> 20000 | I45: =IF(AND(I$33-$S45+1-$B$22>=1,I$33-$S45+1-$B$22<=8),INDEX($C$27:$J$27,1,I$33-$S45+1-$B$22),0)*$U45*I$34 -> 20000 | J45: =IF(AND(J$33-$S45+1-$B$22>=1,J$33-$S45+1-$B$22<=8),INDEX($C$27:$J$27,1,J$33-$S45+1-$B$22),0)*$U45*J$34 -> 20000 | ... Q45: =IF(AND(Q$33-$S45+1-$B$22>=1,Q$33-$S45+1-$B$22<=8),INDEX($C$27:$J$27,1,Q$33-$S45+1-$B$22),0)*$U45*Q$34 -> 0 | S45: =$B$20+3 -> 2030 | T45: =IF($S45>$B$20+Scenarios!$C$8-1,0,$B$19*(1+$B$21*Scenarios!$C$7)^3) -> 100000 | U45: =IFERROR($T45/INDEX($C$34:$Q$34,1,MATCH($S45,$C$33:$Q$33,0)),0) -> 555.55556 | V45: =SUMPRODUCT(($C$25:$J$25<=$Q$33-$S45+1-$B$22)*$C$27:$J$27)*$U45 -> 555.55556 | W45: =$U45-$V45 -> 0
A46: Refresher grant 5 | C46: =IF(AND(C$33-$S46+1-$B$22>=1,C$33-$S46+1-$B$22<=8),INDEX($C$27:$J$27,1,C$33-$S46+1-$B$22),0)*$U46*C$34 -> 0 | D46: =IF(AND(D$33-$S46+1-$B$22>=1,D$33-$S46+1-$B$22<=8),INDEX($C$27:$J$27,1,D$33-$S46+1-$B$22),0)*$U46*D$34 -> 0 | E46: =IF(AND(E$33-$S46+1-$B$22>=1,E$33-$S46+1-$B$22<=8),INDEX($C$27:$J$27,1,E$33-$S46+1-$B$22),0)*$U46*E$34 -> 0 | F46: =IF(AND(F$33-$S46+1-$B$22>=1,F$33-$S46+1-$B$22<=8),INDEX($C$27:$J$27,1,F$33-$S46+1-$B$22),0)*$U46*F$34 -> 0 | G46: =IF(AND(G$33-$S46+1-$B$22>=1,G$33-$S46+1-$B$22<=8),INDEX($C$27:$J$27,1,G$33-$S46+1-$B$22),0)*$U46*G$34 -> 0 | H46: =IF(AND(H$33-$S46+1-$B$22>=1,H$33-$S46+1-$B$22<=8),INDEX($C$27:$J$27,1,H$33-$S46+1-$B$22),0)*$U46*H$34 -> 0 | I46: =IF(AND(I$33-$S46+1-$B$22>=1,I$33-$S46+1-$B$22<=8),INDEX($C$27:$J$27,1,I$33-$S46+1-$B$22),0)*$U46*I$34 -> 0 | J46: =IF(AND(J$33-$S46+1-$B$22>=1,J$33-$S46+1-$B$22<=8),INDEX($C$27:$J$27,1,J$33-$S46+1-$B$22),0)*$U46*J$34 -> 0 | ... Q46: =IF(AND(Q$33-$S46+1-$B$22>=1,Q$33-$S46+1-$B$22<=8),INDEX($C$27:$J$27,1,Q$33-$S46+1-$B$22),0)*$U46*Q$34 -> 0 | S46: =$B$20+4 -> 2031 | T46: =IF($S46>$B$20+Scenarios!$C$8-1,0,$B$19*(1+$B$21*Scenarios!$C$7)^4) -> 0 | U46: =IFERROR($T46/INDEX($C$34:$Q$34,1,MATCH($S46,$C$33:$Q$33,0)),0) -> 0 | V46: =SUMPRODUCT(($C$25:$J$25<=$Q$33-$S46+1-$B$22)*$C$27:$J$27)*$U46 -> 0 | W46: =$U46-$V46 -> 0
A47: Refresher grant 6 | C47: =IF(AND(C$33-$S47+1-$B$22>=1,C$33-$S47+1-$B$22<=8),INDEX($C$27:$J$27,1,C$33-$S47+1-$B$22),0)*$U47*C$34 -> 0 | D47: =IF(AND(D$33-$S47+1-$B$22>=1,D$33-$S47+1-$B$22<=8),INDEX($C$27:$J$27,1,D$33-$S47+1-$B$22),0)*$U47*D$34 -> 0 | E47: =IF(AND(E$33-$S47+1-$B$22>=1,E$33-$S47+1-$B$22<=8),INDEX($C$27:$J$27,1,E$33-$S47+1-$B$22),0)*$U47*E$34 -> 0 | F47: =IF(AND(F$33-$S47+1-$B$22>=1,F$33-$S47+1-$B$22<=8),INDEX($C$27:$J$27,1,F$33-$S47+1-$B$22),0)*$U47*F$34 -> 0 | G47: =IF(AND(G$33-$S47+1-$B$22>=1,G$33-$S47+1-$B$22<=8),INDEX($C$27:$J$27,1,G$33-$S47+1-$B$22),0)*$U47*G$34 -> 0 | H47: =IF(AND(H$33-$S47+1-$B$22>=1,H$33-$S47+1-$B$22<=8),INDEX($C$27:$J$27,1,H$33-$S47+1-$B$22),0)*$U47*H$34 -> 0 | I47: =IF(AND(I$33-$S47+1-$B$22>=1,I$33-$S47+1-$B$22<=8),INDEX($C$27:$J$27,1,I$33-$S47+1-$B$22),0)*$U47*I$34 -> 0 | J47: =IF(AND(J$33-$S47+1-$B$22>=1,J$33-$S47+1-$B$22<=8),INDEX($C$27:$J$27,1,J$33-$S47+1-$B$22),0)*$U47*J$34 -> 0 | ... Q47: =IF(AND(Q$33-$S47+1-$B$22>=1,Q$33-$S47+1-$B$22<=8),INDEX($C$27:$J$27,1,Q$33-$S47+1-$B$22),0)*$U47*Q$34 -> 0 | S47: =$B$20+5 -> 2032 | T47: =IF($S47>$B$20+Scenarios!$C$8-1,0,$B$19*(1+$B$21*Scenarios!$C$7)^5) -> 0 | U47: =IFERROR($T47/INDEX($C$34:$Q$34,1,MATCH($S47,$C$33:$Q$33,0)),0) -> 0 | V47: =SUMPRODUCT(($C$25:$J$25<=$Q$33-$S47+1-$B$22)*$C$27:$J$27)*$U47 -> 0 | W47: =$U47-$V47 -> 0
A48: Refresher grant 7 | C48: =IF(AND(C$33-$S48+1-$B$22>=1,C$33-$S48+1-$B$22<=8),INDEX($C$27:$J$27,1,C$33-$S48+1-$B$22),0)*$U48*C$34 -> 0 | D48: =IF(AND(D$33-$S48+1-$B$22>=1,D$33-$S48+1-$B$22<=8),INDEX($C$27:$J$27,1,D$33-$S48+1-$B$22),0)*$U48*D$34 -> 0 | E48: =IF(AND(E$33-$S48+1-$B$22>=1,E$33-$S48+1-$B$22<=8),INDEX($C$27:$J$27,1,E$33-$S48+1-$B$22),0)*$U48*E$34 -> 0 | F48: =IF(AND(F$33-$S48+1-$B$22>=1,F$33-$S48+1-$B$22<=8),INDEX($C$27:$J$27,1,F$33-$S48+1-$B$22),0)*$U48*F$34 -> 0 | G48: =IF(AND(G$33-$S48+1-$B$22>=1,G$33-$S48+1-$B$22<=8),INDEX($C$27:$J$27,1,G$33-$S48+1-$B$22),0)*$U48*G$34 -> 0 | H48: =IF(AND(H$33-$S48+1-$B$22>=1,H$33-$S48+1-$B$22<=8),INDEX($C$27:$J$27,1,H$33-$S48+1-$B$22),0)*$U48*H$34 -> 0 | I48: =IF(AND(I$33-$S48+1-$B$22>=1,I$33-$S48+1-$B$22<=8),INDEX($C$27:$J$27,1,I$33-$S48+1-$B$22),0)*$U48*I$34 -> 0 | J48: =IF(AND(J$33-$S48+1-$B$22>=1,J$33-$S48+1-$B$22<=8),INDEX($C$27:$J$27,1,J$33-$S48+1-$B$22),0)*$U48*J$34 -> 0 | ... Q48: =IF(AND(Q$33-$S48+1-$B$22>=1,Q$33-$S48+1-$B$22<=8),INDEX($C$27:$J$27,1,Q$33-$S48+1-$B$22),0)*$U48*Q$34 -> 0 | S48: =$B$20+6 -> 2033 | T48: =IF($S48>$B$20+Scenarios!$C$8-1,0,$B$19*(1+$B$21*Scenarios!$C$7)^6) -> 0 | U48: =IFERROR($T48/INDEX($C$34:$Q$34,1,MATCH($S48,$C$33:$Q$33,0)),0) -> 0 | V48: =SUMPRODUCT(($C$25:$J$25<=$Q$33-$S48+1-$B$22)*$C$27:$J$27)*$U48 -> 0 | W48: =$U48-$V48 -> 0
A49: Refresher grant 8 | C49: =IF(AND(C$33-$S49+1-$B$22>=1,C$33-$S49+1-$B$22<=8),INDEX($C$27:$J$27,1,C$33-$S49+1-$B$22),0)*$U49*C$34 -> 0 | D49: =IF(AND(D$33-$S49+1-$B$22>=1,D$33-$S49+1-$B$22<=8),INDEX($C$27:$J$27,1,D$33-$S49+1-$B$22),0)*$U49*D$34 -> 0 | E49: =IF(AND(E$33-$S49+1-$B$22>=1,E$33-$S49+1-$B$22<=8),INDEX($C$27:$J$27,1,E$33-$S49+1-$B$22),0)*$U49*E$34 -> 0 | F49: =IF(AND(F$33-$S49+1-$B$22>=1,F$33-$S49+1-$B$22<=8),INDEX($C$27:$J$27,1,F$33-$S49+1-$B$22),0)*$U49*F$34 -> 0 | G49: =IF(AND(G$33-$S49+1-$B$22>=1,G$33-$S49+1-$B$22<=8),INDEX($C$27:$J$27,1,G$33-$S49+1-$B$22),0)*$U49*G$34 -> 0 | H49: =IF(AND(H$33-$S49+1-$B$22>=1,H$33-$S49+1-$B$22<=8),INDEX($C$27:$J$27,1,H$33-$S49+1-$B$22),0)*$U49*H$34 -> 0 | I49: =IF(AND(I$33-$S49+1-$B$22>=1,I$33-$S49+1-$B$22<=8),INDEX($C$27:$J$27,1,I$33-$S49+1-$B$22),0)*$U49*I$34 -> 0 | J49: =IF(AND(J$33-$S49+1-$B$22>=1,J$33-$S49+1-$B$22<=8),INDEX($C$27:$J$27,1,J$33-$S49+1-$B$22),0)*$U49*J$34 -> 0 | ... Q49: =IF(AND(Q$33-$S49+1-$B$22>=1,Q$33-$S49+1-$B$22<=8),INDEX($C$27:$J$27,1,Q$33-$S49+1-$B$22),0)*$U49*Q$34 -> 0 | S49: =$B$20+7 -> 2034 | T49: =IF($S49>$B$20+Scenarios!$C$8-1,0,$B$19*(1+$B$21*Scenarios!$C$7)^7) -> 0 | U49: =IFERROR($T49/INDEX($C$34:$Q$34,1,MATCH($S49,$C$33:$Q$33,0)),0) -> 0 | V49: =SUMPRODUCT(($C$25:$J$25<=$Q$33-$S49+1-$B$22)*$C$27:$J$27)*$U49 -> 0 | W49: =$U49-$V49 -> 0
A50: Refresher grant 9 | C50: =IF(AND(C$33-$S50+1-$B$22>=1,C$33-$S50+1-$B$22<=8),INDEX($C$27:$J$27,1,C$33-$S50+1-$B$22),0)*$U50*C$34 -> 0 | D50: =IF(AND(D$33-$S50+1-$B$22>=1,D$33-$S50+1-$B$22<=8),INDEX($C$27:$J$27,1,D$33-$S50+1-$B$22),0)*$U50*D$34 -> 0 | E50: =IF(AND(E$33-$S50+1-$B$22>=1,E$33-$S50+1-$B$22<=8),INDEX($C$27:$J$27,1,E$33-$S50+1-$B$22),0)*$U50*E$34 -> 0 | F50: =IF(AND(F$33-$S50+1-$B$22>=1,F$33-$S50+1-$B$22<=8),INDEX($C$27:$J$27,1,F$33-$S50+1-$B$22),0)*$U50*F$34 -> 0 | G50: =IF(AND(G$33-$S50+1-$B$22>=1,G$33-$S50+1-$B$22<=8),INDEX($C$27:$J$27,1,G$33-$S50+1-$B$22),0)*$U50*G$34 -> 0 | H50: =IF(AND(H$33-$S50+1-$B$22>=1,H$33-$S50+1-$B$22<=8),INDEX($C$27:$J$27,1,H$33-$S50+1-$B$22),0)*$U50*H$34 -> 0 | I50: =IF(AND(I$33-$S50+1-$B$22>=1,I$33-$S50+1-$B$22<=8),INDEX($C$27:$J$27,1,I$33-$S50+1-$B$22),0)*$U50*I$34 -> 0 | J50: =IF(AND(J$33-$S50+1-$B$22>=1,J$33-$S50+1-$B$22<=8),INDEX($C$27:$J$27,1,J$33-$S50+1-$B$22),0)*$U50*J$34 -> 0 | ... Q50: =IF(AND(Q$33-$S50+1-$B$22>=1,Q$33-$S50+1-$B$22<=8),INDEX($C$27:$J$27,1,Q$33-$S50+1-$B$22),0)*$U50*Q$34 -> 0 | S50: =$B$20+8 -> 2035 | T50: =IF($S50>$B$20+Scenarios!$C$8-1,0,$B$19*(1+$B$21*Scenarios!$C$7)^8) -> 0 | U50: =IFERROR($T50/INDEX($C$34:$Q$34,1,MATCH($S50,$C$33:$Q$33,0)),0) -> 0 | V50: =SUMPRODUCT(($C$25:$J$25<=$Q$33-$S50+1-$B$22)*$C$27:$J$27)*$U50 -> 0 | W50: =$U50-$V50 -> 0
A51: Refresher grant 10 | C51: =IF(AND(C$33-$S51+1-$B$22>=1,C$33-$S51+1-$B$22<=8),INDEX($C$27:$J$27,1,C$33-$S51+1-$B$22),0)*$U51*C$34 -> 0 | D51: =IF(AND(D$33-$S51+1-$B$22>=1,D$33-$S51+1-$B$22<=8),INDEX($C$27:$J$27,1,D$33-$S51+1-$B$22),0)*$U51*D$34 -> 0 | E51: =IF(AND(E$33-$S51+1-$B$22>=1,E$33-$S51+1-$B$22<=8),INDEX($C$27:$J$27,1,E$33-$S51+1-$B$22),0)*$U51*E$34 -> 0 | F51: =IF(AND(F$33-$S51+1-$B$22>=1,F$33-$S51+1-$B$22<=8),INDEX($C$27:$J$27,1,F$33-$S51+1-$B$22),0)*$U51*F$34 -> 0 | G51: =IF(AND(G$33-$S51+1-$B$22>=1,G$33-$S51+1-$B$22<=8),INDEX($C$27:$J$27,1,G$33-$S51+1-$B$22),0)*$U51*G$34 -> 0 | H51: =IF(AND(H$33-$S51+1-$B$22>=1,H$33-$S51+1-$B$22<=8),INDEX($C$27:$J$27,1,H$33-$S51+1-$B$22),0)*$U51*H$34 -> 0 | I51: =IF(AND(I$33-$S51+1-$B$22>=1,I$33-$S51+1-$B$22<=8),INDEX($C$27:$J$27,1,I$33-$S51+1-$B$22),0)*$U51*I$34 -> 0 | J51: =IF(AND(J$33-$S51+1-$B$22>=1,J$33-$S51+1-$B$22<=8),INDEX($C$27:$J$27,1,J$33-$S51+1-$B$22),0)*$U51*J$34 -> 0 | ... Q51: =IF(AND(Q$33-$S51+1-$B$22>=1,Q$33-$S51+1-$B$22<=8),INDEX($C$27:$J$27,1,Q$33-$S51+1-$B$22),0)*$U51*Q$34 -> 0 | S51: =$B$20+9 -> 2036 | T51: =IF($S51>$B$20+Scenarios!$C$8-1,0,$B$19*(1+$B$21*Scenarios!$C$7)^9) -> 0 | U51: =IFERROR($T51/INDEX($C$34:$Q$34,1,MATCH($S51,$C$33:$Q$33,0)),0) -> 0 | V51: =SUMPRODUCT(($C$25:$J$25<=$Q$33-$S51+1-$B$22)*$C$27:$J$27)*$U51 -> 0 | W51: =$U51-$V51 -> 0
A52: Refresher grant 11 | C52: =IF(AND(C$33-$S52+1-$B$22>=1,C$33-$S52+1-$B$22<=8),INDEX($C$27:$J$27,1,C$33-$S52+1-$B$22),0)*$U52*C$34 -> 0 | D52: =IF(AND(D$33-$S52+1-$B$22>=1,D$33-$S52+1-$B$22<=8),INDEX($C$27:$J$27,1,D$33-$S52+1-$B$22),0)*$U52*D$34 -> 0 | E52: =IF(AND(E$33-$S52+1-$B$22>=1,E$33-$S52+1-$B$22<=8),INDEX($C$27:$J$27,1,E$33-$S52+1-$B$22),0)*$U52*E$34 -> 0 | F52: =IF(AND(F$33-$S52+1-$B$22>=1,F$33-$S52+1-$B$22<=8),INDEX($C$27:$J$27,1,F$33-$S52+1-$B$22),0)*$U52*F$34 -> 0 | G52: =IF(AND(G$33-$S52+1-$B$22>=1,G$33-$S52+1-$B$22<=8),INDEX($C$27:$J$27,1,G$33-$S52+1-$B$22),0)*$U52*G$34 -> 0 | H52: =IF(AND(H$33-$S52+1-$B$22>=1,H$33-$S52+1-$B$22<=8),INDEX($C$27:$J$27,1,H$33-$S52+1-$B$22),0)*$U52*H$34 -> 0 | I52: =IF(AND(I$33-$S52+1-$B$22>=1,I$33-$S52+1-$B$22<=8),INDEX($C$27:$J$27,1,I$33-$S52+1-$B$22),0)*$U52*I$34 -> 0 | J52: =IF(AND(J$33-$S52+1-$B$22>=1,J$33-$S52+1-$B$22<=8),INDEX($C$27:$J$27,1,J$33-$S52+1-$B$22),0)*$U52*J$34 -> 0 | ... Q52: =IF(AND(Q$33-$S52+1-$B$22>=1,Q$33-$S52+1-$B$22<=8),INDEX($C$27:$J$27,1,Q$33-$S52+1-$B$22),0)*$U52*Q$34 -> 0 | S52: =$B$20+10 -> 2037 | T52: =IF($S52>$B$20+Scenarios!$C$8-1,0,$B$19*(1+$B$21*Scenarios!$C$7)^10) -> 0 | U52: =IFERROR($T52/INDEX($C$34:$Q$34,1,MATCH($S52,$C$33:$Q$33,0)),0) -> 0 | V52: =SUMPRODUCT(($C$25:$J$25<=$Q$33-$S52+1-$B$22)*$C$27:$J$27)*$U52 -> 0 | W52: =$U52-$V52 -> 0
A53: Refresher grant 12 | C53: =IF(AND(C$33-$S53+1-$B$22>=1,C$33-$S53+1-$B$22<=8),INDEX($C$27:$J$27,1,C$33-$S53+1-$B$22),0)*$U53*C$34 -> 0 | D53: =IF(AND(D$33-$S53+1-$B$22>=1,D$33-$S53+1-$B$22<=8),INDEX($C$27:$J$27,1,D$33-$S53+1-$B$22),0)*$U53*D$34 -> 0 | E53: =IF(AND(E$33-$S53+1-$B$22>=1,E$33-$S53+1-$B$22<=8),INDEX($C$27:$J$27,1,E$33-$S53+1-$B$22),0)*$U53*E$34 -> 0 | F53: =IF(AND(F$33-$S53+1-$B$22>=1,F$33-$S53+1-$B$22<=8),INDEX($C$27:$J$27,1,F$33-$S53+1-$B$22),0)*$U53*F$34 -> 0 | G53: =IF(AND(G$33-$S53+1-$B$22>=1,G$33-$S53+1-$B$22<=8),INDEX($C$27:$J$27,1,G$33-$S53+1-$B$22),0)*$U53*G$34 -> 0 | H53: =IF(AND(H$33-$S53+1-$B$22>=1,H$33-$S53+1-$B$22<=8),INDEX($C$27:$J$27,1,H$33-$S53+1-$B$22),0)*$U53*H$34 -> 0 | I53: =IF(AND(I$33-$S53+1-$B$22>=1,I$33-$S53+1-$B$22<=8),INDEX($C$27:$J$27,1,I$33-$S53+1-$B$22),0)*$U53*I$34 -> 0 | J53: =IF(AND(J$33-$S53+1-$B$22>=1,J$33-$S53+1-$B$22<=8),INDEX($C$27:$J$27,1,J$33-$S53+1-$B$22),0)*$U53*J$34 -> 0 | ... Q53: =IF(AND(Q$33-$S53+1-$B$22>=1,Q$33-$S53+1-$B$22<=8),INDEX($C$27:$J$27,1,Q$33-$S53+1-$B$22),0)*$U53*Q$34 -> 0 | S53: =$B$20+11 -> 2038 | T53: =IF($S53>$B$20+Scenarios!$C$8-1,0,$B$19*(1+$B$21*Scenarios!$C$7)^11) -> 0 | U53: =IFERROR($T53/INDEX($C$34:$Q$34,1,MATCH($S53,$C$33:$Q$33,0)),0) -> 0 | V53: =SUMPRODUCT(($C$25:$J$25<=$Q$33-$S53+1-$B$22)*$C$27:$J$27)*$U53 -> 0 | W53: =$U53-$V53 -> 0
A55: Initial grant vest ($) | C55: =C41 -> 0 | D55: =D41 -> 100000 | E55: =E41 -> 100000 | F55: =F41 -> 100000 | G55: =G41 -> 100000 | H55: =H41 -> 100000 | I55: =I41 -> 0 | J55: =J41 -> 0 | ... Q55: =Q41 -> 0
A56: Refresher vest ($) | C56: =SUM(C42:C53) -> 0 | D56: =SUM(D42:D53) -> 0 | E56: =SUM(E42:E53) -> 20000 | F56: =SUM(F42:F53) -> 40000 | G56: =SUM(G42:G53) -> 60000 | H56: =SUM(H42:H53) -> 80000 | I56: =SUM(I42:I53) -> 80000 | J56: =SUM(J42:J53) -> 60000 | ... Q56: =SUM(Q42:Q53) -> 0
A57: Total equity vest ($) | C57: =C55+C56 -> 0 | D57: =D55+D56 -> 100000 | E57: =E55+E56 -> 120000 | F57: =F55+F56 -> 140000 | G57: =G55+G56 -> 160000 | H57: =H55+H56 -> 180000 | I57: =I55+I56 -> 80000 | J57: =J55+J56 -> 60000 | ... Q57: =Q55+Q56 -> 0
A58: Concurrent grants vesting (count) | C58: =SUMPRODUCT((C41:C53>0)*1) -> 0 | D58: =SUMPRODUCT((D41:D53>0)*1) -> 1 | E58: =SUMPRODUCT((E41:E53>0)*1) -> 2 | F58: =SUMPRODUCT((F41:F53>0)*1) -> 3 | G58: =SUMPRODUCT((G41:G53>0)*1) -> 4 | H58: =SUMPRODUCT((H41:H53>0)*1) -> 5 | I58: =SUMPRODUCT((I41:I53>0)*1) -> 4 | J58: =SUMPRODUCT((J41:J53>0)*1) -> 3 | ... Q58: =SUMPRODUCT((Q41:Q53>0)*1) -> 0
A60: TOTAL GROSS COMPENSATION | C60: =C35+C37+C38+C57 -> 215000 | D60: =D35+D37+D38+D57 -> 339545.62 | E60: =E35+E37+E38+E57 -> 337763.81 | F60: =F35+F37+F38+F57 -> 361030.27 | G60: =G35+G37+G38+G57 -> 384345.72 | H60: =H35+H37+H38+H57 -> 407710.91 | I60: =I35+I37+I38+I57 -> 311126.57 | J60: =J35+J37+J38+J57 -> 294593.47 | ... Q60: =Q35+Q37+Q38+Q57 -> 260362.37
A61: Cumulative gross | C61: =C60 -> 215000 | D61: =C61+D60 -> 554545.62 | E61: =D61+E60 -> 892309.43 | F61: =E61+F60 -> 1253339.7 | G61: =F61+G60 -> 1637685.4 | H61: =G61+H60 -> 2045396.3 | I61: =H61+I60 -> 2356522.9 | J61: =I61+J60 -> 2651116.4 | K61: =J61+K60 -> 2929228.7 | ... Q61: =P61+Q60 -> 4454811.9
A63: Unvested shares at end of horizon | B63: =SUM(W41:W53) -> 0
A64: Unvested equity value at horizon price | B64: =B63*$Q$34 -> 0
A76: SCENARIO: MEDIUM | B76: =Scenarios!D$3 -> Medium
A77: Year index | C77: 1 | D77: 2 | E77: 3 | F77: 4 | G77: 5 | H77: 6 | I77: 7 | J77: 8 | K77: 9 | L77: 10 | M77: 11 | N77: 12 | O77: 13 | P77: 14 | Q77: 15
A78: Calendar year | C78: =$B$6 -> 2026 | D78: =C78+1 -> 2027 | E78: =D78+1 -> 2028 | F78: =E78+1 -> 2029 | G78: =F78+1 -> 2030 | H78: =G78+1 -> 2031 | I78: =H78+1 -> 2032 | J78: =I78+1 -> 2033 | K78: =J78+1 -> 2034 | ... Q78: =P78+1 -> 2040
A79: Share price ($) | C79: =$B$17 -> 180 | D79: =C79*(1+Scenarios!$D$4) -> 192.6 | E79: =D79*(1+Scenarios!$D$4) -> 206.082 | F79: =E79*(1+Scenarios!$D$4) -> 220.50774 | G79: =F79*(1+Scenarios!$D$4) -> 235.94328 | H79: =G79*(1+Scenarios!$D$4) -> 252.45931 | I79: =H79*(1+Scenarios!$D$4) -> 270.13146 | J79: =I79*(1+Scenarios!$D$4) -> 289.04067 | K79: =J79*(1+Scenarios!$D$4) -> 309.27351 | ... Q79: =P79*(1+Scenarios!$D$4) -> 464.13615
A80: Base salary | C80: =$B$7 -> 190000 | D80: =C80*(1+$B$8*Scenarios!$D$5) -> 195700 | E80: =D80*(1+$B$8*Scenarios!$D$5) -> 201571 | F80: =E80*(1+$B$8*Scenarios!$D$5) -> 207618.13 | G80: =F80*(1+$B$8*Scenarios!$D$5) -> 213846.67 | H80: =G80*(1+$B$8*Scenarios!$D$5) -> 220262.07 | I80: =H80*(1+$B$8*Scenarios!$D$5) -> 226869.94 | J80: =I80*(1+$B$8*Scenarios!$D$5) -> 233676.03 | K80: =J80*(1+$B$8*Scenarios!$D$5) -> 240686.32 | ... Q80: =P80*(1+$B$8*Scenarios!$D$5) -> 287392.05
A81: Bonus basis salary | C81: =IF($B$10="Prior",0,C80) -> 190000 | D81: =IF($B$10="Prior",C80,D80) -> 195700 | E81: =IF($B$10="Prior",D80,E80) -> 201571 | F81: =IF($B$10="Prior",E80,F80) -> 207618.13 | G81: =IF($B$10="Prior",F80,G80) -> 213846.67 | H81: =IF($B$10="Prior",G80,H80) -> 220262.07 | I81: =IF($B$10="Prior",H80,I80) -> 226869.94 | J81: =IF($B$10="Prior",I80,J80) -> 233676.03 | K81: =IF($B$10="Prior",J80,K80) -> 240686.32 | ... Q81: =IF($B$10="Prior",P80,Q80) -> 287392.05
A82: Annual bonus | C82: =IF($B$11="No",0,C81*$B$9*Scenarios!$D$6) -> 0 | D82: =D81*$B$9*Scenarios!$D$6 -> 29355 | E82: =E81*$B$9*Scenarios!$D$6 -> 30235.65 | F82: =F81*$B$9*Scenarios!$D$6 -> 31142.719 | G82: =G81*$B$9*Scenarios!$D$6 -> 32077.001 | H82: =H81*$B$9*Scenarios!$D$6 -> 33039.311 | I82: =I81*$B$9*Scenarios!$D$6 -> 34030.49 | J82: =J81*$B$9*Scenarios!$D$6 -> 35051.405 | K82: =K81*$B$9*Scenarios!$D$6 -> 36102.947 | ... Q82: =Q81*$B$9*Scenarios!$D$6 -> 43108.807
A83: Sign-on paid | C83: =$B$12*$B$13 -> 25000 | D83: =$B$12*$B$14 -> 25000 | E83: =$B$12*$B$15 -> 0 | F83: 0 | G83: 0 | H83: 0 | I83: 0 | J83: 0 | K83: 0 | L83: 0 | M83: 0 | N83: 0 | O83: 0 | P83: 0 | Q83: 0
A85: GRANT LEDGER — dollar value vesting each year, one row per grant | S85: Grant year | T85: Grant value ($) | U85: Shares granted | V85: Shares vested in horizon | W85: Unvested shares
A86: Initial grant | C86: =IF(AND(C$78-$S86+1-$B$22>=1,C$78-$S86+1-$B$22<=8),INDEX($C$26:$J$26,1,C$78-$S86+1-$B$22),0)*$U86*C$79 -> 0 | D86: =IF(AND(D$78-$S86+1-$B$22>=1,D$78-$S86+1-$B$22<=8),INDEX($C$26:$J$26,1,D$78-$S86+1-$B$22),0)*$U86*D$79 -> 107000 | E86: =IF(AND(E$78-$S86+1-$B$22>=1,E$78-$S86+1-$B$22<=8),INDEX($C$26:$J$26,1,E$78-$S86+1-$B$22),0)*$U86*E$79 -> 114490 | F86: =IF(AND(F$78-$S86+1-$B$22>=1,F$78-$S86+1-$B$22<=8),INDEX($C$26:$J$26,1,F$78-$S86+1-$B$22),0)*$U86*F$79 -> 122504.3 | G86: =IF(AND(G$78-$S86+1-$B$22>=1,G$78-$S86+1-$B$22<=8),INDEX($C$26:$J$26,1,G$78-$S86+1-$B$22),0)*$U86*G$79 -> 131079.6 | H86: =IF(AND(H$78-$S86+1-$B$22>=1,H$78-$S86+1-$B$22<=8),INDEX($C$26:$J$26,1,H$78-$S86+1-$B$22),0)*$U86*H$79 -> 140255.17 | I86: =IF(AND(I$78-$S86+1-$B$22>=1,I$78-$S86+1-$B$22<=8),INDEX($C$26:$J$26,1,I$78-$S86+1-$B$22),0)*$U86*I$79 -> 0 | J86: =IF(AND(J$78-$S86+1-$B$22>=1,J$78-$S86+1-$B$22<=8),INDEX($C$26:$J$26,1,J$78-$S86+1-$B$22),0)*$U86*J$79 -> 0 | ... Q86: =IF(AND(Q$78-$S86+1-$B$22>=1,Q$78-$S86+1-$B$22<=8),INDEX($C$26:$J$26,1,Q$78-$S86+1-$B$22),0)*$U86*Q$79 -> 0 | S86: =$B$6 -> 2026 | T86: =$B$18 -> 500000 | U86: =IFERROR(T86/$B$17,0) -> 2777.7778 | V86: =SUMPRODUCT(($C$25:$J$25<=$Q$78-$S86+1-$B$22)*$C$26:$J$26)*$U86 -> 2777.7778 | W86: =$U86-$V86 -> 0
A87: Refresher grant 1 | C87: =IF(AND(C$78-$S87+1-$B$22>=1,C$78-$S87+1-$B$22<=8),INDEX($C$27:$J$27,1,C$78-$S87+1-$B$22),0)*$U87*C$79 -> 0 | D87: =IF(AND(D$78-$S87+1-$B$22>=1,D$78-$S87+1-$B$22<=8),INDEX($C$27:$J$27,1,D$78-$S87+1-$B$22),0)*$U87*D$79 -> 0 | E87: =IF(AND(E$78-$S87+1-$B$22>=1,E$78-$S87+1-$B$22<=8),INDEX($C$27:$J$27,1,E$78-$S87+1-$B$22),0)*$U87*E$79 -> 21400 | F87: =IF(AND(F$78-$S87+1-$B$22>=1,F$78-$S87+1-$B$22<=8),INDEX($C$27:$J$27,1,F$78-$S87+1-$B$22),0)*$U87*F$79 -> 22898 | G87: =IF(AND(G$78-$S87+1-$B$22>=1,G$78-$S87+1-$B$22<=8),INDEX($C$27:$J$27,1,G$78-$S87+1-$B$22),0)*$U87*G$79 -> 24500.86 | H87: =IF(AND(H$78-$S87+1-$B$22>=1,H$78-$S87+1-$B$22<=8),INDEX($C$27:$J$27,1,H$78-$S87+1-$B$22),0)*$U87*H$79 -> 26215.92 | I87: =IF(AND(I$78-$S87+1-$B$22>=1,I$78-$S87+1-$B$22<=8),INDEX($C$27:$J$27,1,I$78-$S87+1-$B$22),0)*$U87*I$79 -> 28051.035 | J87: =IF(AND(J$78-$S87+1-$B$22>=1,J$78-$S87+1-$B$22<=8),INDEX($C$27:$J$27,1,J$78-$S87+1-$B$22),0)*$U87*J$79 -> 0 | ... Q87: =IF(AND(Q$78-$S87+1-$B$22>=1,Q$78-$S87+1-$B$22<=8),INDEX($C$27:$J$27,1,Q$78-$S87+1-$B$22),0)*$U87*Q$79 -> 0 | S87: =$B$20+0 -> 2027 | T87: =IF($S87>$B$20+Scenarios!$D$8-1,0,$B$19*(1+$B$21*Scenarios!$D$7)^0) -> 100000 | U87: =IFERROR($T87/INDEX($C$79:$Q$79,1,MATCH($S87,$C$78:$Q$78,0)),0) -> 519.2108 | V87: =SUMPRODUCT(($C$25:$J$25<=$Q$78-$S87+1-$B$22)*$C$27:$J$27)*$U87 -> 519.2108 | W87: =$U87-$V87 -> 0
A88: Refresher grant 2 | C88: =IF(AND(C$78-$S88+1-$B$22>=1,C$78-$S88+1-$B$22<=8),INDEX($C$27:$J$27,1,C$78-$S88+1-$B$22),0)*$U88*C$79 -> 0 | D88: =IF(AND(D$78-$S88+1-$B$22>=1,D$78-$S88+1-$B$22<=8),INDEX($C$27:$J$27,1,D$78-$S88+1-$B$22),0)*$U88*D$79 -> 0 | E88: =IF(AND(E$78-$S88+1-$B$22>=1,E$78-$S88+1-$B$22<=8),INDEX($C$27:$J$27,1,E$78-$S88+1-$B$22),0)*$U88*E$79 -> 0 | F88: =IF(AND(F$78-$S88+1-$B$22>=1,F$78-$S88+1-$B$22<=8),INDEX($C$27:$J$27,1,F$78-$S88+1-$B$22),0)*$U88*F$79 -> 22042 | G88: =IF(AND(G$78-$S88+1-$B$22>=1,G$78-$S88+1-$B$22<=8),INDEX($C$27:$J$27,1,G$78-$S88+1-$B$22),0)*$U88*G$79 -> 23584.94 | H88: =IF(AND(H$78-$S88+1-$B$22>=1,H$78-$S88+1-$B$22<=8),INDEX($C$27:$J$27,1,H$78-$S88+1-$B$22),0)*$U88*H$79 -> 25235.886 | I88: =IF(AND(I$78-$S88+1-$B$22>=1,I$78-$S88+1-$B$22<=8),INDEX($C$27:$J$27,1,I$78-$S88+1-$B$22),0)*$U88*I$79 -> 27002.398 | J88: =IF(AND(J$78-$S88+1-$B$22>=1,J$78-$S88+1-$B$22<=8),INDEX($C$27:$J$27,1,J$78-$S88+1-$B$22),0)*$U88*J$79 -> 28892.566 | ... Q88: =IF(AND(Q$78-$S88+1-$B$22>=1,Q$78-$S88+1-$B$22<=8),INDEX($C$27:$J$27,1,Q$78-$S88+1-$B$22),0)*$U88*Q$79 -> 0 | S88: =$B$20+1 -> 2028 | T88: =IF($S88>$B$20+Scenarios!$D$8-1,0,$B$19*(1+$B$21*Scenarios!$D$7)^1) -> 103000 | U88: =IFERROR($T88/INDEX($C$79:$Q$79,1,MATCH($S88,$C$78:$Q$78,0)),0) -> 499.80105 | V88: =SUMPRODUCT(($C$25:$J$25<=$Q$78-$S88+1-$B$22)*$C$27:$J$27)*$U88 -> 499.80105 | W88: =$U88-$V88 -> 0
A89: Refresher grant 3 | C89: =IF(AND(C$78-$S89+1-$B$22>=1,C$78-$S89+1-$B$22<=8),INDEX($C$27:$J$27,1,C$78-$S89+1-$B$22),0)*$U89*C$79 -> 0 | D89: =IF(AND(D$78-$S89+1-$B$22>=1,D$78-$S89+1-$B$22<=8),INDEX($C$27:$J$27,1,D$78-$S89+1-$B$22),0)*$U89*D$79 -> 0 | E89: =IF(AND(E$78-$S89+1-$B$22>=1,E$78-$S89+1-$B$22<=8),INDEX($C$27:$J$27,1,E$78-$S89+1-$B$22),0)*$U89*E$79 -> 0 | F89: =IF(AND(F$78-$S89+1-$B$22>=1,F$78-$S89+1-$B$22<=8),INDEX($C$27:$J$27,1,F$78-$S89+1-$B$22),0)*$U89*F$79 -> 0 | G89: =IF(AND(G$78-$S89+1-$B$22>=1,G$78-$S89+1-$B$22<=8),INDEX($C$27:$J$27,1,G$78-$S89+1-$B$22),0)*$U89*G$79 -> 22703.26 | H89: =IF(AND(H$78-$S89+1-$B$22>=1,H$78-$S89+1-$B$22<=8),INDEX($C$27:$J$27,1,H$78-$S89+1-$B$22),0)*$U89*H$79 -> 24292.488 | I89: =IF(AND(I$78-$S89+1-$B$22>=1,I$78-$S89+1-$B$22<=8),INDEX($C$27:$J$27,1,I$78-$S89+1-$B$22),0)*$U89*I$79 -> 25992.962 | J89: =IF(AND(J$78-$S89+1-$B$22>=1,J$78-$S89+1-$B$22<=8),INDEX($C$27:$J$27,1,J$78-$S89+1-$B$22),0)*$U89*J$79 -> 27812.47 | ... Q89: =IF(AND(Q$78-$S89+1-$B$22>=1,Q$78-$S89+1-$B$22<=8),INDEX($C$27:$J$27,1,Q$78-$S89+1-$B$22),0)*$U89*Q$79 -> 0 | S89: =$B$20+2 -> 2029 | T89: =IF($S89>$B$20+Scenarios!$D$8-1,0,$B$19*(1+$B$21*Scenarios!$D$7)^2) -> 106090 | U89: =IFERROR($T89/INDEX($C$79:$Q$79,1,MATCH($S89,$C$78:$Q$78,0)),0) -> 481.1169 | V89: =SUMPRODUCT(($C$25:$J$25<=$Q$78-$S89+1-$B$22)*$C$27:$J$27)*$U89 -> 481.1169 | W89: =$U89-$V89 -> 0
A90: Refresher grant 4 | C90: =IF(AND(C$78-$S90+1-$B$22>=1,C$78-$S90+1-$B$22<=8),INDEX($C$27:$J$27,1,C$78-$S90+1-$B$22),0)*$U90*C$79 -> 0 | D90: =IF(AND(D$78-$S90+1-$B$22>=1,D$78-$S90+1-$B$22<=8),INDEX($C$27:$J$27,1,D$78-$S90+1-$B$22),0)*$U90*D$79 -> 0 | E90: =IF(AND(E$78-$S90+1-$B$22>=1,E$78-$S90+1-$B$22<=8),INDEX($C$27:$J$27,1,E$78-$S90+1-$B$22),0)*$U90*E$79 -> 0 | F90: =IF(AND(F$78-$S90+1-$B$22>=1,F$78-$S90+1-$B$22<=8),INDEX($C$27:$J$27,1,F$78-$S90+1-$B$22),0)*$U90*F$79 -> 0 | G90: =IF(AND(G$78-$S90+1-$B$22>=1,G$78-$S90+1-$B$22<=8),INDEX($C$27:$J$27,1,G$78-$S90+1-$B$22),0)*$U90*G$79 -> 0 | H90: =IF(AND(H$78-$S90+1-$B$22>=1,H$78-$S90+1-$B$22<=8),INDEX($C$27:$J$27,1,H$78-$S90+1-$B$22),0)*$U90*H$79 -> 23384.358 | I90: =IF(AND(I$78-$S90+1-$B$22>=1,I$78-$S90+1-$B$22<=8),INDEX($C$27:$J$27,1,I$78-$S90+1-$B$22),0)*$U90*I$79 -> 25021.263 | J90: =IF(AND(J$78-$S90+1-$B$22>=1,J$78-$S90+1-$B$22<=8),INDEX($C$27:$J$27,1,J$78-$S90+1-$B$22),0)*$U90*J$79 -> 26772.751 | ... Q90: =IF(AND(Q$78-$S90+1-$B$22>=1,Q$78-$S90+1-$B$22<=8),INDEX($C$27:$J$27,1,Q$78-$S90+1-$B$22),0)*$U90*Q$79 -> 0 | S90: =$B$20+3 -> 2030 | T90: =IF($S90>$B$20+Scenarios!$D$8-1,0,$B$19*(1+$B$21*Scenarios!$D$7)^3) -> 109272.7 | U90: =IFERROR($T90/INDEX($C$79:$Q$79,1,MATCH($S90,$C$78:$Q$78,0)),0) -> 463.13122 | V90: =SUMPRODUCT(($C$25:$J$25<=$Q$78-$S90+1-$B$22)*$C$27:$J$27)*$U90 -> 463.13122 | W90: =$U90-$V90 -> 0
A91: Refresher grant 5 | C91: =IF(AND(C$78-$S91+1-$B$22>=1,C$78-$S91+1-$B$22<=8),INDEX($C$27:$J$27,1,C$78-$S91+1-$B$22),0)*$U91*C$79 -> 0 | D91: =IF(AND(D$78-$S91+1-$B$22>=1,D$78-$S91+1-$B$22<=8),INDEX($C$27:$J$27,1,D$78-$S91+1-$B$22),0)*$U91*D$79 -> 0 | E91: =IF(AND(E$78-$S91+1-$B$22>=1,E$78-$S91+1-$B$22<=8),INDEX($C$27:$J$27,1,E$78-$S91+1-$B$22),0)*$U91*E$79 -> 0 | F91: =IF(AND(F$78-$S91+1-$B$22>=1,F$78-$S91+1-$B$22<=8),INDEX($C$27:$J$27,1,F$78-$S91+1-$B$22),0)*$U91*F$79 -> 0 | G91: =IF(AND(G$78-$S91+1-$B$22>=1,G$78-$S91+1-$B$22<=8),INDEX($C$27:$J$27,1,G$78-$S91+1-$B$22),0)*$U91*G$79 -> 0 | H91: =IF(AND(H$78-$S91+1-$B$22>=1,H$78-$S91+1-$B$22<=8),INDEX($C$27:$J$27,1,H$78-$S91+1-$B$22),0)*$U91*H$79 -> 0 | I91: =IF(AND(I$78-$S91+1-$B$22>=1,I$78-$S91+1-$B$22<=8),INDEX($C$27:$J$27,1,I$78-$S91+1-$B$22),0)*$U91*I$79 -> 24085.889 | J91: =IF(AND(J$78-$S91+1-$B$22>=1,J$78-$S91+1-$B$22<=8),INDEX($C$27:$J$27,1,J$78-$S91+1-$B$22),0)*$U91*J$79 -> 25771.901 | ... Q91: =IF(AND(Q$78-$S91+1-$B$22>=1,Q$78-$S91+1-$B$22<=8),INDEX($C$27:$J$27,1,Q$78-$S91+1-$B$22),0)*$U91*Q$79 -> 0 | S91: =$B$20+4 -> 2031 | T91: =IF($S91>$B$20+Scenarios!$D$8-1,0,$B$19*(1+$B$21*Scenarios!$D$7)^4) -> 112550.88 | U91: =IFERROR($T91/INDEX($C$79:$Q$79,1,MATCH($S91,$C$78:$Q$78,0)),0) -> 445.8179 | V91: =SUMPRODUCT(($C$25:$J$25<=$Q$78-$S91+1-$B$22)*$C$27:$J$27)*$U91 -> 445.8179 | W91: =$U91-$V91 -> 0
A92: Refresher grant 6 | C92: =IF(AND(C$78-$S92+1-$B$22>=1,C$78-$S92+1-$B$22<=8),INDEX($C$27:$J$27,1,C$78-$S92+1-$B$22),0)*$U92*C$79 -> 0 | D92: =IF(AND(D$78-$S92+1-$B$22>=1,D$78-$S92+1-$B$22<=8),INDEX($C$27:$J$27,1,D$78-$S92+1-$B$22),0)*$U92*D$79 -> 0 | E92: =IF(AND(E$78-$S92+1-$B$22>=1,E$78-$S92+1-$B$22<=8),INDEX($C$27:$J$27,1,E$78-$S92+1-$B$22),0)*$U92*E$79 -> 0 | F92: =IF(AND(F$78-$S92+1-$B$22>=1,F$78-$S92+1-$B$22<=8),INDEX($C$27:$J$27,1,F$78-$S92+1-$B$22),0)*$U92*F$79 -> 0 | G92: =IF(AND(G$78-$S92+1-$B$22>=1,G$78-$S92+1-$B$22<=8),INDEX($C$27:$J$27,1,G$78-$S92+1-$B$22),0)*$U92*G$79 -> 0 | H92: =IF(AND(H$78-$S92+1-$B$22>=1,H$78-$S92+1-$B$22<=8),INDEX($C$27:$J$27,1,H$78-$S92+1-$B$22),0)*$U92*H$79 -> 0 | I92: =IF(AND(I$78-$S92+1-$B$22>=1,I$78-$S92+1-$B$22<=8),INDEX($C$27:$J$27,1,I$78-$S92+1-$B$22),0)*$U92*I$79 -> 0 | J92: =IF(AND(J$78-$S92+1-$B$22>=1,J$78-$S92+1-$B$22<=8),INDEX($C$27:$J$27,1,J$78-$S92+1-$B$22),0)*$U92*J$79 -> 24808.465 | ... Q92: =IF(AND(Q$78-$S92+1-$B$22>=1,Q$78-$S92+1-$B$22<=8),INDEX($C$27:$J$27,1,Q$78-$S92+1-$B$22),0)*$U92*Q$79 -> 0 | S92: =$B$20+5 -> 2032 | T92: =IF($S92>$B$20+Scenarios!$D$8-1,0,$B$19*(1+$B$21*Scenarios!$D$7)^5) -> 115927.41 | U92: =IFERROR($T92/INDEX($C$79:$Q$79,1,MATCH($S92,$C$78:$Q$78,0)),0) -> 429.15181 | V92: =SUMPRODUCT(($C$25:$J$25<=$Q$78-$S92+1-$B$22)*$C$27:$J$27)*$U92 -> 429.15181 | W92: =$U92-$V92 -> 0
A93: Refresher grant 7 | C93: =IF(AND(C$78-$S93+1-$B$22>=1,C$78-$S93+1-$B$22<=8),INDEX($C$27:$J$27,1,C$78-$S93+1-$B$22),0)*$U93*C$79 -> 0 | D93: =IF(AND(D$78-$S93+1-$B$22>=1,D$78-$S93+1-$B$22<=8),INDEX($C$27:$J$27,1,D$78-$S93+1-$B$22),0)*$U93*D$79 -> 0 | E93: =IF(AND(E$78-$S93+1-$B$22>=1,E$78-$S93+1-$B$22<=8),INDEX($C$27:$J$27,1,E$78-$S93+1-$B$22),0)*$U93*E$79 -> 0 | F93: =IF(AND(F$78-$S93+1-$B$22>=1,F$78-$S93+1-$B$22<=8),INDEX($C$27:$J$27,1,F$78-$S93+1-$B$22),0)*$U93*F$79 -> 0 | G93: =IF(AND(G$78-$S93+1-$B$22>=1,G$78-$S93+1-$B$22<=8),INDEX($C$27:$J$27,1,G$78-$S93+1-$B$22),0)*$U93*G$79 -> 0 | H93: =IF(AND(H$78-$S93+1-$B$22>=1,H$78-$S93+1-$B$22<=8),INDEX($C$27:$J$27,1,H$78-$S93+1-$B$22),0)*$U93*H$79 -> 0 | I93: =IF(AND(I$78-$S93+1-$B$22>=1,I$78-$S93+1-$B$22<=8),INDEX($C$27:$J$27,1,I$78-$S93+1-$B$22),0)*$U93*I$79 -> 0 | J93: =IF(AND(J$78-$S93+1-$B$22>=1,J$78-$S93+1-$B$22<=8),INDEX($C$27:$J$27,1,J$78-$S93+1-$B$22),0)*$U93*J$79 -> 0 | ... Q93: =IF(AND(Q$78-$S93+1-$B$22>=1,Q$78-$S93+1-$B$22<=8),INDEX($C$27:$J$27,1,Q$78-$S93+1-$B$22),0)*$U93*Q$79 -> 0 | S93: =$B$20+6 -> 2033 | T93: =IF($S93>$B$20+Scenarios!$D$8-1,0,$B$19*(1+$B$21*Scenarios!$D$7)^6) -> 119405.23 | U93: =IFERROR($T93/INDEX($C$79:$Q$79,1,MATCH($S93,$C$78:$Q$78,0)),0) -> 413.10876 | V93: =SUMPRODUCT(($C$25:$J$25<=$Q$78-$S93+1-$B$22)*$C$27:$J$27)*$U93 -> 413.10876 | W93: =$U93-$V93 -> 0
A94: Refresher grant 8 | C94: =IF(AND(C$78-$S94+1-$B$22>=1,C$78-$S94+1-$B$22<=8),INDEX($C$27:$J$27,1,C$78-$S94+1-$B$22),0)*$U94*C$79 -> 0 | D94: =IF(AND(D$78-$S94+1-$B$22>=1,D$78-$S94+1-$B$22<=8),INDEX($C$27:$J$27,1,D$78-$S94+1-$B$22),0)*$U94*D$79 -> 0 | E94: =IF(AND(E$78-$S94+1-$B$22>=1,E$78-$S94+1-$B$22<=8),INDEX($C$27:$J$27,1,E$78-$S94+1-$B$22),0)*$U94*E$79 -> 0 | F94: =IF(AND(F$78-$S94+1-$B$22>=1,F$78-$S94+1-$B$22<=8),INDEX($C$27:$J$27,1,F$78-$S94+1-$B$22),0)*$U94*F$79 -> 0 | G94: =IF(AND(G$78-$S94+1-$B$22>=1,G$78-$S94+1-$B$22<=8),INDEX($C$27:$J$27,1,G$78-$S94+1-$B$22),0)*$U94*G$79 -> 0 | H94: =IF(AND(H$78-$S94+1-$B$22>=1,H$78-$S94+1-$B$22<=8),INDEX($C$27:$J$27,1,H$78-$S94+1-$B$22),0)*$U94*H$79 -> 0 | I94: =IF(AND(I$78-$S94+1-$B$22>=1,I$78-$S94+1-$B$22<=8),INDEX($C$27:$J$27,1,I$78-$S94+1-$B$22),0)*$U94*I$79 -> 0 | J94: =IF(AND(J$78-$S94+1-$B$22>=1,J$78-$S94+1-$B$22<=8),INDEX($C$27:$J$27,1,J$78-$S94+1-$B$22),0)*$U94*J$79 -> 0 | ... Q94: =IF(AND(Q$78-$S94+1-$B$22>=1,Q$78-$S94+1-$B$22<=8),INDEX($C$27:$J$27,1,Q$78-$S94+1-$B$22),0)*$U94*Q$79 -> 0 | S94: =$B$20+7 -> 2034 | T94: =IF($S94>$B$20+Scenarios!$D$8-1,0,$B$19*(1+$B$21*Scenarios!$D$7)^7) -> 122987.39 | U94: =IFERROR($T94/INDEX($C$79:$Q$79,1,MATCH($S94,$C$78:$Q$78,0)),0) -> 397.66544 | V94: =SUMPRODUCT(($C$25:$J$25<=$Q$78-$S94+1-$B$22)*$C$27:$J$27)*$U94 -> 397.66544 | W94: =$U94-$V94 -> 0
A95: Refresher grant 9 | C95: =IF(AND(C$78-$S95+1-$B$22>=1,C$78-$S95+1-$B$22<=8),INDEX($C$27:$J$27,1,C$78-$S95+1-$B$22),0)*$U95*C$79 -> 0 | D95: =IF(AND(D$78-$S95+1-$B$22>=1,D$78-$S95+1-$B$22<=8),INDEX($C$27:$J$27,1,D$78-$S95+1-$B$22),0)*$U95*D$79 -> 0 | E95: =IF(AND(E$78-$S95+1-$B$22>=1,E$78-$S95+1-$B$22<=8),INDEX($C$27:$J$27,1,E$78-$S95+1-$B$22),0)*$U95*E$79 -> 0 | F95: =IF(AND(F$78-$S95+1-$B$22>=1,F$78-$S95+1-$B$22<=8),INDEX($C$27:$J$27,1,F$78-$S95+1-$B$22),0)*$U95*F$79 -> 0 | G95: =IF(AND(G$78-$S95+1-$B$22>=1,G$78-$S95+1-$B$22<=8),INDEX($C$27:$J$27,1,G$78-$S95+1-$B$22),0)*$U95*G$79 -> 0 | H95: =IF(AND(H$78-$S95+1-$B$22>=1,H$78-$S95+1-$B$22<=8),INDEX($C$27:$J$27,1,H$78-$S95+1-$B$22),0)*$U95*H$79 -> 0 | I95: =IF(AND(I$78-$S95+1-$B$22>=1,I$78-$S95+1-$B$22<=8),INDEX($C$27:$J$27,1,I$78-$S95+1-$B$22),0)*$U95*I$79 -> 0 | J95: =IF(AND(J$78-$S95+1-$B$22>=1,J$78-$S95+1-$B$22<=8),INDEX($C$27:$J$27,1,J$78-$S95+1-$B$22),0)*$U95*J$79 -> 0 | ... Q95: =IF(AND(Q$78-$S95+1-$B$22>=1,Q$78-$S95+1-$B$22<=8),INDEX($C$27:$J$27,1,Q$78-$S95+1-$B$22),0)*$U95*Q$79 -> 35534.211 | S95: =$B$20+8 -> 2035 | T95: =IF($S95>$B$20+Scenarios!$D$8-1,0,$B$19*(1+$B$21*Scenarios!$D$7)^8) -> 126677.01 | U95: =IFERROR($T95/INDEX($C$79:$Q$79,1,MATCH($S95,$C$78:$Q$78,0)),0) -> 382.79944 | V95: =SUMPRODUCT(($C$25:$J$25<=$Q$78-$S95+1-$B$22)*$C$27:$J$27)*$U95 -> 382.79944 | W95: =$U95-$V95 -> 0
A96: Refresher grant 10 | C96: =IF(AND(C$78-$S96+1-$B$22>=1,C$78-$S96+1-$B$22<=8),INDEX($C$27:$J$27,1,C$78-$S96+1-$B$22),0)*$U96*C$79 -> 0 | D96: =IF(AND(D$78-$S96+1-$B$22>=1,D$78-$S96+1-$B$22<=8),INDEX($C$27:$J$27,1,D$78-$S96+1-$B$22),0)*$U96*D$79 -> 0 | E96: =IF(AND(E$78-$S96+1-$B$22>=1,E$78-$S96+1-$B$22<=8),INDEX($C$27:$J$27,1,E$78-$S96+1-$B$22),0)*$U96*E$79 -> 0 | F96: =IF(AND(F$78-$S96+1-$B$22>=1,F$78-$S96+1-$B$22<=8),INDEX($C$27:$J$27,1,F$78-$S96+1-$B$22),0)*$U96*F$79 -> 0 | G96: =IF(AND(G$78-$S96+1-$B$22>=1,G$78-$S96+1-$B$22<=8),INDEX($C$27:$J$27,1,G$78-$S96+1-$B$22),0)*$U96*G$79 -> 0 | H96: =IF(AND(H$78-$S96+1-$B$22>=1,H$78-$S96+1-$B$22<=8),INDEX($C$27:$J$27,1,H$78-$S96+1-$B$22),0)*$U96*H$79 -> 0 | I96: =IF(AND(I$78-$S96+1-$B$22>=1,I$78-$S96+1-$B$22<=8),INDEX($C$27:$J$27,1,I$78-$S96+1-$B$22),0)*$U96*I$79 -> 0 | J96: =IF(AND(J$78-$S96+1-$B$22>=1,J$78-$S96+1-$B$22<=8),INDEX($C$27:$J$27,1,J$78-$S96+1-$B$22),0)*$U96*J$79 -> 0 | ... Q96: =IF(AND(Q$78-$S96+1-$B$22>=1,Q$78-$S96+1-$B$22<=8),INDEX($C$27:$J$27,1,Q$78-$S96+1-$B$22),0)*$U96*Q$79 -> 34205.83 | S96: =$B$20+9 -> 2036 | T96: =IF($S96>$B$20+Scenarios!$D$8-1,0,$B$19*(1+$B$21*Scenarios!$D$7)^9) -> 130477.32 | U96: =IFERROR($T96/INDEX($C$79:$Q$79,1,MATCH($S96,$C$78:$Q$78,0)),0) -> 368.48918 | V96: =SUMPRODUCT(($C$25:$J$25<=$Q$78-$S96+1-$B$22)*$C$27:$J$27)*$U96 -> 294.79134 | W96: =$U96-$V96 -> 73.697836
A97: Refresher grant 11 | C97: =IF(AND(C$78-$S97+1-$B$22>=1,C$78-$S97+1-$B$22<=8),INDEX($C$27:$J$27,1,C$78-$S97+1-$B$22),0)*$U97*C$79 -> 0 | D97: =IF(AND(D$78-$S97+1-$B$22>=1,D$78-$S97+1-$B$22<=8),INDEX($C$27:$J$27,1,D$78-$S97+1-$B$22),0)*$U97*D$79 -> 0 | E97: =IF(AND(E$78-$S97+1-$B$22>=1,E$78-$S97+1-$B$22<=8),INDEX($C$27:$J$27,1,E$78-$S97+1-$B$22),0)*$U97*E$79 -> 0 | F97: =IF(AND(F$78-$S97+1-$B$22>=1,F$78-$S97+1-$B$22<=8),INDEX($C$27:$J$27,1,F$78-$S97+1-$B$22),0)*$U97*F$79 -> 0 | G97: =IF(AND(G$78-$S97+1-$B$22>=1,G$78-$S97+1-$B$22<=8),INDEX($C$27:$J$27,1,G$78-$S97+1-$B$22),0)*$U97*G$79 -> 0 | H97: =IF(AND(H$78-$S97+1-$B$22>=1,H$78-$S97+1-$B$22<=8),INDEX($C$27:$J$27,1,H$78-$S97+1-$B$22),0)*$U97*H$79 -> 0 | I97: =IF(AND(I$78-$S97+1-$B$22>=1,I$78-$S97+1-$B$22<=8),INDEX($C$27:$J$27,1,I$78-$S97+1-$B$22),0)*$U97*I$79 -> 0 | J97: =IF(AND(J$78-$S97+1-$B$22>=1,J$78-$S97+1-$B$22<=8),INDEX($C$27:$J$27,1,J$78-$S97+1-$B$22),0)*$U97*J$79 -> 0 | ... Q97: =IF(AND(Q$78-$S97+1-$B$22>=1,Q$78-$S97+1-$B$22<=8),INDEX($C$27:$J$27,1,Q$78-$S97+1-$B$22),0)*$U97*Q$79 -> 32927.107 | S97: =$B$20+10 -> 2037 | T97: =IF($S97>$B$20+Scenarios!$D$8-1,0,$B$19*(1+$B$21*Scenarios!$D$7)^10) -> 134391.64 | U97: =IFERROR($T97/INDEX($C$79:$Q$79,1,MATCH($S97,$C$78:$Q$78,0)),0) -> 354.71388 | V97: =SUMPRODUCT(($C$25:$J$25<=$Q$78-$S97+1-$B$22)*$C$27:$J$27)*$U97 -> 212.82833 | W97: =$U97-$V97 -> 141.88555
A98: Refresher grant 12 | C98: =IF(AND(C$78-$S98+1-$B$22>=1,C$78-$S98+1-$B$22<=8),INDEX($C$27:$J$27,1,C$78-$S98+1-$B$22),0)*$U98*C$79 -> 0 | D98: =IF(AND(D$78-$S98+1-$B$22>=1,D$78-$S98+1-$B$22<=8),INDEX($C$27:$J$27,1,D$78-$S98+1-$B$22),0)*$U98*D$79 -> 0 | E98: =IF(AND(E$78-$S98+1-$B$22>=1,E$78-$S98+1-$B$22<=8),INDEX($C$27:$J$27,1,E$78-$S98+1-$B$22),0)*$U98*E$79 -> 0 | F98: =IF(AND(F$78-$S98+1-$B$22>=1,F$78-$S98+1-$B$22<=8),INDEX($C$27:$J$27,1,F$78-$S98+1-$B$22),0)*$U98*F$79 -> 0 | G98: =IF(AND(G$78-$S98+1-$B$22>=1,G$78-$S98+1-$B$22<=8),INDEX($C$27:$J$27,1,G$78-$S98+1-$B$22),0)*$U98*G$79 -> 0 | H98: =IF(AND(H$78-$S98+1-$B$22>=1,H$78-$S98+1-$B$22<=8),INDEX($C$27:$J$27,1,H$78-$S98+1-$B$22),0)*$U98*H$79 -> 0 | I98: =IF(AND(I$78-$S98+1-$B$22>=1,I$78-$S98+1-$B$22<=8),INDEX($C$27:$J$27,1,I$78-$S98+1-$B$22),0)*$U98*I$79 -> 0 | J98: =IF(AND(J$78-$S98+1-$B$22>=1,J$78-$S98+1-$B$22<=8),INDEX($C$27:$J$27,1,J$78-$S98+1-$B$22),0)*$U98*J$79 -> 0 | ... Q98: =IF(AND(Q$78-$S98+1-$B$22>=1,Q$78-$S98+1-$B$22<=8),INDEX($C$27:$J$27,1,Q$78-$S98+1-$B$22),0)*$U98*Q$79 -> 31696.187 | S98: =$B$20+11 -> 2038 | T98: =IF($S98>$B$20+Scenarios!$D$8-1,0,$B$19*(1+$B$21*Scenarios!$D$7)^11) -> 138423.39 | U98: =IFERROR($T98/INDEX($C$79:$Q$79,1,MATCH($S98,$C$78:$Q$78,0)),0) -> 341.45355 | V98: =SUMPRODUCT(($C$25:$J$25<=$Q$78-$S98+1-$B$22)*$C$27:$J$27)*$U98 -> 136.58142 | W98: =$U98-$V98 -> 204.87213
A100: Initial grant vest ($) | C100: =C86 -> 0 | D100: =D86 -> 107000 | E100: =E86 -> 114490 | F100: =F86 -> 122504.3 | G100: =G86 -> 131079.6 | H100: =H86 -> 140255.17 | I100: =I86 -> 0 | J100: =J86 -> 0 | ... Q100: =Q86 -> 0
A101: Refresher vest ($) | C101: =SUM(C87:C98) -> 0 | D101: =SUM(D87:D98) -> 0 | E101: =SUM(E87:E98) -> 21400 | F101: =SUM(F87:F98) -> 44940 | G101: =SUM(G87:G98) -> 70789.06 | H101: =SUM(H87:H98) -> 99128.652 | I101: =SUM(I87:I98) -> 130153.55 | J101: =SUM(J87:J98) -> 134058.15 | ... Q101: =SUM(Q87:Q98) -> 134363.34
A102: Total equity vest ($) | C102: =C100+C101 -> 0 | D102: =D100+D101 -> 107000 | E102: =E100+E101 -> 135890 | F102: =F100+F101 -> 167444.3 | G102: =G100+G101 -> 201868.66 | H102: =H100+H101 -> 239383.83 | I102: =I100+I101 -> 130153.55 | J102: =J100+J101 -> 134058.15 | ... Q102: =Q100+Q101 -> 134363.34
A103: Concurrent grants vesting (count) | C103: =SUMPRODUCT((C86:C98>0)*1) -> 0 | D103: =SUMPRODUCT((D86:D98>0)*1) -> 1 | E103: =SUMPRODUCT((E86:E98>0)*1) -> 2 | F103: =SUMPRODUCT((F86:F98>0)*1) -> 3 | G103: =SUMPRODUCT((G86:G98>0)*1) -> 4 | H103: =SUMPRODUCT((H86:H98>0)*1) -> 5 | I103: =SUMPRODUCT((I86:I98>0)*1) -> 5 | J103: =SUMPRODUCT((J86:J98>0)*1) -> 5 | ... Q103: =SUMPRODUCT((Q86:Q98>0)*1) -> 4
A105: TOTAL GROSS COMPENSATION | C105: =C80+C82+C83+C102 -> 215000 | D105: =D80+D82+D83+D102 -> 357055 | E105: =E80+E82+E83+E102 -> 367696.65 | F105: =F80+F82+F83+F102 -> 406205.15 | G105: =G80+G82+G83+G102 -> 447792.34 | H105: =H80+H82+H83+H102 -> 492685.21 | I105: =I80+I82+I83+I102 -> 391053.97 | J105: =J80+J82+J83+J102 -> 402785.59 | ... Q105: =Q80+Q82+Q83+Q102 -> 464864.19
A106: Cumulative gross | C106: =C105 -> 215000 | D106: =C106+D105 -> 572055 | E106: =D106+E105 -> 939751.65 | F106: =E106+F105 -> 1345956.8 | G106: =F106+G105 -> 1793749.1 | H106: =G106+H105 -> 2286434.3 | I106: =H106+I105 -> 2677488.3 | J106: =I106+J105 -> 3080273.9 | K106: =J106+K105 -> 3495143.1 | ... Q106: =P106+Q105 -> 6228681.9
A108: Unvested shares at end of horizon | B108: =SUM(W86:W98) -> 420.45552
A109: Unvested equity value at horizon price | B109: =B108*$Q$79 -> 195148.61
A121: SCENARIO: AGGRESSIVE | B121: =Scenarios!E$3 -> Aggressive
A122: Year index | C122: 1 | D122: 2 | E122: 3 | F122: 4 | G122: 5 | H122: 6 | I122: 7 | J122: 8 | K122: 9 | L122: 10 | M122: 11 | N122: 12 | O122: 13 | P122: 14 | Q122: 15
A123: Calendar year | C123: =$B$6 -> 2026 | D123: =C123+1 -> 2027 | E123: =D123+1 -> 2028 | F123: =E123+1 -> 2029 | G123: =F123+1 -> 2030 | H123: =G123+1 -> 2031 | I123: =H123+1 -> 2032 | J123: =I123+1 -> 2033 | K123: =J123+1 -> 2034 | ... Q123: =P123+1 -> 2040
A124: Share price ($) | C124: =$B$17 -> 180 | D124: =C124*(1+Scenarios!$E$4) -> 207 | E124: =D124*(1+Scenarios!$E$4) -> 238.05 | F124: =E124*(1+Scenarios!$E$4) -> 273.7575 | G124: =F124*(1+Scenarios!$E$4) -> 314.82112 | H124: =G124*(1+Scenarios!$E$4) -> 362.04429 | I124: =H124*(1+Scenarios!$E$4) -> 416.35094 | J124: =I124*(1+Scenarios!$E$4) -> 478.80358 | K124: =J124*(1+Scenarios!$E$4) -> 550.62412 | ... Q124: =P124*(1+Scenarios!$E$4) -> 1273.627
A125: Base salary | C125: =$B$7 -> 190000 | D125: =C125*(1+$B$8*Scenarios!$E$5) -> 198550 | E125: =D125*(1+$B$8*Scenarios!$E$5) -> 207484.75 | F125: =E125*(1+$B$8*Scenarios!$E$5) -> 216821.56 | G125: =F125*(1+$B$8*Scenarios!$E$5) -> 226578.53 | H125: =G125*(1+$B$8*Scenarios!$E$5) -> 236774.57 | I125: =H125*(1+$B$8*Scenarios!$E$5) -> 247429.42 | J125: =I125*(1+$B$8*Scenarios!$E$5) -> 258563.75 | K125: =J125*(1+$B$8*Scenarios!$E$5) -> 270199.12 | ... Q125: =P125*(1+$B$8*Scenarios!$E$5) -> 351869.54
A126: Bonus basis salary | C126: =IF($B$10="Prior",0,C125) -> 190000 | D126: =IF($B$10="Prior",C125,D125) -> 198550 | E126: =IF($B$10="Prior",D125,E125) -> 207484.75 | F126: =IF($B$10="Prior",E125,F125) -> 216821.56 | G126: =IF($B$10="Prior",F125,G125) -> 226578.53 | H126: =IF($B$10="Prior",G125,H125) -> 236774.57 | I126: =IF($B$10="Prior",H125,I125) -> 247429.42 | J126: =IF($B$10="Prior",I125,J125) -> 258563.75 | K126: =IF($B$10="Prior",J125,K125) -> 270199.12 | ... Q126: =IF($B$10="Prior",P125,Q125) -> 351869.54
A127: Annual bonus | C127: =IF($B$11="No",0,C126*$B$9*Scenarios!$E$6) -> 0 | D127: =D126*$B$9*Scenarios!$E$6 -> 37228.125 | E127: =E126*$B$9*Scenarios!$E$6 -> 38903.391 | F127: =F126*$B$9*Scenarios!$E$6 -> 40654.043 | G127: =G126*$B$9*Scenarios!$E$6 -> 42483.475 | H127: =H126*$B$9*Scenarios!$E$6 -> 44395.232 | I127: =I126*$B$9*Scenarios!$E$6 -> 46393.017 | J127: =J126*$B$9*Scenarios!$E$6 -> 48480.703 | K127: =K126*$B$9*Scenarios!$E$6 -> 50662.334 | ... Q127: =Q126*$B$9*Scenarios!$E$6 -> 65975.538
A128: Sign-on paid | C128: =$B$12*$B$13 -> 25000 | D128: =$B$12*$B$14 -> 25000 | E128: =$B$12*$B$15 -> 0 | F128: 0 | G128: 0 | H128: 0 | I128: 0 | J128: 0 | K128: 0 | L128: 0 | M128: 0 | N128: 0 | O128: 0 | P128: 0 | Q128: 0
A130: GRANT LEDGER — dollar value vesting each year, one row per grant | S130: Grant year | T130: Grant value ($) | U130: Shares granted | V130: Shares vested in horizon | W130: Unvested shares
A131: Initial grant | C131: =IF(AND(C$123-$S131+1-$B$22>=1,C$123-$S131+1-$B$22<=8),INDEX($C$26:$J$26,1,C$123-$S131+1-$B$22),0)*$U131*C$124 -> 0 | D131: =IF(AND(D$123-$S131+1-$B$22>=1,D$123-$S131+1-$B$22<=8),INDEX($C$26:$J$26,1,D$123-$S131+1-$B$22),0)*$U131*D$124 -> 115000 | E131: =IF(AND(E$123-$S131+1-$B$22>=1,E$123-$S131+1-$B$22<=8),INDEX($C$26:$J$26,1,E$123-$S131+1-$B$22),0)*$U131*E$124 -> 132250 | F131: =IF(AND(F$123-$S131+1-$B$22>=1,F$123-$S131+1-$B$22<=8),INDEX($C$26:$J$26,1,F$123-$S131+1-$B$22),0)*$U131*F$124 -> 152087.5 | G131: =IF(AND(G$123-$S131+1-$B$22>=1,G$123-$S131+1-$B$22<=8),INDEX($C$26:$J$26,1,G$123-$S131+1-$B$22),0)*$U131*G$124 -> 174900.62 | H131: =IF(AND(H$123-$S131+1-$B$22>=1,H$123-$S131+1-$B$22<=8),INDEX($C$26:$J$26,1,H$123-$S131+1-$B$22),0)*$U131*H$124 -> 201135.72 | I131: =IF(AND(I$123-$S131+1-$B$22>=1,I$123-$S131+1-$B$22<=8),INDEX($C$26:$J$26,1,I$123-$S131+1-$B$22),0)*$U131*I$124 -> 0 | J131: =IF(AND(J$123-$S131+1-$B$22>=1,J$123-$S131+1-$B$22<=8),INDEX($C$26:$J$26,1,J$123-$S131+1-$B$22),0)*$U131*J$124 -> 0 | ... Q131: =IF(AND(Q$123-$S131+1-$B$22>=1,Q$123-$S131+1-$B$22<=8),INDEX($C$26:$J$26,1,Q$123-$S131+1-$B$22),0)*$U131*Q$124 -> 0 | S131: =$B$6 -> 2026 | T131: =$B$18 -> 500000 | U131: =IFERROR(T131/$B$17,0) -> 2777.7778 | V131: =SUMPRODUCT(($C$25:$J$25<=$Q$123-$S131+1-$B$22)*$C$26:$J$26)*$U131 -> 2777.7778 | W131: =$U131-$V131 -> 0
A132: Refresher grant 1 | C132: =IF(AND(C$123-$S132+1-$B$22>=1,C$123-$S132+1-$B$22<=8),INDEX($C$27:$J$27,1,C$123-$S132+1-$B$22),0)*$U132*C$124 -> 0 | D132: =IF(AND(D$123-$S132+1-$B$22>=1,D$123-$S132+1-$B$22<=8),INDEX($C$27:$J$27,1,D$123-$S132+1-$B$22),0)*$U132*D$124 -> 0 | E132: =IF(AND(E$123-$S132+1-$B$22>=1,E$123-$S132+1-$B$22<=8),INDEX($C$27:$J$27,1,E$123-$S132+1-$B$22),0)*$U132*E$124 -> 23000 | F132: =IF(AND(F$123-$S132+1-$B$22>=1,F$123-$S132+1-$B$22<=8),INDEX($C$27:$J$27,1,F$123-$S132+1-$B$22),0)*$U132*F$124 -> 26450 | G132: =IF(AND(G$123-$S132+1-$B$22>=1,G$123-$S132+1-$B$22<=8),INDEX($C$27:$J$27,1,G$123-$S132+1-$B$22),0)*$U132*G$124 -> 30417.5 | H132: =IF(AND(H$123-$S132+1-$B$22>=1,H$123-$S132+1-$B$22<=8),INDEX($C$27:$J$27,1,H$123-$S132+1-$B$22),0)*$U132*H$124 -> 34980.125 | I132: =IF(AND(I$123-$S132+1-$B$22>=1,I$123-$S132+1-$B$22<=8),INDEX($C$27:$J$27,1,I$123-$S132+1-$B$22),0)*$U132*I$124 -> 40227.144 | J132: =IF(AND(J$123-$S132+1-$B$22>=1,J$123-$S132+1-$B$22<=8),INDEX($C$27:$J$27,1,J$123-$S132+1-$B$22),0)*$U132*J$124 -> 0 | ... Q132: =IF(AND(Q$123-$S132+1-$B$22>=1,Q$123-$S132+1-$B$22<=8),INDEX($C$27:$J$27,1,Q$123-$S132+1-$B$22),0)*$U132*Q$124 -> 0 | S132: =$B$20+0 -> 2027 | T132: =IF($S132>$B$20+Scenarios!$E$8-1,0,$B$19*(1+$B$21*Scenarios!$E$7)^0) -> 100000 | U132: =IFERROR($T132/INDEX($C$124:$Q$124,1,MATCH($S132,$C$123:$Q$123,0)),0) -> 483.09179 | V132: =SUMPRODUCT(($C$25:$J$25<=$Q$123-$S132+1-$B$22)*$C$27:$J$27)*$U132 -> 483.09179 | W132: =$U132-$V132 -> 0
A133: Refresher grant 2 | C133: =IF(AND(C$123-$S133+1-$B$22>=1,C$123-$S133+1-$B$22<=8),INDEX($C$27:$J$27,1,C$123-$S133+1-$B$22),0)*$U133*C$124 -> 0 | D133: =IF(AND(D$123-$S133+1-$B$22>=1,D$123-$S133+1-$B$22<=8),INDEX($C$27:$J$27,1,D$123-$S133+1-$B$22),0)*$U133*D$124 -> 0 | E133: =IF(AND(E$123-$S133+1-$B$22>=1,E$123-$S133+1-$B$22<=8),INDEX($C$27:$J$27,1,E$123-$S133+1-$B$22),0)*$U133*E$124 -> 0 | F133: =IF(AND(F$123-$S133+1-$B$22>=1,F$123-$S133+1-$B$22<=8),INDEX($C$27:$J$27,1,F$123-$S133+1-$B$22),0)*$U133*F$124 -> 23690 | G133: =IF(AND(G$123-$S133+1-$B$22>=1,G$123-$S133+1-$B$22<=8),INDEX($C$27:$J$27,1,G$123-$S133+1-$B$22),0)*$U133*G$124 -> 27243.5 | H133: =IF(AND(H$123-$S133+1-$B$22>=1,H$123-$S133+1-$B$22<=8),INDEX($C$27:$J$27,1,H$123-$S133+1-$B$22),0)*$U133*H$124 -> 31330.025 | I133: =IF(AND(I$123-$S133+1-$B$22>=1,I$123-$S133+1-$B$22<=8),INDEX($C$27:$J$27,1,I$123-$S133+1-$B$22),0)*$U133*I$124 -> 36029.529 | J133: =IF(AND(J$123-$S133+1-$B$22>=1,J$123-$S133+1-$B$22<=8),INDEX($C$27:$J$27,1,J$123-$S133+1-$B$22),0)*$U133*J$124 -> 41433.958 | ... Q133: =IF(AND(Q$123-$S133+1-$B$22>=1,Q$123-$S133+1-$B$22<=8),INDEX($C$27:$J$27,1,Q$123-$S133+1-$B$22),0)*$U133*Q$124 -> 0 | S133: =$B$20+1 -> 2028 | T133: =IF($S133>$B$20+Scenarios!$E$8-1,0,$B$19*(1+$B$21*Scenarios!$E$7)^1) -> 103000 | U133: =IFERROR($T133/INDEX($C$124:$Q$124,1,MATCH($S133,$C$123:$Q$123,0)),0) -> 432.68221 | V133: =SUMPRODUCT(($C$25:$J$25<=$Q$123-$S133+1-$B$22)*$C$27:$J$27)*$U133 -> 432.68221 | W133: =$U133-$V133 -> 0
...

Sheet Current_Comp
A1: CURRENT COMPENSATION (BASELINE)
A2: Blue = you edit. Black = formula, do not edit. Green = link to another tab. Yellow = key assumption.
A3: INPUTS
A4: Company name | B4: Current employer
A5: Ticker | B5: n/a
A6: Start calendar year | B6: 2026
A7: Base salary at start | B7: 275000
A8: Merit increase %/yr | B8: 0.03
A9: Bonus target % of base | B9: 0.22
A10: Bonus basis (Current or Prior) | B10: Current
A11: Bonus paid in Year 1? (Yes/No) | B11: Yes
A12: Sign-on total | B12: 0
A13: Sign-on % paid Year 1 | B13: 0
A14: Sign-on % paid Year 2 | B14: 0
A15: Sign-on % paid Year 3 | B15: 0
A16: Sign-on check (must equal 100%) | B16: =SUM(B13:B15) -> 0 | C16: =IF(ROUND(B16,6)=1,"OK","ERROR - must total 100%") -> ERROR - must total 100%
A17: Grant-date share price | B17: 1
A18: Initial grant value ($) | B18: 0
A19: Refresher value, first grant ($) | B19: 0
A20: First refresher calendar year | B20: 2027
A21: Refresher grant growth %/yr | B21: 0
A22: First vest timing (0 = grant year, 1 = year after) | B22: 1
A23: Share price is entered manually. Replace with a market data lookup in the web app. The original workbook vested in the grant year itself (offset 0); real grants usually vest a year later (offset 1).
A24: VESTING SCHEDULES — % of the grant that vests in each year AFTER the grant date
A25: Years after grant | C25: 1 | D25: 2 | E25: 3 | F25: 4 | G25: 5 | H25: 6 | I25: 7 | J25: 8 | K25: Total
A26: Initial grant | C26: 0.25 | D26: 0.25 | E26: 0.25 | F26: 0.25 | G26: 0 | H26: 0 | I26: 0 | J26: 0 | K26: =SUM(C26:J26) -> 1 | L26: =IF(ROUND(K26,6)=1,"OK","ERROR - must total 100%") -> OK
A27: Refresher grants | C27: 0.25 | D27: 0.25 | E27: 0.25 | F27: 0.25 | G27: 0 | H27: 0 | I27: 0 | J27: 0 | K27: =SUM(C27:J27) -> 1 | L27: =IF(ROUND(K27,6)=1,"OK","ERROR - must total 100%") -> OK
A28: Annual granularity. Sub-annual (quarterly/monthly) vesting and cliffs are handled in the web app, not here.
A31: SCENARIO: CONSERVATIVE | B31: =Scenarios!C$3 -> Conservative
A32: Year index | C32: 1 | D32: 2 | E32: 3 | F32: 4 | G32: 5 | H32: 6 | I32: 7 | J32: 8 | K32: 9 | L32: 10 | M32: 11 | N32: 12 | O32: 13 | P32: 14 | Q32: 15
A33: Calendar year | C33: =$B$6 -> 2026 | D33: =C33+1 -> 2027 | E33: =D33+1 -> 2028 | F33: =E33+1 -> 2029 | G33: =F33+1 -> 2030 | H33: =G33+1 -> 2031 | I33: =H33+1 -> 2032 | J33: =I33+1 -> 2033 | K33: =J33+1 -> 2034 | ... Q33: =P33+1 -> 2040
A34: Share price ($) | C34: =$B$17 -> 1 | D34: =C34*(1+Scenarios!$C$4) -> 1 | E34: =D34*(1+Scenarios!$C$4) -> 1 | F34: =E34*(1+Scenarios!$C$4) -> 1 | G34: =F34*(1+Scenarios!$C$4) -> 1 | H34: =G34*(1+Scenarios!$C$4) -> 1 | I34: =H34*(1+Scenarios!$C$4) -> 1 | J34: =I34*(1+Scenarios!$C$4) -> 1 | K34: =J34*(1+Scenarios!$C$4) -> 1 | ... Q34: =P34*(1+Scenarios!$C$4) -> 1
A35: Base salary | C35: =$B$7 -> 275000 | D35: =C35*(1+$B$8*Scenarios!$C$5) -> 279125 | E35: =D35*(1+$B$8*Scenarios!$C$5) -> 283311.88 | F35: =E35*(1+$B$8*Scenarios!$C$5) -> 287561.55 | G35: =F35*(1+$B$8*Scenarios!$C$5) -> 291874.98 | H35: =G35*(1+$B$8*Scenarios!$C$5) -> 296253.1 | I35: =H35*(1+$B$8*Scenarios!$C$5) -> 300696.9 | J35: =I35*(1+$B$8*Scenarios!$C$5) -> 305207.35 | K35: =J35*(1+$B$8*Scenarios!$C$5) -> 309785.46 | ... Q35: =P35*(1+$B$8*Scenarios!$C$5) -> 338732.83
A36: Bonus basis salary | C36: =IF($B$10="Prior",0,C35) -> 275000 | D36: =IF($B$10="Prior",C35,D35) -> 279125 | E36: =IF($B$10="Prior",D35,E35) -> 283311.88 | F36: =IF($B$10="Prior",E35,F35) -> 287561.55 | G36: =IF($B$10="Prior",F35,G35) -> 291874.98 | H36: =IF($B$10="Prior",G35,H35) -> 296253.1 | I36: =IF($B$10="Prior",H35,I35) -> 300696.9 | J36: =IF($B$10="Prior",I35,J35) -> 305207.35 | K36: =IF($B$10="Prior",J35,K35) -> 309785.46 | ... Q36: =IF($B$10="Prior",P35,Q35) -> 338732.83
A37: Annual bonus | C37: =IF($B$11="No",0,C36*$B$9*Scenarios!$C$6) -> 45375 | D37: =D36*$B$9*Scenarios!$C$6 -> 46055.625 | E37: =E36*$B$9*Scenarios!$C$6 -> 46746.459 | F37: =F36*$B$9*Scenarios!$C$6 -> 47447.656 | G37: =G36*$B$9*Scenarios!$C$6 -> 48159.371 | H37: =H36*$B$9*Scenarios!$C$6 -> 48881.762 | I37: =I36*$B$9*Scenarios!$C$6 -> 49614.988 | J37: =J36*$B$9*Scenarios!$C$6 -> 50359.213 | K37: =K36*$B$9*Scenarios!$C$6 -> 51114.601 | ... Q37: =Q36*$B$9*Scenarios!$C$6 -> 55890.916
A38: Sign-on paid | C38: =$B$12*$B$13 -> 0 | D38: =$B$12*$B$14 -> 0 | E38: =$B$12*$B$15 -> 0 | F38: 0 | G38: 0 | H38: 0 | I38: 0 | J38: 0 | K38: 0 | L38: 0 | M38: 0 | N38: 0 | O38: 0 | P38: 0 | Q38: 0
A40: GRANT LEDGER — dollar value vesting each year, one row per grant | S40: Grant year | T40: Grant value ($) | U40: Shares granted | V40: Shares vested in horizon | W40: Unvested shares
A41: Initial grant | C41: =IF(AND(C$33-$S41+1-$B$22>=1,C$33-$S41+1-$B$22<=8),INDEX($C$26:$J$26,1,C$33-$S41+1-$B$22),0)*$U41*C$34 -> 0 | D41: =IF(AND(D$33-$S41+1-$B$22>=1,D$33-$S41+1-$B$22<=8),INDEX($C$26:$J$26,1,D$33-$S41+1-$B$22),0)*$U41*D$34 -> 0 | E41: =IF(AND(E$33-$S41+1-$B$22>=1,E$33-$S41+1-$B$22<=8),INDEX($C$26:$J$26,1,E$33-$S41+1-$B$22),0)*$U41*E$34 -> 0 | F41: =IF(AND(F$33-$S41+1-$B$22>=1,F$33-$S41+1-$B$22<=8),INDEX($C$26:$J$26,1,F$33-$S41+1-$B$22),0)*$U41*F$34 -> 0 | G41: =IF(AND(G$33-$S41+1-$B$22>=1,G$33-$S41+1-$B$22<=8),INDEX($C$26:$J$26,1,G$33-$S41+1-$B$22),0)*$U41*G$34 -> 0 | H41: =IF(AND(H$33-$S41+1-$B$22>=1,H$33-$S41+1-$B$22<=8),INDEX($C$26:$J$26,1,H$33-$S41+1-$B$22),0)*$U41*H$34 -> 0 | I41: =IF(AND(I$33-$S41+1-$B$22>=1,I$33-$S41+1-$B$22<=8),INDEX($C$26:$J$26,1,I$33-$S41+1-$B$22),0)*$U41*I$34 -> 0 | J41: =IF(AND(J$33-$S41+1-$B$22>=1,J$33-$S41+1-$B$22<=8),INDEX($C$26:$J$26,1,J$33-$S41+1-$B$22),0)*$U41*J$34 -> 0 | ... Q41: =IF(AND(Q$33-$S41+1-$B$22>=1,Q$33-$S41+1-$B$22<=8),INDEX($C$26:$J$26,1,Q$33-$S41+1-$B$22),0)*$U41*Q$34 -> 0 | S41: =$B$6 -> 2026 | T41: =$B$18 -> 0 | U41: =IFERROR(T41/$B$17,0) -> 0 | V41: =SUMPRODUCT(($C$25:$J$25<=$Q$33-$S41+1-$B$22)*$C$26:$J$26)*$U41 -> 0 | W41: =$U41-$V41 -> 0
A42: Refresher grant 1 | C42: =IF(AND(C$33-$S42+1-$B$22>=1,C$33-$S42+1-$B$22<=8),INDEX($C$27:$J$27,1,C$33-$S42+1-$B$22),0)*$U42*C$34 -> 0 | D42: =IF(AND(D$33-$S42+1-$B$22>=1,D$33-$S42+1-$B$22<=8),INDEX($C$27:$J$27,1,D$33-$S42+1-$B$22),0)*$U42*D$34 -> 0 | E42: =IF(AND(E$33-$S42+1-$B$22>=1,E$33-$S42+1-$B$22<=8),INDEX($C$27:$J$27,1,E$33-$S42+1-$B$22),0)*$U42*E$34 -> 0 | F42: =IF(AND(F$33-$S42+1-$B$22>=1,F$33-$S42+1-$B$22<=8),INDEX($C$27:$J$27,1,F$33-$S42+1-$B$22),0)*$U42*F$34 -> 0 | G42: =IF(AND(G$33-$S42+1-$B$22>=1,G$33-$S42+1-$B$22<=8),INDEX($C$27:$J$27,1,G$33-$S42+1-$B$22),0)*$U42*G$34 -> 0 | H42: =IF(AND(H$33-$S42+1-$B$22>=1,H$33-$S42+1-$B$22<=8),INDEX($C$27:$J$27,1,H$33-$S42+1-$B$22),0)*$U42*H$34 -> 0 | I42: =IF(AND(I$33-$S42+1-$B$22>=1,I$33-$S42+1-$B$22<=8),INDEX($C$27:$J$27,1,I$33-$S42+1-$B$22),0)*$U42*I$34 -> 0 | J42: =IF(AND(J$33-$S42+1-$B$22>=1,J$33-$S42+1-$B$22<=8),INDEX($C$27:$J$27,1,J$33-$S42+1-$B$22),0)*$U42*J$34 -> 0 | ... Q42: =IF(AND(Q$33-$S42+1-$B$22>=1,Q$33-$S42+1-$B$22<=8),INDEX($C$27:$J$27,1,Q$33-$S42+1-$B$22),0)*$U42*Q$34 -> 0 | S42: =$B$20+0 -> 2027 | T42: =IF($S42>$B$20+Scenarios!$C$8-1,0,$B$19*(1+$B$21*Scenarios!$C$7)^0) -> 0 | U42: =IFERROR($T42/INDEX($C$34:$Q$34,1,MATCH($S42,$C$33:$Q$33,0)),0) -> 0 | V42: =SUMPRODUCT(($C$25:$J$25<=$Q$33-$S42+1-$B$22)*$C$27:$J$27)*$U42 -> 0 | W42: =$U42-$V42 -> 0
A43: Refresher grant 2 | C43: =IF(AND(C$33-$S43+1-$B$22>=1,C$33-$S43+1-$B$22<=8),INDEX($C$27:$J$27,1,C$33-$S43+1-$B$22),0)*$U43*C$34 -> 0 | D43: =IF(AND(D$33-$S43+1-$B$22>=1,D$33-$S43+1-$B$22<=8),INDEX($C$27:$J$27,1,D$33-$S43+1-$B$22),0)*$U43*D$34 -> 0 | E43: =IF(AND(E$33-$S43+1-$B$22>=1,E$33-$S43+1-$B$22<=8),INDEX($C$27:$J$27,1,E$33-$S43+1-$B$22),0)*$U43*E$34 -> 0 | F43: =IF(AND(F$33-$S43+1-$B$22>=1,F$33-$S43+1-$B$22<=8),INDEX($C$27:$J$27,1,F$33-$S43+1-$B$22),0)*$U43*F$34 -> 0 | G43: =IF(AND(G$33-$S43+1-$B$22>=1,G$33-$S43+1-$B$22<=8),INDEX($C$27:$J$27,1,G$33-$S43+1-$B$22),0)*$U43*G$34 -> 0 | H43: =IF(AND(H$33-$S43+1-$B$22>=1,H$33-$S43+1-$B$22<=8),INDEX($C$27:$J$27,1,H$33-$S43+1-$B$22),0)*$U43*H$34 -> 0 | I43: =IF(AND(I$33-$S43+1-$B$22>=1,I$33-$S43+1-$B$22<=8),INDEX($C$27:$J$27,1,I$33-$S43+1-$B$22),0)*$U43*I$34 -> 0 | J43: =IF(AND(J$33-$S43+1-$B$22>=1,J$33-$S43+1-$B$22<=8),INDEX($C$27:$J$27,1,J$33-$S43+1-$B$22),0)*$U43*J$34 -> 0 | ... Q43: =IF(AND(Q$33-$S43+1-$B$22>=1,Q$33-$S43+1-$B$22<=8),INDEX($C$27:$J$27,1,Q$33-$S43+1-$B$22),0)*$U43*Q$34 -> 0 | S43: =$B$20+1 -> 2028 | T43: =IF($S43>$B$20+Scenarios!$C$8-1,0,$B$19*(1+$B$21*Scenarios!$C$7)^1) -> 0 | U43: =IFERROR($T43/INDEX($C$34:$Q$34,1,MATCH($S43,$C$33:$Q$33,0)),0) -> 0 | V43: =SUMPRODUCT(($C$25:$J$25<=$Q$33-$S43+1-$B$22)*$C$27:$J$27)*$U43 -> 0 | W43: =$U43-$V43 -> 0
A44: Refresher grant 3 | C44: =IF(AND(C$33-$S44+1-$B$22>=1,C$33-$S44+1-$B$22<=8),INDEX($C$27:$J$27,1,C$33-$S44+1-$B$22),0)*$U44*C$34 -> 0 | D44: =IF(AND(D$33-$S44+1-$B$22>=1,D$33-$S44+1-$B$22<=8),INDEX($C$27:$J$27,1,D$33-$S44+1-$B$22),0)*$U44*D$34 -> 0 | E44: =IF(AND(E$33-$S44+1-$B$22>=1,E$33-$S44+1-$B$22<=8),INDEX($C$27:$J$27,1,E$33-$S44+1-$B$22),0)*$U44*E$34 -> 0 | F44: =IF(AND(F$33-$S44+1-$B$22>=1,F$33-$S44+1-$B$22<=8),INDEX($C$27:$J$27,1,F$33-$S44+1-$B$22),0)*$U44*F$34 -> 0 | G44: =IF(AND(G$33-$S44+1-$B$22>=1,G$33-$S44+1-$B$22<=8),INDEX($C$27:$J$27,1,G$33-$S44+1-$B$22),0)*$U44*G$34 -> 0 | H44: =IF(AND(H$33-$S44+1-$B$22>=1,H$33-$S44+1-$B$22<=8),INDEX($C$27:$J$27,1,H$33-$S44+1-$B$22),0)*$U44*H$34 -> 0 | I44: =IF(AND(I$33-$S44+1-$B$22>=1,I$33-$S44+1-$B$22<=8),INDEX($C$27:$J$27,1,I$33-$S44+1-$B$22),0)*$U44*I$34 -> 0 | J44: =IF(AND(J$33-$S44+1-$B$22>=1,J$33-$S44+1-$B$22<=8),INDEX($C$27:$J$27,1,J$33-$S44+1-$B$22),0)*$U44*J$34 -> 0 | ... Q44: =IF(AND(Q$33-$S44+1-$B$22>=1,Q$33-$S44+1-$B$22<=8),INDEX($C$27:$J$27,1,Q$33-$S44+1-$B$22),0)*$U44*Q$34 -> 0 | S44: =$B$20+2 -> 2029 | T44: =IF($S44>$B$20+Scenarios!$C$8-1,0,$B$19*(1+$B$21*Scenarios!$C$7)^2) -> 0 | U44: =IFERROR($T44/INDEX($C$34:$Q$34,1,MATCH($S44,$C$33:$Q$33,0)),0) -> 0 | V44: =SUMPRODUCT(($C$25:$J$25<=$Q$33-$S44+1-$B$22)*$C$27:$J$27)*$U44 -> 0 | W44: =$U44-$V44 -> 0
A45: Refresher grant 4 | C45: =IF(AND(C$33-$S45+1-$B$22>=1,C$33-$S45+1-$B$22<=8),INDEX($C$27:$J$27,1,C$33-$S45+1-$B$22),0)*$U45*C$34 -> 0 | D45: =IF(AND(D$33-$S45+1-$B$22>=1,D$33-$S45+1-$B$22<=8),INDEX($C$27:$J$27,1,D$33-$S45+1-$B$22),0)*$U45*D$34 -> 0 | E45: =IF(AND(E$33-$S45+1-$B$22>=1,E$33-$S45+1-$B$22<=8),INDEX($C$27:$J$27,1,E$33-$S45+1-$B$22),0)*$U45*E$34 -> 0 | F45: =IF(AND(F$33-$S45+1-$B$22>=1,F$33-$S45+1-$B$22<=8),INDEX($C$27:$J$27,1,F$33-$S45+1-$B$22),0)*$U45*F$34 -> 0 | G45: =IF(AND(G$33-$S45+1-$B$22>=1,G$33-$S45+1-$B$22<=8),INDEX($C$27:$J$27,1,G$33-$S45+1-$B$22),0)*$U45*G$34 -> 0 | H45: =IF(AND(H$33-$S45+1-$B$22>=1,H$33-$S45+1-$B$22<=8),INDEX($C$27:$J$27,1,H$33-$S45+1-$B$22),0)*$U45*H$34 -> 0 | I45: =IF(AND(I$33-$S45+1-$B$22>=1,I$33-$S45+1-$B$22<=8),INDEX($C$27:$J$27,1,I$33-$S45+1-$B$22),0)*$U45*I$34 -> 0 | J45: =IF(AND(J$33-$S45+1-$B$22>=1,J$33-$S45+1-$B$22<=8),INDEX($C$27:$J$27,1,J$33-$S45+1-$B$22),0)*$U45*J$34 -> 0 | ... Q45: =IF(AND(Q$33-$S45+1-$B$22>=1,Q$33-$S45+1-$B$22<=8),INDEX($C$27:$J$27,1,Q$33-$S45+1-$B$22),0)*$U45*Q$34 -> 0 | S45: =$B$20+3 -> 2030 | T45: =IF($S45>$B$20+Scenarios!$C$8-1,0,$B$19*(1+$B$21*Scenarios!$C$7)^3) -> 0 | U45: =IFERROR($T45/INDEX($C$34:$Q$34,1,MATCH($S45,$C$33:$Q$33,0)),0) -> 0 | V45: =SUMPRODUCT(($C$25:$J$25<=$Q$33-$S45+1-$B$22)*$C$27:$J$27)*$U45 -> 0 | W45: =$U45-$V45 -> 0
A46: Refresher grant 5 | C46: =IF(AND(C$33-$S46+1-$B$22>=1,C$33-$S46+1-$B$22<=8),INDEX($C$27:$J$27,1,C$33-$S46+1-$B$22),0)*$U46*C$34 -> 0 | D46: =IF(AND(D$33-$S46+1-$B$22>=1,D$33-$S46+1-$B$22<=8),INDEX($C$27:$J$27,1,D$33-$S46+1-$B$22),0)*$U46*D$34 -> 0 | E46: =IF(AND(E$33-$S46+1-$B$22>=1,E$33-$S46+1-$B$22<=8),INDEX($C$27:$J$27,1,E$33-$S46+1-$B$22),0)*$U46*E$34 -> 0 | F46: =IF(AND(F$33-$S46+1-$B$22>=1,F$33-$S46+1-$B$22<=8),INDEX($C$27:$J$27,1,F$33-$S46+1-$B$22),0)*$U46*F$34 -> 0 | G46: =IF(AND(G$33-$S46+1-$B$22>=1,G$33-$S46+1-$B$22<=8),INDEX($C$27:$J$27,1,G$33-$S46+1-$B$22),0)*$U46*G$34 -> 0 | H46: =IF(AND(H$33-$S46+1-$B$22>=1,H$33-$S46+1-$B$22<=8),INDEX($C$27:$J$27,1,H$33-$S46+1-$B$22),0)*$U46*H$34 -> 0 | I46: =IF(AND(I$33-$S46+1-$B$22>=1,I$33-$S46+1-$B$22<=8),INDEX($C$27:$J$27,1,I$33-$S46+1-$B$22),0)*$U46*I$34 -> 0 | J46: =IF(AND(J$33-$S46+1-$B$22>=1,J$33-$S46+1-$B$22<=8),INDEX($C$27:$J$27,1,J$33-$S46+1-$B$22),0)*$U46*J$34 -> 0 | ... Q46: =IF(AND(Q$33-$S46+1-$B$22>=1,Q$33-$S46+1-$B$22<=8),INDEX($C$27:$J$27,1,Q$33-$S46+1-$B$22),0)*$U46*Q$34 -> 0 | S46: =$B$20+4 -> 2031 | T46: =IF($S46>$B$20+Scenarios!$C$8-1,0,$B$19*(1+$B$21*Scenarios!$C$7)^4) -> 0 | U46: =IFERROR($T46/INDEX($C$34:$Q$34,1,MATCH($S46,$C$33:$Q$33,0)),0) -> 0 | V46: =SUMPRODUCT(($C$25:$J$25<=$Q$33-$S46+1-$B$22)*$C$27:$J$27)*$U46 -> 0 | W46: =$U46-$V46 -> 0
A47: Refresher grant 6 | C47: =IF(AND(C$33-$S47+1-$B$22>=1,C$33-$S47+1-$B$22<=8),INDEX($C$27:$J$27,1,C$33-$S47+1-$B$22),0)*$U47*C$34 -> 0 | D47: =IF(AND(D$33-$S47+1-$B$22>=1,D$33-$S47+1-$B$22<=8),INDEX($C$27:$J$27,1,D$33-$S47+1-$B$22),0)*$U47*D$34 -> 0 | E47: =IF(AND(E$33-$S47+1-$B$22>=1,E$33-$S47+1-$B$22<=8),INDEX($C$27:$J$27,1,E$33-$S47+1-$B$22),0)*$U47*E$34 -> 0 | F47: =IF(AND(F$33-$S47+1-$B$22>=1,F$33-$S47+1-$B$22<=8),INDEX($C$27:$J$27,1,F$33-$S47+1-$B$22),0)*$U47*F$34 -> 0 | G47: =IF(AND(G$33-$S47+1-$B$22>=1,G$33-$S47+1-$B$22<=8),INDEX($C$27:$J$27,1,G$33-$S47+1-$B$22),0)*$U47*G$34 -> 0 | H47: =IF(AND(H$33-$S47+1-$B$22>=1,H$33-$S47+1-$B$22<=8),INDEX($C$27:$J$27,1,H$33-$S47+1-$B$22),0)*$U47*H$34 -> 0 | I47: =IF(AND(I$33-$S47+1-$B$22>=1,I$33-$S47+1-$B$22<=8),INDEX($C$27:$J$27,1,I$33-$S47+1-$B$22),0)*$U47*I$34 -> 0 | J47: =IF(AND(J$33-$S47+1-$B$22>=1,J$33-$S47+1-$B$22<=8),INDEX($C$27:$J$27,1,J$33-$S47+1-$B$22),0)*$U47*J$34 -> 0 | ... Q47: =IF(AND(Q$33-$S47+1-$B$22>=1,Q$33-$S47+1-$B$22<=8),INDEX($C$27:$J$27,1,Q$33-$S47+1-$B$22),0)*$U47*Q$34 -> 0 | S47: =$B$20+5 -> 2032 | T47: =IF($S47>$B$20+Scenarios!$C$8-1,0,$B$19*(1+$B$21*Scenarios!$C$7)^5) -> 0 | U47: =IFERROR($T47/INDEX($C$34:$Q$34,1,MATCH($S47,$C$33:$Q$33,0)),0) -> 0 | V47: =SUMPRODUCT(($C$25:$J$25<=$Q$33-$S47+1-$B$22)*$C$27:$J$27)*$U47 -> 0 | W47: =$U47-$V47 -> 0
A48: Refresher grant 7 | C48: =IF(AND(C$33-$S48+1-$B$22>=1,C$33-$S48+1-$B$22<=8),INDEX($C$27:$J$27,1,C$33-$S48+1-$B$22),0)*$U48*C$34 -> 0 | D48: =IF(AND(D$33-$S48+1-$B$22>=1,D$33-$S48+1-$B$22<=8),INDEX($C$27:$J$27,1,D$33-$S48+1-$B$22),0)*$U48*D$34 -> 0 | E48: =IF(AND(E$33-$S48+1-$B$22>=1,E$33-$S48+1-$B$22<=8),INDEX($C$27:$J$27,1,E$33-$S48+1-$B$22),0)*$U48*E$34 -> 0 | F48: =IF(AND(F$33-$S48+1-$B$22>=1,F$33-$S48+1-$B$22<=8),INDEX($C$27:$J$27,1,F$33-$S48+1-$B$22),0)*$U48*F$34 -> 0 | G48: =IF(AND(G$33-$S48+1-$B$22>=1,G$33-$S48+1-$B$22<=8),INDEX($C$27:$J$27,1,G$33-$S48+1-$B$22),0)*$U48*G$34 -> 0 | H48: =IF(AND(H$33-$S48+1-$B$22>=1,H$33-$S48+1-$B$22<=8),INDEX($C$27:$J$27,1,H$33-$S48+1-$B$22),0)*$U48*H$34 -> 0 | I48: =IF(AND(I$33-$S48+1-$B$22>=1,I$33-$S48+1-$B$22<=8),INDEX($C$27:$J$27,1,I$33-$S48+1-$B$22),0)*$U48*I$34 -> 0 | J48: =IF(AND(J$33-$S48+1-$B$22>=1,J$33-$S48+1-$B$22<=8),INDEX($C$27:$J$27,1,J$33-$S48+1-$B$22),0)*$U48*J$34 -> 0 | ... Q48: =IF(AND(Q$33-$S48+1-$B$22>=1,Q$33-$S48+1-$B$22<=8),INDEX($C$27:$J$27,1,Q$33-$S48+1-$B$22),0)*$U48*Q$34 -> 0 | S48: =$B$20+6 -> 2033 | T48: =IF($S48>$B$20+Scenarios!$C$8-1,0,$B$19*(1+$B$21*Scenarios!$C$7)^6) -> 0 | U48: =IFERROR($T48/INDEX($C$34:$Q$34,1,MATCH($S48,$C$33:$Q$33,0)),0) -> 0 | V48: =SUMPRODUCT(($C$25:$J$25<=$Q$33-$S48+1-$B$22)*$C$27:$J$27)*$U48 -> 0 | W48: =$U48-$V48 -> 0
A49: Refresher grant 8 | C49: =IF(AND(C$33-$S49+1-$B$22>=1,C$33-$S49+1-$B$22<=8),INDEX($C$27:$J$27,1,C$33-$S49+1-$B$22),0)*$U49*C$34 -> 0 | D49: =IF(AND(D$33-$S49+1-$B$22>=1,D$33-$S49+1-$B$22<=8),INDEX($C$27:$J$27,1,D$33-$S49+1-$B$22),0)*$U49*D$34 -> 0 | E49: =IF(AND(E$33-$S49+1-$B$22>=1,E$33-$S49+1-$B$22<=8),INDEX($C$27:$J$27,1,E$33-$S49+1-$B$22),0)*$U49*E$34 -> 0 | F49: =IF(AND(F$33-$S49+1-$B$22>=1,F$33-$S49+1-$B$22<=8),INDEX($C$27:$J$27,1,F$33-$S49+1-$B$22),0)*$U49*F$34 -> 0 | G49: =IF(AND(G$33-$S49+1-$B$22>=1,G$33-$S49+1-$B$22<=8),INDEX($C$27:$J$27,1,G$33-$S49+1-$B$22),0)*$U49*G$34 -> 0 | H49: =IF(AND(H$33-$S49+1-$B$22>=1,H$33-$S49+1-$B$22<=8),INDEX($C$27:$J$27,1,H$33-$S49+1-$B$22),0)*$U49*H$34 -> 0 | I49: =IF(AND(I$33-$S49+1-$B$22>=1,I$33-$S49+1-$B$22<=8),INDEX($C$27:$J$27,1,I$33-$S49+1-$B$22),0)*$U49*I$34 -> 0 | J49: =IF(AND(J$33-$S49+1-$B$22>=1,J$33-$S49+1-$B$22<=8),INDEX($C$27:$J$27,1,J$33-$S49+1-$B$22),0)*$U49*J$34 -> 0 | ... Q49: =IF(AND(Q$33-$S49+1-$B$22>=1,Q$33-$S49+1-$B$22<=8),INDEX($C$27:$J$27,1,Q$33-$S49+1-$B$22),0)*$U49*Q$34 -> 0 | S49: =$B$20+7 -> 2034 | T49: =IF($S49>$B$20+Scenarios!$C$8-1,0,$B$19*(1+$B$21*Scenarios!$C$7)^7) -> 0 | U49: =IFERROR($T49/INDEX($C$34:$Q$34,1,MATCH($S49,$C$33:$Q$33,0)),0) -> 0 | V49: =SUMPRODUCT(($C$25:$J$25<=$Q$33-$S49+1-$B$22)*$C$27:$J$27)*$U49 -> 0 | W49: =$U49-$V49 -> 0
A50: Refresher grant 9 | C50: =IF(AND(C$33-$S50+1-$B$22>=1,C$33-$S50+1-$B$22<=8),INDEX($C$27:$J$27,1,C$33-$S50+1-$B$22),0)*$U50*C$34 -> 0 | D50: =IF(AND(D$33-$S50+1-$B$22>=1,D$33-$S50+1-$B$22<=8),INDEX($C$27:$J$27,1,D$33-$S50+1-$B$22),0)*$U50*D$34 -> 0 | E50: =IF(AND(E$33-$S50+1-$B$22>=1,E$33-$S50+1-$B$22<=8),INDEX($C$27:$J$27,1,E$33-$S50+1-$B$22),0)*$U50*E$34 -> 0 | F50: =IF(AND(F$33-$S50+1-$B$22>=1,F$33-$S50+1-$B$22<=8),INDEX($C$27:$J$27,1,F$33-$S50+1-$B$22),0)*$U50*F$34 -> 0 | G50: =IF(AND(G$33-$S50+1-$B$22>=1,G$33-$S50+1-$B$22<=8),INDEX($C$27:$J$27,1,G$33-$S50+1-$B$22),0)*$U50*G$34 -> 0 | H50: =IF(AND(H$33-$S50+1-$B$22>=1,H$33-$S50+1-$B$22<=8),INDEX($C$27:$J$27,1,H$33-$S50+1-$B$22),0)*$U50*H$34 -> 0 | I50: =IF(AND(I$33-$S50+1-$B$22>=1,I$33-$S50+1-$B$22<=8),INDEX($C$27:$J$27,1,I$33-$S50+1-$B$22),0)*$U50*I$34 -> 0 | J50: =IF(AND(J$33-$S50+1-$B$22>=1,J$33-$S50+1-$B$22<=8),INDEX($C$27:$J$27,1,J$33-$S50+1-$B$22),0)*$U50*J$34 -> 0 | ... Q50: =IF(AND(Q$33-$S50+1-$B$22>=1,Q$33-$S50+1-$B$22<=8),INDEX($C$27:$J$27,1,Q$33-$S50+1-$B$22),0)*$U50*Q$34 -> 0 | S50: =$B$20+8 -> 2035 | T50: =IF($S50>$B$20+Scenarios!$C$8-1,0,$B$19*(1+$B$21*Scenarios!$C$7)^8) -> 0 | U50: =IFERROR($T50/INDEX($C$34:$Q$34,1,MATCH($S50,$C$33:$Q$33,0)),0) -> 0 | V50: =SUMPRODUCT(($C$25:$J$25<=$Q$33-$S50+1-$B$22)*$C$27:$J$27)*$U50 -> 0 | W50: =$U50-$V50 -> 0
A51: Refresher grant 10 | C51: =IF(AND(C$33-$S51+1-$B$22>=1,C$33-$S51+1-$B$22<=8),INDEX($C$27:$J$27,1,C$33-$S51+1-$B$22),0)*$U51*C$34 -> 0 | D51: =IF(AND(D$33-$S51+1-$B$22>=1,D$33-$S51+1-$B$22<=8),INDEX($C$27:$J$27,1,D$33-$S51+1-$B$22),0)*$U51*D$34 -> 0 | E51: =IF(AND(E$33-$S51+1-$B$22>=1,E$33-$S51+1-$B$22<=8),INDEX($C$27:$J$27,1,E$33-$S51+1-$B$22),0)*$U51*E$34 -> 0 | F51: =IF(AND(F$33-$S51+1-$B$22>=1,F$33-$S51+1-$B$22<=8),INDEX($C$27:$J$27,1,F$33-$S51+1-$B$22),0)*$U51*F$34 -> 0 | G51: =IF(AND(G$33-$S51+1-$B$22>=1,G$33-$S51+1-$B$22<=8),INDEX($C$27:$J$27,1,G$33-$S51+1-$B$22),0)*$U51*G$34 -> 0 | H51: =IF(AND(H$33-$S51+1-$B$22>=1,H$33-$S51+1-$B$22<=8),INDEX($C$27:$J$27,1,H$33-$S51+1-$B$22),0)*$U51*H$34 -> 0 | I51: =IF(AND(I$33-$S51+1-$B$22>=1,I$33-$S51+1-$B$22<=8),INDEX($C$27:$J$27,1,I$33-$S51+1-$B$22),0)*$U51*I$34 -> 0 | J51: =IF(AND(J$33-$S51+1-$B$22>=1,J$33-$S51+1-$B$22<=8),INDEX($C$27:$J$27,1,J$33-$S51+1-$B$22),0)*$U51*J$34 -> 0 | ... Q51: =IF(AND(Q$33-$S51+1-$B$22>=1,Q$33-$S51+1-$B$22<=8),INDEX($C$27:$J$27,1,Q$33-$S51+1-$B$22),0)*$U51*Q$34 -> 0 | S51: =$B$20+9 -> 2036 | T51: =IF($S51>$B$20+Scenarios!$C$8-1,0,$B$19*(1+$B$21*Scenarios!$C$7)^9) -> 0 | U51: =IFERROR($T51/INDEX($C$34:$Q$34,1,MATCH($S51,$C$33:$Q$33,0)),0) -> 0 | V51: =SUMPRODUCT(($C$25:$J$25<=$Q$33-$S51+1-$B$22)*$C$27:$J$27)*$U51 -> 0 | W51: =$U51-$V51 -> 0
A52: Refresher grant 11 | C52: =IF(AND(C$33-$S52+1-$B$22>=1,C$33-$S52+1-$B$22<=8),INDEX($C$27:$J$27,1,C$33-$S52+1-$B$22),0)*$U52*C$34 -> 0 | D52: =IF(AND(D$33-$S52+1-$B$22>=1,D$33-$S52+1-$B$22<=8),INDEX($C$27:$J$27,1,D$33-$S52+1-$B$22),0)*$U52*D$34 -> 0 | E52: =IF(AND(E$33-$S52+1-$B$22>=1,E$33-$S52+1-$B$22<=8),INDEX($C$27:$J$27,1,E$33-$S52+1-$B$22),0)*$U52*E$34 -> 0 | F52: =IF(AND(F$33-$S52+1-$B$22>=1,F$33-$S52+1-$B$22<=8),INDEX($C$27:$J$27,1,F$33-$S52+1-$B$22),0)*$U52*F$34 -> 0 | G52: =IF(AND(G$33-$S52+1-$B$22>=1,G$33-$S52+1-$B$22<=8),INDEX($C$27:$J$27,1,G$33-$S52+1-$B$22),0)*$U52*G$34 -> 0 | H52: =IF(AND(H$33-$S52+1-$B$22>=1,H$33-$S52+1-$B$22<=8),INDEX($C$27:$J$27,1,H$33-$S52+1-$B$22),0)*$U52*H$34 -> 0 | I52: =IF(AND(I$33-$S52+1-$B$22>=1,I$33-$S52+1-$B$22<=8),INDEX($C$27:$J$27,1,I$33-$S52+1-$B$22),0)*$U52*I$34 -> 0 | J52: =IF(AND(J$33-$S52+1-$B$22>=1,J$33-$S52+1-$B$22<=8),INDEX($C$27:$J$27,1,J$33-$S52+1-$B$22),0)*$U52*J$34 -> 0 | ... Q52: =IF(AND(Q$33-$S52+1-$B$22>=1,Q$33-$S52+1-$B$22<=8),INDEX($C$27:$J$27,1,Q$33-$S52+1-$B$22),0)*$U52*Q$34 -> 0 | S52: =$B$20+10 -> 2037 | T52: =IF($S52>$B$20+Scenarios!$C$8-1,0,$B$19*(1+$B$21*Scenarios!$C$7)^10) -> 0 | U52: =IFERROR($T52/INDEX($C$34:$Q$34,1,MATCH($S52,$C$33:$Q$33,0)),0) -> 0 | V52: =SUMPRODUCT(($C$25:$J$25<=$Q$33-$S52+1-$B$22)*$C$27:$J$27)*$U52 -> 0 | W52: =$U52-$V52 -> 0
A53: Refresher grant 12 | C53: =IF(AND(C$33-$S53+1-$B$22>=1,C$33-$S53+1-$B$22<=8),INDEX($C$27:$J$27,1,C$33-$S53+1-$B$22),0)*$U53*C$34 -> 0 | D53: =IF(AND(D$33-$S53+1-$B$22>=1,D$33-$S53+1-$B$22<=8),INDEX($C$27:$J$27,1,D$33-$S53+1-$B$22),0)*$U53*D$34 -> 0 | E53: =IF(AND(E$33-$S53+1-$B$22>=1,E$33-$S53+1-$B$22<=8),INDEX($C$27:$J$27,1,E$33-$S53+1-$B$22),0)*$U53*E$34 -> 0 | F53: =IF(AND(F$33-$S53+1-$B$22>=1,F$33-$S53+1-$B$22<=8),INDEX($C$27:$J$27,1,F$33-$S53+1-$B$22),0)*$U53*F$34 -> 0 | G53: =IF(AND(G$33-$S53+1-$B$22>=1,G$33-$S53+1-$B$22<=8),INDEX($C$27:$J$27,1,G$33-$S53+1-$B$22),0)*$U53*G$34 -> 0 | H53: =IF(AND(H$33-$S53+1-$B$22>=1,H$33-$S53+1-$B$22<=8),INDEX($C$27:$J$27,1,H$33-$S53+1-$B$22),0)*$U53*H$34 -> 0 | I53: =IF(AND(I$33-$S53+1-$B$22>=1,I$33-$S53+1-$B$22<=8),INDEX($C$27:$J$27,1,I$33-$S53+1-$B$22),0)*$U53*I$34 -> 0 | J53: =IF(AND(J$33-$S53+1-$B$22>=1,J$33-$S53+1-$B$22<=8),INDEX($C$27:$J$27,1,J$33-$S53+1-$B$22),0)*$U53*J$34 -> 0 | ... Q53: =IF(AND(Q$33-$S53+1-$B$22>=1,Q$33-$S53+1-$B$22<=8),INDEX($C$27:$J$27,1,Q$33-$S53+1-$B$22),0)*$U53*Q$34 -> 0 | S53: =$B$20+11 -> 2038 | T53: =IF($S53>$B$20+Scenarios!$C$8-1,0,$B$19*(1+$B$21*Scenarios!$C$7)^11) -> 0 | U53: =IFERROR($T53/INDEX($C$34:$Q$34,1,MATCH($S53,$C$33:$Q$33,0)),0) -> 0 | V53: =SUMPRODUCT(($C$25:$J$25<=$Q$33-$S53+1-$B$22)*$C$27:$J$27)*$U53 -> 0 | W53: =$U53-$V53 -> 0
A55: Initial grant vest ($) | C55: =C41 -> 0 | D55: =D41 -> 0 | E55: =E41 -> 0 | F55: =F41 -> 0 | G55: =G41 -> 0 | H55: =H41 -> 0 | I55: =I41 -> 0 | J55: =J41 -> 0 | ... Q55: =Q41 -> 0
A56: Refresher vest ($) | C56: =SUM(C42:C53) -> 0 | D56: =SUM(D42:D53) -> 0 | E56: =SUM(E42:E53) -> 0 | F56: =SUM(F42:F53) -> 0 | G56: =SUM(G42:G53) -> 0 | H56: =SUM(H42:H53) -> 0 | I56: =SUM(I42:I53) -> 0 | J56: =SUM(J42:J53) -> 0 | ... Q56: =SUM(Q42:Q53) -> 0
A57: Total equity vest ($) | C57: =C55+C56 -> 0 | D57: =D55+D56 -> 0 | E57: =E55+E56 -> 0 | F57: =F55+F56 -> 0 | G57: =G55+G56 -> 0 | H57: =H55+H56 -> 0 | I57: =I55+I56 -> 0 | J57: =J55+J56 -> 0 | ... Q57: =Q55+Q56 -> 0
A58: Concurrent grants vesting (count) | C58: =SUMPRODUCT((C41:C53>0)*1) -> 0 | D58: =SUMPRODUCT((D41:D53>0)*1) -> 0 | E58: =SUMPRODUCT((E41:E53>0)*1) -> 0 | F58: =SUMPRODUCT((F41:F53>0)*1) -> 0 | G58: =SUMPRODUCT((G41:G53>0)*1) -> 0 | H58: =SUMPRODUCT((H41:H53>0)*1) -> 0 | I58: =SUMPRODUCT((I41:I53>0)*1) -> 0 | J58: =SUMPRODUCT((J41:J53>0)*1) -> 0 | ... Q58: =SUMPRODUCT((Q41:Q53>0)*1) -> 0
A60: TOTAL GROSS COMPENSATION | C60: =C35+C37+C38+C57 -> 320375 | D60: =D35+D37+D38+D57 -> 325180.62 | E60: =E35+E37+E38+E57 -> 330058.33 | F60: =F35+F37+F38+F57 -> 335009.21 | G60: =G35+G37+G38+G57 -> 340034.35 | H60: =H35+H37+H38+H57 -> 345134.86 | I60: =I35+I37+I38+I57 -> 350311.89 | J60: =J35+J37+J38+J57 -> 355566.56 | ... Q60: =Q35+Q37+Q38+Q57 -> 394623.74
A61: Cumulative gross | C61: =C60 -> 320375 | D61: =C61+D60 -> 645555.62 | E61: =D61+E60 -> 975613.96 | F61: =E61+F60 -> 1310623.2 | G61: =F61+G60 -> 1650657.5 | H61: =G61+H60 -> 1995792.4 | I61: =H61+I60 -> 2346104.3 | J61: =I61+J60 -> 2701670.8 | K61: =J61+K60 -> 3062570.9 | ... Q61: =P61+Q60 -> 5344539.9
A63: Unvested shares at end of horizon | B63: =SUM(W41:W53) -> 0
A64: Unvested equity value at horizon price | B64: =B63*$Q$34 -> 0
A76: SCENARIO: MEDIUM | B76: =Scenarios!D$3 -> Medium
A77: Year index | C77: 1 | D77: 2 | E77: 3 | F77: 4 | G77: 5 | H77: 6 | I77: 7 | J77: 8 | K77: 9 | L77: 10 | M77: 11 | N77: 12 | O77: 13 | P77: 14 | Q77: 15
A78: Calendar year | C78: =$B$6 -> 2026 | D78: =C78+1 -> 2027 | E78: =D78+1 -> 2028 | F78: =E78+1 -> 2029 | G78: =F78+1 -> 2030 | H78: =G78+1 -> 2031 | I78: =H78+1 -> 2032 | J78: =I78+1 -> 2033 | K78: =J78+1 -> 2034 | ... Q78: =P78+1 -> 2040
A79: Share price ($) | C79: =$B$17 -> 1 | D79: =C79*(1+Scenarios!$D$4) -> 1.07 | E79: =D79*(1+Scenarios!$D$4) -> 1.1449 | F79: =E79*(1+Scenarios!$D$4) -> 1.225043 | G79: =F79*(1+Scenarios!$D$4) -> 1.310796 | H79: =G79*(1+Scenarios!$D$4) -> 1.4025517 | I79: =H79*(1+Scenarios!$D$4) -> 1.5007304 | J79: =I79*(1+Scenarios!$D$4) -> 1.6057815 | K79: =J79*(1+Scenarios!$D$4) -> 1.7181862 | ... Q79: =P79*(1+Scenarios!$D$4) -> 2.5785342
A80: Base salary | C80: =$B$7 -> 275000 | D80: =C80*(1+$B$8*Scenarios!$D$5) -> 283250 | E80: =D80*(1+$B$8*Scenarios!$D$5) -> 291747.5 | F80: =E80*(1+$B$8*Scenarios!$D$5) -> 300499.92 | G80: =F80*(1+$B$8*Scenarios!$D$5) -> 309514.92 | H80: =G80*(1+$B$8*Scenarios!$D$5) -> 318800.37 | I80: =H80*(1+$B$8*Scenarios!$D$5) -> 328364.38 | J80: =I80*(1+$B$8*Scenarios!$D$5) -> 338215.31 | K80: =J80*(1+$B$8*Scenarios!$D$5) -> 348361.77 | ... Q80: =P80*(1+$B$8*Scenarios!$D$5) -> 415962.17
A81: Bonus basis salary | C81: =IF($B$10="Prior",0,C80) -> 275000 | D81: =IF($B$10="Prior",C80,D80) -> 283250 | E81: =IF($B$10="Prior",D80,E80) -> 291747.5 | F81: =IF($B$10="Prior",E80,F80) -> 300499.92 | G81: =IF($B$10="Prior",F80,G80) -> 309514.92 | H81: =IF($B$10="Prior",G80,H80) -> 318800.37 | I81: =IF($B$10="Prior",H80,I80) -> 328364.38 | J81: =IF($B$10="Prior",I80,J80) -> 338215.31 | K81: =IF($B$10="Prior",J80,K80) -> 348361.77 | ... Q81: =IF($B$10="Prior",P80,Q80) -> 415962.17
A82: Annual bonus | C82: =IF($B$11="No",0,C81*$B$9*Scenarios!$D$6) -> 60500 | D82: =D81*$B$9*Scenarios!$D$6 -> 62315 | E82: =E81*$B$9*Scenarios!$D$6 -> 64184.45 | F82: =F81*$B$9*Scenarios!$D$6 -> 66109.984 | G82: =G81*$B$9*Scenarios!$D$6 -> 68093.283 | H82: =H81*$B$9*Scenarios!$D$6 -> 70136.081 | I82: =I81*$B$9*Scenarios!$D$6 -> 72240.164 | J82: =J81*$B$9*Scenarios!$D$6 -> 74407.369 | K82: =K81*$B$9*Scenarios!$D$6 -> 76639.59 | ... Q82: =Q81*$B$9*Scenarios!$D$6 -> 91511.678
A83: Sign-on paid | C83: =$B$12*$B$13 -> 0 | D83: =$B$12*$B$14 -> 0 | E83: =$B$12*$B$15 -> 0 | F83: 0 | G83: 0 | H83: 0 | I83: 0 | J83: 0 | K83: 0 | L83: 0 | M83: 0 | N83: 0 | O83: 0 | P83: 0 | Q83: 0
A85: GRANT LEDGER — dollar value vesting each year, one row per grant | S85: Grant year | T85: Grant value ($) | U85: Shares granted | V85: Shares vested in horizon | W85: Unvested shares
A86: Initial grant | C86: =IF(AND(C$78-$S86+1-$B$22>=1,C$78-$S86+1-$B$22<=8),INDEX($C$26:$J$26,1,C$78-$S86+1-$B$22),0)*$U86*C$79 -> 0 | D86: =IF(AND(D$78-$S86+1-$B$22>=1,D$78-$S86+1-$B$22<=8),INDEX($C$26:$J$26,1,D$78-$S86+1-$B$22),0)*$U86*D$79 -> 0 | E86: =IF(AND(E$78-$S86+1-$B$22>=1,E$78-$S86+1-$B$22<=8),INDEX($C$26:$J$26,1,E$78-$S86+1-$B$22),0)*$U86*E$79 -> 0 | F86: =IF(AND(F$78-$S86+1-$B$22>=1,F$78-$S86+1-$B$22<=8),INDEX($C$26:$J$26,1,F$78-$S86+1-$B$22),0)*$U86*F$79 -> 0 | G86: =IF(AND(G$78-$S86+1-$B$22>=1,G$78-$S86+1-$B$22<=8),INDEX($C$26:$J$26,1,G$78-$S86+1-$B$22),0)*$U86*G$79 -> 0 | H86: =IF(AND(H$78-$S86+1-$B$22>=1,H$78-$S86+1-$B$22<=8),INDEX($C$26:$J$26,1,H$78-$S86+1-$B$22),0)*$U86*H$79 -> 0 | I86: =IF(AND(I$78-$S86+1-$B$22>=1,I$78-$S86+1-$B$22<=8),INDEX($C$26:$J$26,1,I$78-$S86+1-$B$22),0)*$U86*I$79 -> 0 | J86: =IF(AND(J$78-$S86+1-$B$22>=1,J$78-$S86+1-$B$22<=8),INDEX($C$26:$J$26,1,J$78-$S86+1-$B$22),0)*$U86*J$79 -> 0 | ... Q86: =IF(AND(Q$78-$S86+1-$B$22>=1,Q$78-$S86+1-$B$22<=8),INDEX($C$26:$J$26,1,Q$78-$S86+1-$B$22),0)*$U86*Q$79 -> 0 | S86: =$B$6 -> 2026 | T86: =$B$18 -> 0 | U86: =IFERROR(T86/$B$17,0) -> 0 | V86: =SUMPRODUCT(($C$25:$J$25<=$Q$78-$S86+1-$B$22)*$C$26:$J$26)*$U86 -> 0 | W86: =$U86-$V86 -> 0
A87: Refresher grant 1 | C87: =IF(AND(C$78-$S87+1-$B$22>=1,C$78-$S87+1-$B$22<=8),INDEX($C$27:$J$27,1,C$78-$S87+1-$B$22),0)*$U87*C$79 -> 0 | D87: =IF(AND(D$78-$S87+1-$B$22>=1,D$78-$S87+1-$B$22<=8),INDEX($C$27:$J$27,1,D$78-$S87+1-$B$22),0)*$U87*D$79 -> 0 | E87: =IF(AND(E$78-$S87+1-$B$22>=1,E$78-$S87+1-$B$22<=8),INDEX($C$27:$J$27,1,E$78-$S87+1-$B$22),0)*$U87*E$79 -> 0 | F87: =IF(AND(F$78-$S87+1-$B$22>=1,F$78-$S87+1-$B$22<=8),INDEX($C$27:$J$27,1,F$78-$S87+1-$B$22),0)*$U87*F$79 -> 0 | G87: =IF(AND(G$78-$S87+1-$B$22>=1,G$78-$S87+1-$B$22<=8),INDEX($C$27:$J$27,1,G$78-$S87+1-$B$22),0)*$U87*G$79 -> 0 | H87: =IF(AND(H$78-$S87+1-$B$22>=1,H$78-$S87+1-$B$22<=8),INDEX($C$27:$J$27,1,H$78-$S87+1-$B$22),0)*$U87*H$79 -> 0 | I87: =IF(AND(I$78-$S87+1-$B$22>=1,I$78-$S87+1-$B$22<=8),INDEX($C$27:$J$27,1,I$78-$S87+1-$B$22),0)*$U87*I$79 -> 0 | J87: =IF(AND(J$78-$S87+1-$B$22>=1,J$78-$S87+1-$B$22<=8),INDEX($C$27:$J$27,1,J$78-$S87+1-$B$22),0)*$U87*J$79 -> 0 | ... Q87: =IF(AND(Q$78-$S87+1-$B$22>=1,Q$78-$S87+1-$B$22<=8),INDEX($C$27:$J$27,1,Q$78-$S87+1-$B$22),0)*$U87*Q$79 -> 0 | S87: =$B$20+0 -> 2027 | T87: =IF($S87>$B$20+Scenarios!$D$8-1,0,$B$19*(1+$B$21*Scenarios!$D$7)^0) -> 0 | U87: =IFERROR($T87/INDEX($C$79:$Q$79,1,MATCH($S87,$C$78:$Q$78,0)),0) -> 0 | V87: =SUMPRODUCT(($C$25:$J$25<=$Q$78-$S87+1-$B$22)*$C$27:$J$27)*$U87 -> 0 | W87: =$U87-$V87 -> 0
A88: Refresher grant 2 | C88: =IF(AND(C$78-$S88+1-$B$22>=1,C$78-$S88+1-$B$22<=8),INDEX($C$27:$J$27,1,C$78-$S88+1-$B$22),0)*$U88*C$79 -> 0 | D88: =IF(AND(D$78-$S88+1-$B$22>=1,D$78-$S88+1-$B$22<=8),INDEX($C$27:$J$27,1,D$78-$S88+1-$B$22),0)*$U88*D$79 -> 0 | E88: =IF(AND(E$78-$S88+1-$B$22>=1,E$78-$S88+1-$B$22<=8),INDEX($C$27:$J$27,1,E$78-$S88+1-$B$22),0)*$U88*E$79 -> 0 | F88: =IF(AND(F$78-$S88+1-$B$22>=1,F$78-$S88+1-$B$22<=8),INDEX($C$27:$J$27,1,F$78-$S88+1-$B$22),0)*$U88*F$79 -> 0 | G88: =IF(AND(G$78-$S88+1-$B$22>=1,G$78-$S88+1-$B$22<=8),INDEX($C$27:$J$27,1,G$78-$S88+1-$B$22),0)*$U88*G$79 -> 0 | H88: =IF(AND(H$78-$S88+1-$B$22>=1,H$78-$S88+1-$B$22<=8),INDEX($C$27:$J$27,1,H$78-$S88+1-$B$22),0)*$U88*H$79 -> 0 | I88: =IF(AND(I$78-$S88+1-$B$22>=1,I$78-$S88+1-$B$22<=8),INDEX($C$27:$J$27,1,I$78-$S88+1-$B$22),0)*$U88*I$79 -> 0 | J88: =IF(AND(J$78-$S88+1-$B$22>=1,J$78-$S88+1-$B$22<=8),INDEX($C$27:$J$27,1,J$78-$S88+1-$B$22),0)*$U88*J$79 -> 0 | ... Q88: =IF(AND(Q$78-$S88+1-$B$22>=1,Q$78-$S88+1-$B$22<=8),INDEX($C$27:$J$27,1,Q$78-$S88+1-$B$22),0)*$U88*Q$79 -> 0 | S88: =$B$20+1 -> 2028 | T88: =IF($S88>$B$20+Scenarios!$D$8-1,0,$B$19*(1+$B$21*Scenarios!$D$7)^1) -> 0 | U88: =IFERROR($T88/INDEX($C$79:$Q$79,1,MATCH($S88,$C$78:$Q$78,0)),0) -> 0 | V88: =SUMPRODUCT(($C$25:$J$25<=$Q$78-$S88+1-$B$22)*$C$27:$J$27)*$U88 -> 0 | W88: =$U88-$V88 -> 0
A89: Refresher grant 3 | C89: =IF(AND(C$78-$S89+1-$B$22>=1,C$78-$S89+1-$B$22<=8),INDEX($C$27:$J$27,1,C$78-$S89+1-$B$22),0)*$U89*C$79 -> 0 | D89: =IF(AND(D$78-$S89+1-$B$22>=1,D$78-$S89+1-$B$22<=8),INDEX($C$27:$J$27,1,D$78-$S89+1-$B$22),0)*$U89*D$79 -> 0 | E89: =IF(AND(E$78-$S89+1-$B$22>=1,E$78-$S89+1-$B$22<=8),INDEX($C$27:$J$27,1,E$78-$S89+1-$B$22),0)*$U89*E$79 -> 0 | F89: =IF(AND(F$78-$S89+1-$B$22>=1,F$78-$S89+1-$B$22<=8),INDEX($C$27:$J$27,1,F$78-$S89+1-$B$22),0)*$U89*F$79 -> 0 | G89: =IF(AND(G$78-$S89+1-$B$22>=1,G$78-$S89+1-$B$22<=8),INDEX($C$27:$J$27,1,G$78-$S89+1-$B$22),0)*$U89*G$79 -> 0 | H89: =IF(AND(H$78-$S89+1-$B$22>=1,H$78-$S89+1-$B$22<=8),INDEX($C$27:$J$27,1,H$78-$S89+1-$B$22),0)*$U89*H$79 -> 0 | I89: =IF(AND(I$78-$S89+1-$B$22>=1,I$78-$S89+1-$B$22<=8),INDEX($C$27:$J$27,1,I$78-$S89+1-$B$22),0)*$U89*I$79 -> 0 | J89: =IF(AND(J$78-$S89+1-$B$22>=1,J$78-$S89+1-$B$22<=8),INDEX($C$27:$J$27,1,J$78-$S89+1-$B$22),0)*$U89*J$79 -> 0 | ... Q89: =IF(AND(Q$78-$S89+1-$B$22>=1,Q$78-$S89+1-$B$22<=8),INDEX($C$27:$J$27,1,Q$78-$S89+1-$B$22),0)*$U89*Q$79 -> 0 | S89: =$B$20+2 -> 2029 | T89: =IF($S89>$B$20+Scenarios!$D$8-1,0,$B$19*(1+$B$21*Scenarios!$D$7)^2) -> 0 | U89: =IFERROR($T89/INDEX($C$79:$Q$79,1,MATCH($S89,$C$78:$Q$78,0)),0) -> 0 | V89: =SUMPRODUCT(($C$25:$J$25<=$Q$78-$S89+1-$B$22)*$C$27:$J$27)*$U89 -> 0 | W89: =$U89-$V89 -> 0
A90: Refresher grant 4 | C90: =IF(AND(C$78-$S90+1-$B$22>=1,C$78-$S90+1-$B$22<=8),INDEX($C$27:$J$27,1,C$78-$S90+1-$B$22),0)*$U90*C$79 -> 0 | D90: =IF(AND(D$78-$S90+1-$B$22>=1,D$78-$S90+1-$B$22<=8),INDEX($C$27:$J$27,1,D$78-$S90+1-$B$22),0)*$U90*D$79 -> 0 | E90: =IF(AND(E$78-$S90+1-$B$22>=1,E$78-$S90+1-$B$22<=8),INDEX($C$27:$J$27,1,E$78-$S90+1-$B$22),0)*$U90*E$79 -> 0 | F90: =IF(AND(F$78-$S90+1-$B$22>=1,F$78-$S90+1-$B$22<=8),INDEX($C$27:$J$27,1,F$78-$S90+1-$B$22),0)*$U90*F$79 -> 0 | G90: =IF(AND(G$78-$S90+1-$B$22>=1,G$78-$S90+1-$B$22<=8),INDEX($C$27:$J$27,1,G$78-$S90+1-$B$22),0)*$U90*G$79 -> 0 | H90: =IF(AND(H$78-$S90+1-$B$22>=1,H$78-$S90+1-$B$22<=8),INDEX($C$27:$J$27,1,H$78-$S90+1-$B$22),0)*$U90*H$79 -> 0 | I90: =IF(AND(I$78-$S90+1-$B$22>=1,I$78-$S90+1-$B$22<=8),INDEX($C$27:$J$27,1,I$78-$S90+1-$B$22),0)*$U90*I$79 -> 0 | J90: =IF(AND(J$78-$S90+1-$B$22>=1,J$78-$S90+1-$B$22<=8),INDEX($C$27:$J$27,1,J$78-$S90+1-$B$22),0)*$U90*J$79 -> 0 | ... Q90: =IF(AND(Q$78-$S90+1-$B$22>=1,Q$78-$S90+1-$B$22<=8),INDEX($C$27:$J$27,1,Q$78-$S90+1-$B$22),0)*$U90*Q$79 -> 0 | S90: =$B$20+3 -> 2030 | T90: =IF($S90>$B$20+Scenarios!$D$8-1,0,$B$19*(1+$B$21*Scenarios!$D$7)^3) -> 0 | U90: =IFERROR($T90/INDEX($C$79:$Q$79,1,MATCH($S90,$C$78:$Q$78,0)),0) -> 0 | V90: =SUMPRODUCT(($C$25:$J$25<=$Q$78-$S90+1-$B$22)*$C$27:$J$27)*$U90 -> 0 | W90: =$U90-$V90 -> 0
A91: Refresher grant 5 | C91: =IF(AND(C$78-$S91+1-$B$22>=1,C$78-$S91+1-$B$22<=8),INDEX($C$27:$J$27,1,C$78-$S91+1-$B$22),0)*$U91*C$79 -> 0 | D91: =IF(AND(D$78-$S91+1-$B$22>=1,D$78-$S91+1-$B$22<=8),INDEX($C$27:$J$27,1,D$78-$S91+1-$B$22),0)*$U91*D$79 -> 0 | E91: =IF(AND(E$78-$S91+1-$B$22>=1,E$78-$S91+1-$B$22<=8),INDEX($C$27:$J$27,1,E$78-$S91+1-$B$22),0)*$U91*E$79 -> 0 | F91: =IF(AND(F$78-$S91+1-$B$22>=1,F$78-$S91+1-$B$22<=8),INDEX($C$27:$J$27,1,F$78-$S91+1-$B$22),0)*$U91*F$79 -> 0 | G91: =IF(AND(G$78-$S91+1-$B$22>=1,G$78-$S91+1-$B$22<=8),INDEX($C$27:$J$27,1,G$78-$S91+1-$B$22),0)*$U91*G$79 -> 0 | H91: =IF(AND(H$78-$S91+1-$B$22>=1,H$78-$S91+1-$B$22<=8),INDEX($C$27:$J$27,1,H$78-$S91+1-$B$22),0)*$U91*H$79 -> 0 | I91: =IF(AND(I$78-$S91+1-$B$22>=1,I$78-$S91+1-$B$22<=8),INDEX($C$27:$J$27,1,I$78-$S91+1-$B$22),0)*$U91*I$79 -> 0 | J91: =IF(AND(J$78-$S91+1-$B$22>=1,J$78-$S91+1-$B$22<=8),INDEX($C$27:$J$27,1,J$78-$S91+1-$B$22),0)*$U91*J$79 -> 0 | ... Q91: =IF(AND(Q$78-$S91+1-$B$22>=1,Q$78-$S91+1-$B$22<=8),INDEX($C$27:$J$27,1,Q$78-$S91+1-$B$22),0)*$U91*Q$79 -> 0 | S91: =$B$20+4 -> 2031 | T91: =IF($S91>$B$20+Scenarios!$D$8-1,0,$B$19*(1+$B$21*Scenarios!$D$7)^4) -> 0 | U91: =IFERROR($T91/INDEX($C$79:$Q$79,1,MATCH($S91,$C$78:$Q$78,0)),0) -> 0 | V91: =SUMPRODUCT(($C$25:$J$25<=$Q$78-$S91+1-$B$22)*$C$27:$J$27)*$U91 -> 0 | W91: =$U91-$V91 -> 0
A92: Refresher grant 6 | C92: =IF(AND(C$78-$S92+1-$B$22>=1,C$78-$S92+1-$B$22<=8),INDEX($C$27:$J$27,1,C$78-$S92+1-$B$22),0)*$U92*C$79 -> 0 | D92: =IF(AND(D$78-$S92+1-$B$22>=1,D$78-$S92+1-$B$22<=8),INDEX($C$27:$J$27,1,D$78-$S92+1-$B$22),0)*$U92*D$79 -> 0 | E92: =IF(AND(E$78-$S92+1-$B$22>=1,E$78-$S92+1-$B$22<=8),INDEX($C$27:$J$27,1,E$78-$S92+1-$B$22),0)*$U92*E$79 -> 0 | F92: =IF(AND(F$78-$S92+1-$B$22>=1,F$78-$S92+1-$B$22<=8),INDEX($C$27:$J$27,1,F$78-$S92+1-$B$22),0)*$U92*F$79 -> 0 | G92: =IF(AND(G$78-$S92+1-$B$22>=1,G$78-$S92+1-$B$22<=8),INDEX($C$27:$J$27,1,G$78-$S92+1-$B$22),0)*$U92*G$79 -> 0 | H92: =IF(AND(H$78-$S92+1-$B$22>=1,H$78-$S92+1-$B$22<=8),INDEX($C$27:$J$27,1,H$78-$S92+1-$B$22),0)*$U92*H$79 -> 0 | I92: =IF(AND(I$78-$S92+1-$B$22>=1,I$78-$S92+1-$B$22<=8),INDEX($C$27:$J$27,1,I$78-$S92+1-$B$22),0)*$U92*I$79 -> 0 | J92: =IF(AND(J$78-$S92+1-$B$22>=1,J$78-$S92+1-$B$22<=8),INDEX($C$27:$J$27,1,J$78-$S92+1-$B$22),0)*$U92*J$79 -> 0 | ... Q92: =IF(AND(Q$78-$S92+1-$B$22>=1,Q$78-$S92+1-$B$22<=8),INDEX($C$27:$J$27,1,Q$78-$S92+1-$B$22),0)*$U92*Q$79 -> 0 | S92: =$B$20+5 -> 2032 | T92: =IF($S92>$B$20+Scenarios!$D$8-1,0,$B$19*(1+$B$21*Scenarios!$D$7)^5) -> 0 | U92: =IFERROR($T92/INDEX($C$79:$Q$79,1,MATCH($S92,$C$78:$Q$78,0)),0) -> 0 | V92: =SUMPRODUCT(($C$25:$J$25<=$Q$78-$S92+1-$B$22)*$C$27:$J$27)*$U92 -> 0 | W92: =$U92-$V92 -> 0
